Workbook
Name Addr_Country: Iniciar!$Q$48
Name Addr_Mail: 'Modelo Energético'!$G$1307
Name Addr_Manufacturer: 'Modelo Energético'!$E$1307
Name Addr_Model: 'Modelo Energético'!$F$1307
Name Addr_ProductType: 'Modelo Energético'!$C$1307
Name Addr_Province: Iniciar!$R$48
Name Addr_PVManufacturer: 'Modelo Energético'!$Z$1329
Name Addr_PVModel: 'Modelo Energético'!$AA$1329
Name Addr_PVType: 'Modelo Energético'!$AD$1329
Name Addr_Region: 'Modelo Energético'!$AB$1329
Name Addr_Station: Iniciar!$S$48
Name Addr_type: 'Modelo Energético'!$S$474
Name Addr_Web: 'Modelo Energético'!$H$1307
Name AfterIRR: 'Análise Financeira'!$AA$63
Name AnalType: Iniciar!$D$28
Name Ann_costs: 'Análise Financeira'!$K$22
Name Ann_heat_deg_days: 'Carga e Rede'!$AI$5
Name Ann_sav: 'Análise Financeira'!$K$36
Name AnnEarthTempAmp: Iniciar!$D$54
Name AnnEarthTempAmpUnit: Iniciar!$V$52
Name AtmosPressure_Jan: Iniciar!$G$58
Name AvgAtmosPressUnit: Iniciar!$T$54
Name AvgDailyRadiation_Jan: Iniciar!$F$58
Name AvgDailyRadUnit: Iniciar!$T$55
Name AvgTemp_Jan: Iniciar!$D$58
Name avgTempUnit: Iniciar!$R$50
Name AvgWindSpeed_Jan: Iniciar!$H$58
Name AvgWindSpeedUnit: Iniciar!$T$53
Name BatMismatch: 'Modelo Energético '!$D$266
Name BatTemp: 'Modelo Energético '!$R$264:$R$266
Name BatTempCtrl: 'Modelo Energético '!$D$263
Name BatTempIndex: 'Modelo Energético '!$M$264
Name Bench_area: 'Modelo Energético '!$A$183:$A$188
Name Bench_ref: 'Modelo Energético '!$C$181
Name Bench_ref2: 'Modelo Energético '!$J$1173
Name CA_all: 'Análise de Custos'!$I$1:$M$1
Name CA_Balance: 'Análise de Custos'!$D$100
Name CA_BPlist_sort: 'Análise de Custos'!$H$261
Name CA_BPlist1: 'Análise de Custos'!$F$261:$F$272
Name CA_BPlist2: 'Análise de Custos'!$H$261:$H$272
Name CA_Canada: 'Análise de Custos'!$K$1:$L$1
Name CA_CapacityUnit: 'Análise de Custos'!$E$46,'Análise de Custos'!$D$74:$D$78,'Análise de Custos'!$D$87:$D$89
Name CA_CoolingHelp: 'Análise de Custos'!$L$87
Name CA_Costcells: 'Análise de Custos'!$F$11:$G$20,'Análise de Custos'!$F$23:$G$213,'Análise de Custos'!$G$215:$G$227,'Análise de Custos'!$F$254:$G$256
Name CA_Costcells2: 'Análise de Custos'!$G$229:$G$251
Name CA_Costcells3: 'Análise de Custos'!$F$215:$F$224
Name CA_Costcells31: 'Análise de Custos'!$F$229:$F$250
Name CA_country1: 'Análise de Emissões'!$D$341:$D$589
Name CA_country2: 'Análise de Emissões'!$C$341:$C$589
Name CA_country2sort: 'Análise de Emissões'!$C$341
Name CA_CS: 'Análise de Custos'!$O$14
Name CA_fuelBC: 'Análise de Custos'!$O$227
Name CA_fuelPC: 'Análise de Custos'!$O$214
Name CA_Heatinghelp: 'Análise de Custos'!$L$74
Name CA_HS: 'Análise de Custos'!$O$12
Name CA_IC: 'Análise de Custos'!$O$15
Name CA_link: 'Análise de Custos'!$D$258
Name CA_Month: 'Análise de Custos'!$E$197
Name CA_new1: 'Análise de Custos'!$M$1:$M$1
Name CA_OMS: 'Análise de Custos'!$O$203

Sheet Parameter
A1: PARAMETERS TABLE
A2: MODULE | B2: NAME | C2: VALUE | D2: (comments)
A3: model version | B3: modelVersion | C3: =Iniciar!B80 -> RETScreen4 2012-06-01 | D3: Model version take from Start!B80
A4: Start worksheet
B5: unit | C5: 1 | D5: project name
B6: projectName | C6: =IF(TRIM(Iniciar!D14) = "","RETScreen",Iniciar!D14) -> Estudo de Caso Foto Voltaico | D6: project location
B7: projectLocation | C7: =Iniciar!D15 -> 0
B8: preparedFor | C8: =Iniciar!D17 -> 0
B9: preparedBy | C9: =Iniciar!D18 -> 0
B10: projectType | C10: =EM_Projtype_V -> Produção de eletricidade
B11: gridType | C11: =Set_GridType -> Rede Central
B12: heatingValueRef | C12: =Iniciar!D30 -> Poder Calorífico Inferior (PCI) | D12: A copy of the language value show in the start sheet, use in case of a DB error
B13: languageShow | C13: Portuguese - Português | D13: The value of the language as see in the start sheet
B14: language | C14: Portuguese
B15: userManual | C15: =OnlineManualLanguage -> English - Anglais | D15: Name or symbol of the currency
B16: Currency_name | C16: =Currency_name -> Euro | D16: The name of the technology to show in the Project Form
B17: projectTech | C17: 41061
B18: SaveDate | C18: 39758
B19: ActiveMap | C19: Public release 2008-12-09
B20: projectCurrency | C20: =IF(Iniciar!D37=Language!C80,0,1) -> 0 | D20: 0 --> metric 1-->imperial
B21: elevationUnitFactor | C21: =Iniciar!N51 -> 1
B22: heatingTempUnitFactor | C22: =Iniciar!N52 -> 1
B23: coolongTempUnitFactor | C23: =Iniciar!N53 -> 1
B24: earthTempAmpUnitFactor | C24: =Iniciar!N54 -> 1
B25: airTempUnitFactor | C25: =Iniciar!O56 -> 1
B26: earthTempUnitFactor | C26: =Iniciar!S56 -> 1
B27: solarUnitFactor | C27: =Iniciar!P56 -> 1
B28: atmPressureUnitFactor | C28: =Iniciar!Q56 -> 1
B29: windSpeedUnitFactor | C29: =Iniciar!R56 -> 1
B30: heatingDegreeDaysUnitFactor | C30: =Iniciar!T56 -> 1
B31: coolingDegreeDaysUnitFactor | C31: =Iniciar!U56 -> 1
B32: lastHelpFilePath
B33: isFirstRun | C33: TRUE
A36: hydro form | B36: hydroPastedCountry | C36: 35 | D36: the last Country ID pasted by the hydro form
B37: hydroPastedProvince | D37: the last provice ID pasted by the hydro form
B38: hydroPastedCurveType | C38: AA1 | D38: the last curve type ID pasted by the hydro form
B39: hydroPastedGaugeName | C39: 207 | D39: the last gauge ID pasted by the hydro form
A41: Others unit … | B41: lastRETFilePath | D41: The last valid path for the user's .ret file (note: default RETScreen.ret file in defaultDBPath)
B42: defaultRETName | D42: the name of the .ret file with all the default projects/case studies
B43: defaultRETPath | D43: Last valid path for the default Project DB file… should be the same as defaultDBPath when first installed
B44: casestudyHyperlink | D44: Link to the website for the currently opened case study

Sheet Iniciar
W1: 30000
A2: =Language!C848 -> Software de Análise de Projetos de Energia Limpa | N2: =IF(ISERROR(SUM(N3:O28)+P20),1,SUM(N3:O28)+P20) -> 20933 | O2: 20933 | W2: 30000
P3: =IF(ISERROR(VLOOKUP(Set_OpenClose,N149:R368,5,FALSE)),0,VLOOKUP(Set_OpenClose,N149:R368,5,FALSE)) -> 0 | Q3: Fuel calc source | W3: 30000
C4: =Language!C1910 -> Informação sobre o projeto | D4: =Language!C1962 -> Veja banco de Dados do projeto | P4: =IF(ISERROR(VLOOKUP(Set_OpenClose,N149:O368,2,FALSE)),0,VLOOKUP(Set_OpenClose,N149:O368,2,FALSE)) -> 0 | Q4: 0 | R4: EE_type | W4: 6000000
R5: 1 | S5: =Set_T1 -> Sistema à biomassa | W5: 31000
W6: 30000
C7: =C32 -> Idioma | D7: Portuguese - Português | W7: 30000
W8: 30000
C9: =VLOOKUP($D$7,$H$83:$K$118,2,FALSE) -> Observaçao importante | W9: 30000
B10: =VLOOKUP($D$7,$H$83:$K$118,4,FALSE) -> O software RETScreen utiliza macros do Excel. Devido aos parâmetros de segurança de macros definidos em alguns computadores, você poderá ter que habilitar macros quando abrir o arquivo RETScreen no Excel. | W10: 30000
W11: 30000
B12: =VLOOKUP($D$7,$H$83:$K$118,3,FALSE) -> Além disso, em alguns computadores, o nível de segurança de macros do Excel é automaticamente definido como "muito alto" . Neste caso você terá que redefinir o nível de segurança para "médio" ou "alto" usando o Menu em "Ferramentas, Macro, Nível de segurança..." antes de usar o RETScreen. Caso isto não seja feito o software não funcionará corretamente. | W12: 30000
W13: 30000
C14: =Language!C181 -> Nome do Projeto | D14: Estudo de Caso Foto Voltaico | R14: 2 | S14: =Set_T2 -> Fotovoltaica | W14: 31002
C15: =Language!C182 -> Localização do Projeto | R15: 3 | S15: =Set_T3 -> Bomba de calor | W15: 31004
R16: 4 | S16: =Equip_PowerType -> Fotovoltaica | W16: 31000
C17: =Language!C1904 -> Preparado para | R17: 5 | S17: =Equip_PowerType&" - "&Equip_CoolType -> Fotovoltaica - Bomba de calor | W17: 31006
C18: =Language!C1903 -> Preparado por | P18: RETScreen4.xls - 1:27:08 PM - 6/1/2012 | R18: 6 | S18: =Equip_HeatingType&" - "&Equip_CoolType -> Sistema à biomassa - Bomba de calor | W18: 31008
R19: 7 | S19: =Equip_PowerType&" - "&Equip_CoolType -> Fotovoltaica - Bomba de calor | W19: 31000
C20: =Language!C1911 -> Tipo de projeto | D20: Produção de eletricidade | N20: =IF(D20="",1,IF(MATCH(D20,B107:B116,0)=10,2,MATCH(D20,B107:B116,0))) -> 2 | P20: =IF(D20="",1,MATCH(D20,B107:B116,0)) -> 2 | R20: 8 | S20: =D22 -> Industrial | W20: 31010
Q21: =VLOOKUP(P20,R5:S22,2) -> Fotovoltaica | R21: 9 | S21: =IF(EE_UserCode=1,'Modelo Energético '!D933,IF(EE_UserCode=2,'Modelo Energético '!D934,G111)) -> Energia | W21: 31000
C22: =Language!C1647 -> Tipo de instalação | D22: Industrial | N22: =IF(D22="",1,MATCH(D22,G107:G111,0)) -> 4 | P22: =IF(HideCode_projectType=8,1,0) -> 0 | R22: 10 | S22: =Equip_PowerType&" - "&Equip_PowerTypeInter -> Fotovoltaica - Turbina à gas | W22: 31012
C23: =Language!C2015 -> Tecnologia | D23: Sistema à biomassa | N23: =IF(OR(HideCode_projectType<>1,D23=""),0,MATCH(D23,C107:C114,0)) -> 0 | W23: 31014
C24: =$C$23 -> Tecnologia | D24: Fotovoltaica | N24: =IF(OR(HideCode_projectType<>2,D24=""),0,IF(P20=10,0,MATCH(D24,D107:D121,0))) -> 9 | W24: 31014
C25: =$C$23 -> Tecnologia | D25: Bomba de calor | N25: =IF(OR(HideCode_projectType<>3,D25=""),0,MATCH(D25,E107:E112,0)) -> 0 | W25: 31014
C26: =Language!C586 -> Tipo de grid | D26: Rede Central | N26: =O26 -> 1 | O26: =IF(OR(N20=1,N20=3,N20=6,N20>7),0,IF(Set_GridType="",1,MATCH(Set_GridType,LN_GridType,0))) -> 1 | W26: 31016
W27: 31000
C28: =Language!C1476 -> Tipo de análise | D28: Método 2 | N28: =IF(D28="",2,MATCH(D28,E127:E128,0)) -> 2 | O28: =Q28+N28 -> 20912 | Q28: =N20*10000+(N23+N24+N25)*100+N26*10 -> 20910 | W28: 31018
W29: 31000
C30: =Language!C1723 -> Poder calorífico de referência | D30: Poder Calorífico Inferior (PCI) | W30: 31020
C31: =Language!C1972 -> Ver parâmetros | N31: TRUE | W31: 31022
C32: =Language!C177 -> Idioma | D32: Portuguese - Português | N32: =IF(D32="",1,MATCH(D32,H83:H118,0)) -> 23 | W32: 31024
C33: =Language!C2614 -> Manual do usuário | D33: English - Anglais | N33: =IF(OnlineManualLanguage=B125,"RETScreen4F.chm","RETScreen4.chm") -> RETScreen4.chm | W33: 31026
W34: 31000
C35: =Language!C495 -> Moeda | D35: Euro | N35: =IF(Currency_name="",1,MATCH(Currency_name,currency_list,0)) -> 2 | O35: 1 | W35: 31028
C36: =Language!C497 -> Símbolo | W36: 31030
C37: =Language!C178 -> Unidades | D37: Unidades métricas | N37: =IF(OR(D37=B127,D37=""),TRUE,FALSE) -> TRUE | W37: 31032
N38: =IF(OR(D30=C127,D30=""),1,2) -> 2 | W38: 31000
W39: 32000
B40: =Language!C179 -> Condições de Referência do site | D40: =Language!C1964 -> Selecionar local de dados climáticos | W40: 32000
O41: Location ID | W41: 32000
C42: =Language!C1538 -> Localização dos dados climáticos | D42: Coimbra | O42: 160 | P42: 268 | Q42: 085490 | W42: 32002
W43: 32000
C44: =Language!C1970 -> Mostrar dado | N44: FALSE | W44: 32004
W45: 32000
W46: 30000
W47: 33000
C48: =Language!C180 -> Unidade | D48: =Language!C1538 -> Localização dos dados climáticos | E48: =C15 -> Localização do Projeto | W48: 33000
B49: =Language!C1133 -> Latitude | C49: =Language!C2173 -> ˚N | D49: 40.2 | E49: =Latitude -> 40.2 | O49: rad | P49: =E49*PI()/180 -> 0.70162236 | W49: 33002
B50: =Language!C1134 -> Longitude | C50: =Language!C2172 -> ˚E | D50: -8.42 | E50: =Longitude -> -8.42 | W50: 33004
B51: =Language!C1151 -> Elevação | C51: m | D51: 140 | E51: =Elevation -> 140 | N51: =IF(C51="",1,VLOOKUP(C51,B87:C88,2,FALSE)) -> 1 | O51: m | P51: =N51*D51 -> 140 | W51: 33006
B52: =Language!C1132 -> Temperatura para projeto de aquecimento | C52: °C | D52: 3.3 | N52: =IF(C52="",1,VLOOKUP(C52,$B$84:$C$85,2,FALSE)) -> 1 | O52: °C | P52: =N52*(D52+40)-40 -> 3.3 | W52: 33008
B53: =Language!C1130 -> Temperatura para projeto de refrigeração | C53: °C | D53: 31.3 | N53: =IF(C53="",1,VLOOKUP(C53,$B$84:$C$85,2,FALSE)) -> 1 | O53: °C | P53: =N53*(D53+40)-40 -> 31.3 | W53: 33010
B54: =Language!C1150 -> Amplitude da Temperatura do Solo | C54: °C | D54: 18.43 | N54: =IF(C54="",1,VLOOKUP(C54,$B$84:$C$85,2,FALSE)) -> 1 | O54: °C | P54: =N54*D54 -> 18.43 | W54: 33012
W55: 33000
B56: =Language!C250 -> Mês | D56: =Language!C1144 -> Temperatura do Ar | E56: =Language!C1145 -> Humidade relativa | F56: =Language!C1146 -> Radiação solar diária - horizontal | G56: =Language!C1147 -> Pressão Atmosférica | H56: =Language!C1148 -> Velocidade do Vento | I56: =Language!C1149 -> Temperatura do Solo | J56: =Language!C1136 -> Graus-dia para aquecimento | K56: =Language!C1563 -> Refrigeração graus-dias | O56: =IF(D57="",1,VLOOKUP(D57,B84:C85,2,FALSE)) -> 1 | P56: =IF(F57="",1,VLOOKUP(F57,B90:C91,2,FALSE)) -> 1 | Q56: =IF(G57="",1,VLOOKUP(G57,B99:C101,2,FALSE)) -> 1 | R56: =IF(H57="",1,VLOOKUP(H57,B93:C94,2,FALSE)) -> 1 | S56: =IF(I57="",1,VLOOKUP(I57,B84:C85,2,FALSE)) -> 1 | T56: =IF(J57="",1,VLOOKUP(J57,B96:C97,2,FALSE)) -> 1 | U56: =IF(K57="",1,VLOOKUP(K57,B96:C97,2,FALSE)) -> 1 | W56: 33000 | X56: Average day of month | Y56: Declination | Z56: Sunrise/Sunset hour angle | AA56: Day length | AB56: Monthly average daily radiation on horizontal (MJ/m2/d) | AC56: Monthly average daily extrater. radiation on horizontal (MJ/m2/d) | AD56: Monthly average daily clearness index (KT bar) ( ) | AE56: Average albedo | AF56: a (DB 2.24.4b) | AG56: b (DB 2.24.4c) | AH56: c (DB 2.24.4d)
D57: °C | E57: % | F57: kWh/m²/d | G57: kPa | H57: m/s | I57: °C | J57: °C-d | K57: °C-d | O57: °C | P57: kWh/m²/d | Q57: kPa | R57: m/s | S57: °C | T57: °C-d | U57: °C-d | W57: 33000 | X57: - | Y57: rad | Z57: rad | AA57: h
B58: =Language!C251 -> Janeiro | D58: 10 | E58: 0.8 | F58: 1.98 | G58: 100.38 | H58: 3 | I58: 7.81 | J58: 248 | K58: 0 | O58: =$O$56*(D58+40)-40 -> 10 | P58: =F58*$P$56 -> 1.98 | Q58: =G58*$Q$56 -> 100.38 | R58: =H58*$R$56 -> 3 | S58: =$S$56*(I58+40)-40 -> 7.81 | T58: =J58*$T$56 -> 248 | U58: =K58*$U$56 -> 0 | V58: 31 | W58: 33000 | X58: 17 | Y58: -0.36506987 | Z58: =getsunsethourangle($P$49,Y58) -> 1.2419173 | AA58: =2*Z58*180/PI()/15 -> 9.4875491 | AB58: =P58*3.6 -> 7.128 | AC58: =GetHExtra_integ(Z58, $P$49, Y58, GetNExtra(X58))/1000000 -> 15.088111 | AD58: =IF(AC58>0,MIN(AB58/AC58,1),1) -> 0.47242495 | AE58: =GetAlbedo(O58) -> 0.2 | AF58: =2.943+AD58*(-9.271+4.031*AD58) -> -0.53719162 | AG58: =-4.345+AD58*(8.853-3.602*AD58) -> -0.9665355 | AH58: =-0.17+AD58*(-0.306+2.936*AD58) -> 0.3407101
B59: =Language!C252 -> Fevereiro | D59: 11 | E59: 0.776 | F59: 2.9 | G59: 100.14 | H59: 3.1 | I59: 9.26 | J59: 196 | K59: 28 | O59: =$O$56*(D59+40)-40 -> 11 | P59: =F59*$P$56 -> 2.9 | Q59: =G59*$Q$56 -> 100.14 | R59: =H59*$R$56 -> 3.1 | S59: =$S$56*(I59+40)-40 -> 9.26 | T59: =J59*$T$56 -> 196 | U59: =K59*$U$56 -> 28 | V59: 28 | W59: 33000 | X59: 47 | Y59: -0.22610056 | Z59: =getsunsethourangle($P$49,Y59) -> 1.3751607 | AA59: =2*Z59*180/PI()/15 -> 10.505454 | AB59: =P59*3.6 -> 10.44 | AC59: =GetHExtra_integ(Z59, $P$49, Y59, GetNExtra(X59))/1000000 -> 20.4244 | AD59: =IF(AC59>0,MIN(AB59/AC59,1),1) -> 0.51115332 | AE59: =GetAlbedo(O59) -> 0.2 | AF59: =2.943+AD59*(-9.271+4.031*AD59) -> -0.74269198 | AG59: =-4.345+AD59*(8.853-3.602*AD59) -> -0.76088197 | AH59: =-0.17+AD59*(-0.306+2.936*AD59) -> 0.44069847
B60: =Language!C253 -> Março | D60: 12.5 | E60: 0.733 | F60: 4.38 | G60: 100.16 | H60: 2.8 | I60: 12.96 | J60: 170.5 | K60: 77.5 | O60: =$O$56*(D60+40)-40 -> 12.5 | P60: =F60*$P$56 -> 4.38 | Q60: =G60*$Q$56 -> 100.16 | R60: =H60*$R$56 -> 2.8 | S60: =$S$56*(I60+40)-40 -> 12.96 | T60: =J60*$T$56 -> 170.5 | U60: =K60*$U$56 -> 77.5 | V60: 31 | W60: 33000 | X60: 75 | Y60: -0.042197433 | Z60: =getsunsethourangle($P$49,Y60) -> 1.5351116 | AA60: =2*Z60*180/PI()/15 -> 11.727389 | AB60: =P60*3.6 -> 15.768 | AC60: =GetHExtra_integ(Z60, $P$49, Y60, GetNExtra(X60))/1000000 -> 27.346711 | AD60: =IF(AC60>0,MIN(AB60/AC60,1),1) -> 0.57659585 | AE60: =GetAlbedo(O60) -> 0.2 | AF60: =2.943+AD60*(-9.271+4.031*AD60) -> -1.0624627 | AG60: =-4.345+AD60*(8.853-3.602*AD60) -> -0.43792786 | AH60: =-0.17+AD60*(-0.306+2.936*AD60) -> 0.62967237
B61: =Language!C254 -> Abril | D61: 14 | E61: 0.747 | F61: 5.45 | G61: 99.88 | H61: 2.7 | I61: 15.42 | J61: 120 | K61: 120 | O61: =$O$56*(D61+40)-40 -> 14 | P61: =F61*$P$56 -> 5.45 | Q61: =G61*$Q$56 -> 99.88 | R61: =H61*$R$56 -> 2.7 | S61: =$S$56*(I61+40)-40 -> 15.42 | T61: =J61*$T$56 -> 120 | U61: =K61*$U$56 -> 120 | V61: 30 | W61: 33000 | X61: 105 | Y61: 0.16432089 | Z61: =getsunsethourangle($P$49,Y61) -> 1.711388 | AA61: =2*Z61*180/PI()/15 -> 13.074042 | AB61: =P61*3.6 -> 19.62 | AC61: =GetHExtra_integ(Z61, $P$49, Y61, GetNExtra(X61))/1000000 -> 34.572508 | AD61: =IF(AC61>0,MIN(AB61/AC61,1),1) -> 0.56750294 | AE61: =GetAlbedo(O61) -> 0.2 | AF61: =2.943+AD61*(-9.271+4.031*AD61) -> -1.0200976 | AG61: =-4.345+AD61*(8.853-3.602*AD61) -> -0.4809551 | AH61: =-0.17+AD61*(-0.306+2.936*AD61) -> 0.60191105
B62: =Language!C255 -> Maio | D62: 16.4 | E62: 0.743 | F62: 6.07 | G62: 99.95 | H62: 2.5 | I62: 19.62 | J62: 49.6 | K62: 198.4 | O62: =$O$56*(D62+40)-40 -> 16.4 | P62: =F62*$P$56 -> 6.07 | Q62: =G62*$Q$56 -> 99.95 | R62: =H62*$R$56 -> 2.5 | S62: =$S$56*(I62+40)-40 -> 19.62 | T62: =J62*$T$56 -> 49.6 | U62: =K62*$U$56 -> 198.4 | V62: 31 | W62: 33000 | X62: 135 | Y62: 0.32798083 | Z62: =getsunsethourangle($P$49,Y62) -> 1.8624686 | AA62: =2*Z62*180/PI()/15 -> 14.228212 | AB62: =P62*3.6 -> 21.852 | AC62: =GetHExtra_integ(Z62, $P$49, Y62, GetNExtra(X62))/1000000 -> 39.678766 | AD62: =IF(AC62>0,MIN(AB62/AC62,1),1) -> 0.55072277 | AE62: =GetAlbedo(O62) -> 0.2 | AF62: =2.943+AD62*(-9.271+4.031*AD62) -> -0.94016635 | AG62: =-4.345+AD62*(8.853-3.602*AD62) -> -0.56192196 | AH62: =-0.17+AD62*(-0.306+2.936*AD62) -> 0.55195462
B63: =Language!C256 -> Junho | D63: 19.6 | E63: 0.747 | F63: 6.42 | G63: 100.01 | H63: 2.4 | I63: 24.53 | J63: 0 | K63: 288 | O63: =$O$56*(D63+40)-40 -> 19.6 | P63: =F63*$P$56 -> 6.42 | Q63: =G63*$Q$56 -> 100.01 | R63: =H63*$R$56 -> 2.4 | S63: =$S$56*(I63+40)-40 -> 24.53 | T63: =J63*$T$56 -> 0 | U63: =K63*$U$56 -> 288 | V63: 30 | W63: 33000 | X63: 162 | Y63: 0.40292516 | Z63: =getsunsethourangle($P$49,Y63) -> 1.9392881 | AA63: =2*Z63*180/PI()/15 -> 14.81507 | AB63: =P63*3.6 -> 23.112 | AC63: =GetHExtra_integ(Z63, $P$49, Y63, GetNExtra(X63))/1000000 -> 41.760126 | AD63: =IF(AC63>0,MIN(AB63/AC63,1),1) -> 0.55344661 | AE63: =GetAlbedo(O63) -> 0.2 | AF63: =2.943+AD63*(-9.271+4.031*AD63) -> -0.95329551 | AG63: =-4.345+AD63*(8.853-3.602*AD63) -> -0.54864113 | AH63: =-0.17+AD63*(-0.306+2.936*AD63) -> 0.55995138
B64: =Language!C257 -> Julho | D64: 21.8 | E64: 0.726 | F64: 6.81 | G64: 100.06 | H64: 2.4 | I64: 26.89 | J64: 0 | K64: 365.8 | O64: =$O$56*(D64+40)-40 -> 21.8 | P64: =F64*$P$56 -> 6.81 | Q64: =G64*$Q$56 -> 100.06 | R64: =H64*$R$56 -> 2.4 | S64: =$S$56*(I64+40)-40 -> 26.89 | T64: =J64*$T$56 -> 0 | U64: =K64*$U$56 -> 365.8 | V64: 31 | W64: 33000 | X64: 198 | Y64: 0.3697252 | Z64: =getsunsethourangle($P$49,Y64) -> 1.9044592 | AA64: =2*Z64*180/PI()/15 -> 14.548997 | AB64: =P64*3.6 -> 24.516 | AC64: =GetHExtra_integ(Z64, $P$49, Y64, GetNExtra(X64))/1000000 -> 40.660945 | AD64: =IF(AC64>0,MIN(AB64/AC64,1),1) -> 0.6029373 | AE64: =GetAlbedo(O64) -> 0.2 | AF64: =2.943+AD64*(-9.271+4.031*AD64) -> -1.1814286 | AG64: =-4.345+AD64*(8.853-3.602*AD64) -> -0.31664336 | AH64: =-0.17+AD64*(-0.306+2.936*AD64) -> 0.71283521
B65: =Language!C258 -> Agosto | D65: 21.8 | E65: 0.717 | F65: 6.23 | G65: 100.02 | H65: 2.4 | I65: 25.52 | J65: 0 | K65: 365.8 | O65: =$O$56*(D65+40)-40 -> 21.8 | P65: =F65*$P$56 -> 6.23 | Q65: =G65*$Q$56 -> 100.02 | R65: =H65*$R$56 -> 2.4 | S65: =$S$56*(I65+40)-40 -> 25.52 | T65: =J65*$T$56 -> 0 | U65: =K65*$U$56 -> 365.8 | V65: 31 | W65: 33000 | X65: 228 | Y65: 0.23483335 | Z65: =getsunsethourangle($P$49,Y65) -> 1.7743832 | AA65: =2*Z65*180/PI()/15 -> 13.555289 | AB65: =P65*3.6 -> 22.428 | AC65: =GetHExtra_integ(Z65, $P$49, Y65, GetNExtra(X65))/1000000 -> 36.494941 | AD65: =IF(AC65>0,MIN(AB65/AC65,1),1) -> 0.61455093 | AE65: =GetAlbedo(O65) -> 0.2 | AF65: =2.943+AD65*(-9.271+4.031*AD65) -> -1.2321024 | AG65: =-4.345+AD65*(8.853-3.602*AD65) -> -0.26475823 | AH65: =-0.17+AD65*(-0.306+2.936*AD65) -> 0.75079488
B66: =Language!C259 -> Setembro | D66: 20.8 | E66: 0.724 | F66: 4.7 | G66: 100.07 | H66: 2.2 | I66: 22.18 | J66: 0 | K66: 324 | O66: =$O$56*(D66+40)-40 -> 20.8 | P66: =F66*$P$56 -> 4.7 | Q66: =G66*$Q$56 -> 100.07 | R66: =H66*$R$56 -> 2.2 | S66: =$S$56*(I66+40)-40 -> 22.18 | T66: =J66*$T$56 -> 0 | U66: =K66*$U$56 -> 324 | V66: 30 | W66: 33000 | X66: 258 | Y66: 0.038691974 | Z66: =getsunsethourangle($P$49,Y66) -> 1.6035194 | AA66: =2*Z66*180/PI()/15 -> 12.249986 | AB66: =P66*3.6 -> 16.92 | AC66: =GetHExtra_integ(Z66, $P$49, Y66, GetNExtra(X66))/1000000 -> 29.916629 | AD66: =IF(AC66>0,MIN(AB66/AC66,1),1) -> 0.56557175 | AE66: =GetAlbedo(O66) -> 0.2 | AF66: =2.943+AD66*(-9.271+4.031*AD66) -> -1.0110141 | AG66: =-4.345+AD66*(8.853-3.602*AD66) -> -0.49017009 | AH66: =-0.17+AD66*(-0.306+2.936*AD66) -> 0.59607749
B67: =Language!C260 -> Outubro | D67: 17.4 | E67: 0.777 | F67: 3.55 | G67: 100.07 | H67: 2.4 | I67: 16.73 | J67: 18.6 | K67: 229.4 | O67: =$O$56*(D67+40)-40 -> 17.4 | P67: =F67*$P$56 -> 3.55 | Q67: =G67*$Q$56 -> 100.07 | R67: =H67*$R$56 -> 2.4 | S67: =$S$56*(I67+40)-40 -> 16.73 | T67: =J67*$T$56 -> 18.6 | U67: =K67*$U$56 -> 229.4 | V67: 31 | W67: 33000 | X67: 288 | Y67: -0.16754109 | Z67: =getsunsethourangle($P$49,Y67) -> 1.4273859 | AA67: =2*Z67*180/PI()/15 -> 10.904425 | AB67: =P67*3.6 -> 12.78 | AC67: =GetHExtra_integ(Z67, $P$49, Y67, GetNExtra(X67))/1000000 -> 22.424593 | AD67: =IF(AC67>0,MIN(AB67/AC67,1),1) -> 0.56991 | AE67: =GetAlbedo(O67) -> 0.2 | AF67: =2.943+AD67*(-9.271+4.031*AD67) -> -1.0313773 | AG67: =-4.345+AD67*(8.853-3.602*AD67) -> -0.46950703 | AH67: =-0.17+AD67*(-0.306+2.936*AD67) -> 0.60921273
B68: =Language!C261 -> Novembro | D68: 13 | E68: 0.822 | F68: 2.46 | G68: 100.14 | H68: 2.6 | I68: 11.8 | J68: 150 | K68: 90 | O68: =$O$56*(D68+40)-40 -> 13 | P68: =F68*$P$56 -> 2.46 | Q68: =G68*$Q$56 -> 100.14 | R68: =H68*$R$56 -> 2.6 | S68: =$S$56*(I68+40)-40 -> 11.8 | T68: =J68*$T$56 -> 150 | U68: =K68*$U$56 -> 90 | V68: 30 | W68: 33000 | X68: 318 | Y68: -0.33007588 | Z68: =getsunsethourangle($P$49,Y68) -> 1.2770667 | AA68: =2*Z68*180/PI()/15 -> 9.7560712 | AB68: =P68*3.6 -> 8.856 | AC68: =GetHExtra_integ(Z68, $P$49, Y68, GetNExtra(X68))/1000000 -> 16.320808 | AD68: =IF(AC68>0,MIN(AB68/AC68,1),1) -> 0.5426202 | AE68: =GetAlbedo(O68) -> 0.2 | AF68: =2.943+AD68*(-9.271+4.031*AD68) -> -0.90075761 | AG68: =-4.345+AD68*(8.853-3.602*AD68) -> -0.60174429 | AH68: =-0.17+AD68*(-0.306+2.936*AD68) -> 0.52842432
B69: =Language!C262 -> Dezembro | D69: 10.4 | E69: 0.805 | F69: 2.17 | G69: 100.31 | H69: 3 | I69: 9.15 | J69: 235.6 | K69: 12.4 | O69: =$O$56*(D69+40)-40 -> 10.4 | P69: =F69*$P$56 -> 2.17 | Q69: =G69*$Q$56 -> 100.31 | R69: =H69*$R$56 -> 3 | S69: =$S$56*(I69+40)-40 -> 9.15 | T69: =J69*$T$56 -> 235.6 | U69: =K69*$U$56 -> 12.4 | V69: 31 | W69: 33000 | X69: 344 | Y69: -0.40229189 | Z69: =getsunsethourangle($P$49,Y69) -> 1.2029895 | AA69: =2*Z69*180/PI()/15 -> 9.1901631 | AB69: =P69*3.6 -> 7.812 | AC69: =GetHExtra_integ(Z69, $P$49, Y69, GetNExtra(X69))/1000000 -> 13.634237 | AD69: =IF(AC69>0,MIN(AB69/AC69,1),1) -> 0.57296935 | AE69: =GetAlbedo(O69) -> 0.2 | AF69: =2.943+AD69*(-9.271+4.031*AD69) -> -1.0456462 | AG69: =-4.345+AD69*(8.853-3.602*AD69) -> -0.4550169 | AH69: =-0.17+AD69*(-0.306+2.936*AD69) -> 0.61854219
B70: =Language!C1152 -> Anual | D70: =SUMPRODUCT(D58:D69,$V$58:$V$69)/365 -> 15.751507 | E70: =SUMPRODUCT(E58:E69,$V$58:$V$69)/365 -> 0.7596137 | F70: =SUMPRODUCT(F58:F69,$V$58:$V$69)/365 -> 4.435589 | G70: =SUMPRODUCT(G58:G69,$V$58:$V$69)/365 -> 100.09964 | H70: =SUMPRODUCT(H58:H69,$V$58:$V$69)/365 -> 2.6227397 | I70: =SUMPRODUCT(I58:I69,$V$58:$V$69)/365 -> 16.866466 | J70: =SUM(J58:J69) -> 1188.3 | K70: =SUM(K58:K69) -> 2099.3 | O70: =SUMPRODUCT(O58:O69,$V$58:$V$69)/365 -> 15.751507 | P70: =SUMPRODUCT(P58:P69,$V$58:$V$69)/365 -> 4.435589 | Q70: =SUMPRODUCT(Q58:Q69,$V$58:$V$69)/365 -> 100.09964 | R70: =SUMPRODUCT(R58:R69,$V$58:$V$69)/365 -> 2.6227397 | S70: =SUMPRODUCT(S58:S69,$V$58:$V$69)/365 -> 16.866466 | T70: =SUM(T58:T69) -> 1188.3 | U70: =SUM(U58:U69) -> 2099.3 | W70: 33000
B71: =Language!C1804 -> Medido a | C71: m | H71: 10 | I71: 0 | N71: =IF(C71="",1,VLOOKUP(C71,B87:C88,2,FALSE)) -> 1 | O71: m | P71: =N71*H71 -> 10 | Q71: =N71*I71 -> 0 | W71: 33030
W72: 33000
W73: 30000
D74: =Language!C1554 -> Completar a planilha de Modelo Energético | W74: 30000
D75: =Language!C1554 -> Completar a planilha de Modelo Energético | W75: 30000
D76: =Language!C54 -> Completar planilha de Carga e Rede | W76: 30000
W77: 30000
W78: 30000
W79: 30000
B80: RETScreen4 2012-06-01 | F80: =Language!C51 -> © Minister of Natural Resources Canada 1997-2012. | L80: =Language!C52 -> NRCan/CanmetENERGY | W80: 30000
W81: 30000
N82: EndOfVisibleWorksheet
B83: Unit | C83: Conversion factor to metric | D83: unit name | H83: Arabic - العربية | I83: ملاحظة هامة | J83: بالاضافة ، بعض الحواسب يكون مستوى التامين لبرامج الماكرو في برنامج الاكسل موضوع على "عالي جدا" في هذه الحالة مطلوب منك ان تعيد وضع مستوى التامين على "متوسط" او "عالي" وذلك باستخدام مفتاح الادوات, لائحة الماكرو ومنها الى التامين وذلك قبل استخدام RETScreen والا فان البرنامج لن يعمل بصورة سليمة. | K83: البرمجية RETScreen تستعمل"الماكرو". ناتجة علي ثوابت حماية بعض الحواسيب، من المحتمل أنكم قمتم ب "نشط ماكرو" عند فتح ملف RETScreen في إكسال
B84: =Language!C1310 -> °C | C84: 1 | D84: celcius | H84: Bengali - বাংলা | I84: Important notice | J84: কিছু কম্পিউটারে এক্সেল ম্যাক্রো নিরাপত্তা স্তর(security level) স্বয়ংক্রিয় ভাবে "অতি উচ্চ" রাখা হয় | RETScreen ব্যবহারের আগে আপনাকে নিরাপত্তার স্তর "Tools,Macro,Security…" মেনু থেকে "মধ্যম" বা "উচ্চ" করতে হবে, না হলে RETScreen সঠিক ভাবে কাজ করবে না | | K84: The RETScreen software uses Microsoft Excel macros. Due to macro security settings on some computers you might have to "enable macros" when opening the RETScreen file in Excel.
B85: =Language!C1313 -> °F | C85: =5/9 -> 0.55555556 | D85: farenheit | H85: Bulgarian - Български | I85: Важно известие | J85: В допълнение, на някои компютри нивото на сигурност на макросите в Excel е настроено автоматично на "много високо". В този случай преди да използвате RETScreen следва да промените настройките на нивото на безопасност на "средно" или "високо" като използвате менюто "Tools, Macro, Security...". В противен случай програмата няма да работи правилно. | K85: Програмата RETScreen използва макроси за Microsoft Еxcel. Заради настройките на макро защитата на някои компютри може да се наложи да се избере опция "разреши макроси", когато отваряте RETScreen file в Excel.
H86: Chinese - 中文 | I86: 重要提示 | J86: 另外，部分电脑中的Excel程序的宏安全性被自动设置为“特高”。在这种情况下，使用RETScreen之前您需要通过选择“工具－宏－安全性…"菜单将其重新设置为“高“或“中”，否则本软件将不能正常运行。 | K86: RETScreen软件使用Microsoft Excel宏程序。由于部分电脑中的宏安全性设置，您在用Excel打开RETScreen文档时，可能需要“启用宏”。
B87: =Language!C1372 -> m | C87: 1 | D87: meter | H87: Croatian - Hrvatski | I87: Važna obavijest | J87: Dodatno, na nekim računalima, razina sigurnosti za makroe u Excelu je automatski postavljena na "vrlo visoka". Ako je ovo slučaj, sigurnosna razina treba se promijeniti na "srednje" ili "visoko" korištenjem menija "Tools - Macro - Security..." prije korištenja RETScreena. U protivnom softver neće imati svoju punu funkcionalnost. | K87: Softver RETScreen koristi Microsoft Excel makroe. Zbog postavki sigurnosti makroa na nekim računalima možda ćete morati "omogućiti" izvršavanje makroa pri otvaranju RETScreenovih datoteka u Excelu
B88: =Language!C1327 -> pe | C88: 0.3048 | D88: feet | H88: Czech - Česko | I88: Důležité upozornění | J88: Navíc je stupeň zabezpečení pro makra v Excelu často nastaven na "velmi vysoký". V tomto případě musíte nastavit stupeň zabezpečení na "střední" nebo "vysoký" předtím, než použijete RETScreen. Zvolte k tomu ve výběrovém menu "Nástroje, Makra, Zabezpečení...". Jinak software nebude fungovat bezchybně. | K88: Software RETScreen využívá Microsoft Excel Makra. Na základě zabezpečovacích nastavení makra na některých počítačích budete možná muset "aktivovat makra", když otevřete databázi RETScreen v Excelu.
F89: Croatian - Hrvatska | H89: Danish - Dansk | I89: Vigtig meddelelse | J89: Desuden er makro-sikkerhedsniveauet på nogle computere automatisk sat til "meget høj". Hvis dette er tilfældet er det nødvendigt at ændre sikkerhedsniveauet til "middel" eller "høj" ved hjælp af "Funktionner, Makro, Sikkerhed"-menuen før RETScreen anvendes. Ellers fungerer softwaren ikke rigtigt. | K89: RETScreen-software anvender Microsoft Excel makroer. På grund af sikkerhedsindstillinger på nogle computere er det måske nødvendigt at "Aktivere makroer", når RETScreen-filen åbnes i Excel.
B90: =Language!C2221 -> kWh/m²/d | C90: 1 | D90: kWhPerM2PerDay | F90: Indonesian - Bahasa Indonesia | H90: Dutch - Nederlands | I90: Belangrijke opmerking | J90: Daarnaast is op sommige computers het macro beveiligingsniveau in Excel automatisch op "heel hoog" gezet. In dit geval, moet u het beveiligingsniveau instellen op "gemiddeld" of "hoog" door het keuzemenu "Extra, Macro, Beveiliging..." te gebruiken voordat u RETScreen gaat starten. Anders zal de software niet goed werken. | K90: De RETScreen software gebruikt macro's van Microsoft Excel. Vanwege macro beveilingsinstellingen op sommige computers moet u misschien op "Macro's inschakelen" klikken als u het RETScreen bestand in Excel opent.
B91: =Language!C2243 -> MJ/m²/d | C91: =1/3.6 -> 0.27777778 | D91: mJPerM2PerDay | H91: English - Anglais | I91: Important notice | J91: In addition, on some computers, the Macro Security Level in Excel is automatically set to "very high." In this case, you will have to re-set the security level to "medium" or "high" by using the "Tools, Macro, Security..." menu selection before using RETScreen. Otherwise, the software will not function properly. | K91: The RETScreen software uses Microsoft Excel macros. Due to macro security settings on some computers you might have to "enable macros" when opening the RETScreen file in Excel.
H92: Farsi - پارسی | I92: Important notice | J92: In addition, on some computers, the Macro Security Level in Excel is automatically set to "very high." In this case, you will have to re-set the security level to "medium" or "high" by using the "Tools, Macro, Security..." menu selection before using RETScreen. Otherwise, the software will not function properly. | K92: The RETScreen software uses Microsoft Excel macros. Due to macro security settings on some computers you might have to "enable macros" when opening the RETScreen file in Excel.
B93: =Language!C2232 -> m/s | C93: =1 -> 1 | D93: meterPerSecond | H93: Finnish - Suomi | I93: Tärkeää | J93: Joissakin tietokoneissa on Makrojen suojaus-taso MS Excelissä asetettu tasolle "hyvin korkea". Tässä tapauksessa tulee suojaus asettaa tasolle "normaali" tai "korkea" valikosta "Työkalut - Makrot - Suojaustasot" ennen RETScreen ohjelman käyttöä. Ilman muutoksia ei ohjelma toimi oikein. | K93: RETScreen ohjelmisto käyttää MS Excel makroja. Makrojen suojausasetusten vuoksi joissakin tietokoneissa tulee makrot "ottaa käyttöön" avattaessa RETScreen tiedosto MS Excelissä.
B94: =Language!C2244 -> mph | C94: 0.44704 | D94: milePerHour | H94: French - Français | I94: Note importante | J94: De plus, sur certains ordinateurs, le niveau de sécurité des macros sélectionné par défaut est "très élevé". Dans ce cas, vous devrez sélectionner le niveau de sécurité "moyen" ou "élevé" à partir du menu d'Excel "Outils, Macro, Sécurité..." avant d'utiliser RETScreen. Ainsi, le logiciel fonctionnera correctement. | K94: Le logiciel RETScreen utilise des macros. Dû aux paramètres de sécurité de certains ordinateurs, vous aurez probablement à "activer les macros" lors de l'ouverture du fichier RETScreen dans Excel.
H95: German - Deutsch | I95: Wichtiger hinweis | J95: Zusätzlich ist die Sicherheitsstufe für Makros in Excel häufig auf "sehr hoch" gesetzt. In diesem Fall müssen Sie die Sicherheitsstufe auf "mittel" oder "hoch" setzen, bevor sie RETScreen benutzen. Wählen Sie dazu in der Menüauswahl "Extras, Makros, Sicherheit...". Ansonsten funktioniert die Software nicht einwandfrei. | K95: Die RETScreen Software benutzt Microsoft Excel Makros. Aufgrund von Makro-Sicherheitseinstellungen auf manchen Computern müssen Sie möglicherweise "Makros aktivieren" wenn Sie die RETScreen-Datei in Excel öffnen.
B96: =Language!C1311 -> °C-d | C96: 1 | D96: celciusDay | H96: Greek - Ελληνικά | I96: Σημαντική Σημείωση | J96: Επιπλέον, σε κάποιους υπολογιστές, το επίπεδο ασφαλείας Μακροεντολών στο Excel, έχει αυτομάτως ρυθμιστεί "πολύ υψηλό". Σε αυτή την περίπτωση, θα χρειαστεί να επανα-ρυθμίσετε το επίπεδο ασφαλείας σε "μέτριο" ή "υψηλό" με τη χρήση της επιλογής μενού "Εργαλεία, Μακροεντολές, Ασφάλεια...", πριν τη χρήση του RETScreen. Διαφορετικά, το λογισμικό δεν θα λειτουργήσει σωστά. | K96: Το λογισμικό RETScreen χρησιμοποιεί μακροεντολές του Microsoft Excell. Λόγω προδιαγραφών ασφάλειας των μακροεντολών σε κάποιους υπολογιστές πιθανώς να πρέπει να γίνει "ενεργοποίηση μακροεντολών" κατά το άνοιγμα ενός αρχείου RETScreen στο Excell.
B97: =Language!C1314 -> °F-d | C97: =5/9 -> 0.55555556 | D97: farenheitDay | H97: Hindi - हिन्दी | I97: Important notice | J97: इसके अतिरिक्त कुछ कम्प्यूटरों में एक्सेल में मैक्रो सुरक्षा स्तर अपने आप ही "अत्यंत उच्च" पर नियत होता है। ऐसे मामले में आपको RETScreen के उपयोग से पहले "औजार, मेक्रो, सुरक्षा..." मेनू में जा कर सुरक्षा स्तर को "‘मध्यम" या "उच्च" पर पुन:नियत करना होगा, अन्यथा, साफ्टवेयर ठीक से कार्य नहीं करेगा।. | K97: The RETScreen software uses Microsoft Excel macros. Due to macro security settings on some computers you might have to "enable macros" when opening the RETScreen file in Excel.
H98: Hungarian - Magyar | I98: Fontos figyelmeztetés | J98: Továbbá, néhány számítógépen a EXCEL Makró Biztonsági Szint beállítások automatikusan "nagyon magas"-ra vannak állítva. Ebben az esetben a RETScreen használata előtt át kell állítani a biztonsági szintet "közepes"-re vagy "magas"-ra, az "Eszközök, Makró, Biztonsági beállítások..." menü útvonalon. Ellenkező esetben a program nem fog megfelelően működni. | K98: A RETScreen szoftver Microsoft Excel makrókat használ. A makrók biztonsági beállításaitól függően néhány számítógépen a RETScreen használata előtt szükséges lehet a makrók futtatásának engedélyezése a RETScreen Excel fájl megnyitásakor.
B99: =Language!C1363 -> kPa | C99: 1 | D99: kiloPascal | H99: Indonesian - Bahasa Indonesia | I99: Pengumuman penting | J99: Selain itu, pada beberapa komputer, Level Macro Security di Excel secara otomatis diset sangat tinggi. Dalam kasus ini anda perlu mengatur ulang security level menjadi medium atau tinggi dengan menggunakan "Tools, Macro, Security..." menu sebelum menggunakan RETScreen. Kalau tidak, software tidak akan beroperasi dengan benar | K99: Perangkat lunak RETScreen menggunakan macros Microsoft Excel. Oleh karena setting keamanan terdapat pada beberapa komputer, mungkin anda harus lakukan "enable macros (perkenankan macros)" ketika membuka file (berkas) RETScreen di Excel.
B100: =Language!C2240 -> mBar | C100: 0.1 | D100: milibar | H100: Italian - Italiano | I100: Nota importante | J100: Inoltre, in alcuni computer, il livello di protezione macro di Excel potrebbe essere impostato su "Molto Elevata". In questo caso, affinché RETScreen funzioni correttamente, devi reimpostare il livello di sicurezza su "Media" o su "Elevata" utilizzando il menu "Strumenti, Macro, Protezione" di Excel prima di utilizzare RETScreen. | K100: Il software RETScreen utilizza le macro di Microsoft Excel. In base alle impostazioni di sicurezza delle macro, potrebbe essere necessario un "abilita macro" all'apertura del file RETScreen con Excel.
...

Sheet Carga e Rede
A1: =Language!C867&'Análise de Emissões'!B188 -> RETScreen Proj. Rede e Carga - Projeto produção de Eletricidade | BA1: 40000
U2: =IF(ISERROR(SUM(U3:V254)+HideCodeEM_1),7,SUM(U3:V254)+HideCodeEM_1) -> 20984 | V2: 80078 | W2: SI units | X2: SI values | Y2: IP units | Z2: IP values | BA2: 40000
BA3: 40000
A4: =Language!C243 -> Projeto do Sistema de Aquecimento | C4: =Language!C180 -> Unidade | BA4: 41000
AG5: =Language!C245 -> Graus-dias anual de aquecimento abaixo 18°C | AH5: =Language!C1311 -> °C-d | AI5: =SUM(Iniciar!T58:T69) -> 1188.3 | BA5: 41000
A6: =Language!C275 -> Sistema de Aquecimento para caso de referência | C6: Prédio individual - aquecimento ambiente | U6: =IF(C6="",1,MATCH(C6,LN_heatsystem,0)) -> 1 | V6: =HideCode_projectType -> 2 | AH6: =Language!C1339 -> h | AI6: =J336 -> 0 | BA6: 41200
BA7: 41200
B8: =Language!C276 -> Área de piso aquecido para o prédio | C8: m² | W8: m² | X8: =IF(C8=$D$260,D8,D8*$E$261) -> 0 | BA8: 41302
B9: =Language!C211 -> Tipo de Combustível | D9: Gas natural - m³ | BA9: 2010106
B10: =Language!C219 -> Eficiência Sazonal | C10: =$C$13 -> % | BA10: 2020208
B11: =Language!C277 -> Cálculo carga p/ aquecimento | BA11: 41400
B12: =Language!C278 -> Carga p/ aquecimento do prédio | C12: W/m² | W12: W/m² | X12: =IF(C12=$D$266,D12,D12*$E$267) -> 0 | BA12: 41402
B13: =Language!C246 -> Demanda base calor p/ rede água quente | C13: =Language!C1306 -> % | BA13: 41403
B14: =Language!C279 -> Carga de ponta p/ aquecimento do processo | C14: kW | W14: kWth | X14: =IF(C14=$D$269,D14,D14/$E$270) -> 0 | BA14: 41404
B15: =Language!C280 -> Características da carga de aquecimento do processo | D15: Padrão | U15: =IF(D15="",1,MATCH(D15,LN_SD,0)) -> 1 | BA15: 41406
B16: =Language!C281 -> Horas equivalentes à plena carga - aquecimento do processo | C16: =$AH$6 -> h | D16: =IF(HideCodeLN_HPT=2,AI6,H336) -> 0 | F16: =Language!C59 -> Completar as cargas mensais do processo | W16: =IF(U15=2,1,IF(D17=0,0,1)) -> 0 | BA16: 41408
B17: =B16 -> Horas equivalentes à plena carga - aquecimento do processo | C17: =$AH$6 -> h | BA17: 41408
B18: =Language!C282 -> Demanda aquecimento ambiente | C18: =IF(Unit=TRUE,Language!C1396,Language!C1382) -> MWh | D18: =IF(Unit=TRUE,X18,Z18) -> 0 | W18: MWh | X18: =IF(X12=0,0,IF(X8=0,"-",E335)) -> 0 | Y18: million Btu | Z18: =X18*$F$270 -> 0 | BA18: 41410
B19: =Language!C283 -> Demanda p/ aquecimento do processo | C19: =C18 -> MWh | D19: =IF(Unit=TRUE,X19,Z19) -> 0 | W19: MWh | X19: =G335+I335 -> 0 | Y19: million Btu | Z19: =X19*$F$270 -> 0 | BA19: 41412
B20: =Language!C284 -> Demanda total p/ aquecimento | C20: =C18 -> MWh | D20: =IF(Unit=TRUE,X20,Z20) -> 0 | W20: MWh | X20: =IF(HideCodeLN_HPT=2,X19,IF(HideCodeLN_HPT=1,X18,IF(HideCodeLN_HPT=3,X19+X18,0))) -> 0 | Y20: million Btu | Z20: =X20*$F$270 -> 0 | BA20: 41414
B21: =Language!C285 -> Carga total p/ aquecimento de ponta | C21: =IF(Unit=TRUE,Language!C1364,Language!C1383) -> kW | D21: =IF(Unit=TRUE,X21,Z21) -> 0 | W21: kW | X21: =IF(HideCodeLN_HPT=1,X8*X12/1000,IF(HideCodeLN_HPT=2,X14*W16,X8*X12/1000+X14*W16)) -> 0 | Y21: million Btu/h | Z21: =X21*$E$270 -> 0 | BA21: 41416
B22: =Language!C286 -> Consumo de combustível - anual | C22: =VLOOKUP($D$9,$E$340:$I$360,3,FALSE) -> m³ | D22: =IF(OR(D10="",D10=0),0,X$20/VLOOKUP($D$9,E340:I360,4,FALSE)*1000/D$10) -> 0 | BA22: 41420
B23: =Language!C212 -> Preço do combustível | C23: =VLOOKUP($D$9,$E$340:$I$360,5,FALSE) -> €/m³ | BA23: 2010108
B24: =Language!C287 -> Custo do combustível | D24: =IF(D$9=$E$344,D23*D22*1000,IF(D$9=$E$360,D23*D22,D23*D22)) -> 0 | BA24: 5097210
A25: =A52 -> Ações de eficiência energética do caso proposto | BA25: 41500
B26: =Language!C289 -> Ações de eficiência energética no uso final | C26: =$C$13 -> % | BA26: 41501
B27: =Language!C290 -> Carga líquida de aquecimento de ponta | C27: =C21 -> kW | D27: =IF(Unit=TRUE,X27,Z27) -> 0 | W27: kW | X27: =MAX(P230:P244) -> 0 | Y27: million Btu/h | Z27: =X27*$E$270 -> 0 | BA27: 41502
B28: =Language!C291 -> Demanda líquida de aquecimento | C28: =C18 -> MWh | D28: =IF(Unit=TRUE,X28,Z28) -> 0 | W28: MWh | X28: =(SUMPRODUCT(C321:C332,P230:P241)+P244*C333)/1000 -> 0 | Y28: million Btu | Z28: =X28*$F$270 -> 0 | BA28: 41504
BA29: 41000
B30: =IF(HideCodeLN_HPT>6,Language!C292,"") | F30: =IF(HideCodeLN_HPT>6,Language!C293,Language!C294) -> Zonas do Prédio | BA30: 41202
F31: 1 | G31: 2 | H31: 3 | I31: 4 | J31: 5 | K31: 6 | L31: 7 | M31: 8 | N31: 9 | O31: 10 | P31: 11 | Q31: 12 | R31: 13 | S31: 14 | BA31: 41302
B32: =IF(HideCodeLN_HPT>6,Language!C295,Language!C297) -> Área de piso aquecido por zona | C32: m² | D32: =IF(C32=$D$260,X32,Z32) -> 1 | F32: 1 | T32: 1 | W32: m² | X32: =SUM(AH32:AU32) -> 1 | Y32: ft² | Z32: =X32/$E$261 -> 10.76391 | AH32: =IF($C32=$D$260,F32,F32*$E$261) -> 1 | AI32: =IF($C32=$D$260,G32,G32*$E$261) -> 0 | AJ32: =IF($C32=$D$260,H32,H32*$E$261) -> 0 | AK32: =IF($C32=$D$260,I32,I32*$E$261) -> 0 | AL32: =IF($C32=$D$260,J32,J32*$E$261) -> 0 | AM32: =IF($C32=$D$260,K32,K32*$E$261) -> 0 | AN32: =IF($C32=$D$260,L32,L32*$E$261) -> 0 | AO32: =IF($C32=$D$260,M32,M32*$E$261) -> 0 | ... AU32: =IF($C32=$D$260,S32,S32*$E$261) -> 0 | BA32: 41302
B33: =Language!C296 -> Número de prédios no condomínio | C33: =Language!C1309 -> prédio | D33: =SUMIF(AH32:AU32,">0",F33:S33) -> 1 | F33: 1 | BA33: 41312
B34: =B9 -> Tipo de Combustível | F34: Gas natural - m³ | G34: Gas natural - m³ | H34: Gas natural - m³ | I34: Gas natural - m³ | J34: Gas natural - m³ | K34: Gas natural - m³ | L34: Gas natural - m³ | M34: Gas natural - m³ | N34: Gas natural - m³ | O34: Gas natural - m³ | P34: Gas natural - m³ | Q34: Gas natural - m³ | R34: Gas natural - m³ | S34: Gas natural - m³ | BA34: 2010106
B35: =B10 -> Eficiência Sazonal | C35: =$C$13 -> % | D35: - | BA35: 2020208
B36: =Language!C277 -> Cálculo carga p/ aquecimento | BA36: 41400
B37: =IF(HideCodeLN_HPT>6,Language!C298,Language!C299) -> Carga de aquecimento por zona | C37: W/m² | D37: - | AH37: =IF($C37=$D$266,F37,F37*$E$267) -> 0 | AI37: =IF($C37=$D$266,G37,G37*$E$267) -> 0 | AJ37: =IF($C37=$D$266,H37,H37*$E$267) -> 0 | AK37: =IF($C37=$D$266,I37,I37*$E$267) -> 0 | AL37: =IF($C37=$D$266,J37,J37*$E$267) -> 0 | AM37: =IF($C37=$D$266,K37,K37*$E$267) -> 0 | AN37: =IF($C37=$D$266,L37,L37*$E$267) -> 0 | AO37: =IF($C37=$D$266,M37,M37*$E$267) -> 0 | ... AU37: =IF($C37=$D$266,S37,S37*$E$267) -> 0 | BA37: 41402
B38: =B13 -> Demanda base calor p/ rede água quente | C38: =$C$13 -> % | BA38: 41403
B39: =Language!C279 -> Carga de ponta p/ aquecimento do processo | C39: kW | D39: =IF(C39=D269,X39,Z39) -> 0 | W39: kW | X39: =IF(U40=2,SUM(AH39:AU39),SUMIF(F42:S42,">0",AH39:AU39)) -> 0 | Y39: million Btu/h | Z39: =X39*$E$270 -> 0 | AG39: =AG44/X39*1000 -> #DIV/0! | AH39: =IF(OR(AH32=0,AH32=""),0,1)*IF($C39=$D$269,F39,F39/$E$270) -> 0 | AI39: =IF(OR(AI32=0,AI32=""),0,1)*IF($C39=$D$269,G39,G39/$E$270) -> 0 | AJ39: =IF(OR(AJ32=0,AJ32=""),0,1)*IF($C39=$D$269,H39,H39/$E$270) -> 0 | AK39: =IF(OR(AK32=0,AK32=""),0,1)*IF($C39=$D$269,I39,I39/$E$270) -> 0 | AL39: =IF(OR(AL32=0,AL32=""),0,1)*IF($C39=$D$269,J39,J39/$E$270) -> 0 | AM39: =IF(OR(AM32=0,AM32=""),0,1)*IF($C39=$D$269,K39,K39/$E$270) -> 0 | AN39: =IF(OR(AN32=0,AN32=""),0,1)*IF($C39=$D$269,L39,L39/$E$270) -> 0 | AO39: =IF(OR(AO32=0,AO32=""),0,1)*IF($C39=$D$269,M39,M39/$E$270) -> 0 | ... AU39: =IF(OR(AU32=0,AU32=""),0,1)*IF($C39=$D$269,S39,S39/$E$270) -> 0 | BA39: 41404
B40: =Language!C280 -> Características da carga de aquecimento do processo | D40: Padrão | U40: =IF(D40="",1,MATCH(D40,LN_SD,0)) -> 1 | AG40: Space kW elect | AH40: =IF(F34=$E$344,IF(OR(F32=0,F35=0,HideCodeLN_HPT=5,HideCodeLN_HPT=8),0,AH32*AH37/F35/1000),0) -> 0 | AI40: =IF(G34=$E$344,IF(OR(G32=0,G35=0,HideCodeLN_HPT=5,HideCodeLN_HPT=8),0,AI32*AI37/G35/1000),0) -> 0 | AJ40: =IF(H34=$E$344,IF(OR(H32=0,H35=0,HideCodeLN_HPT=5,HideCodeLN_HPT=8),0,AJ32*AJ37/H35/1000),0) -> 0 | AK40: =IF(I34=$E$344,IF(OR(I32=0,I35=0,HideCodeLN_HPT=5,HideCodeLN_HPT=8),0,AK32*AK37/I35/1000),0) -> 0 | AL40: =IF(J34=$E$344,IF(OR(J32=0,J35=0,HideCodeLN_HPT=5,HideCodeLN_HPT=8),0,AL32*AL37/J35/1000),0) -> 0 | AM40: =IF(K34=$E$344,IF(OR(K32=0,K35=0,HideCodeLN_HPT=5,HideCodeLN_HPT=8),0,AM32*AM37/K35/1000),0) -> 0 | AN40: =IF(L34=$E$344,IF(OR(L32=0,L35=0,HideCodeLN_HPT=5,HideCodeLN_HPT=8),0,AN32*AN37/L35/1000),0) -> 0 | AO40: =IF(M34=$E$344,IF(OR(M32=0,M35=0,HideCodeLN_HPT=5,HideCodeLN_HPT=8),0,AO32*AO37/M35/1000),0) -> 0 | ... AU40: =IF(S34=$E$344,IF(OR(S32=0,S35=0,HideCodeLN_HPT=5,HideCodeLN_HPT=8),0,AU32*AU37/S35/1000),0) -> 0 | BA40: 41406
B41: =B16 -> Horas equivalentes à plena carga - aquecimento do processo | C41: =$AH$6 -> h | D41: =IF(OR(HideCodeLN_HPT=8,HideCodeLN_HPT=5),AI6,H336) -> 0 | F41: =Language!C59 -> Completar as cargas mensais do processo | AG41: Std pro kW elect | AH41: =IF(F34=$E$344,IF($U$40=1,IF(OR(HideCodeLN_HPT=4,HideCodeLN_HPT=7,F32=0,F35=0,F42=0),0,AH39/F35),IF(OR(HideCodeLN_HPT=4,HideCodeLN_HPT=7,F32=0,F35=0),0,AH39/F35)),0) -> 0 | AI41: =IF(G34=$E$344,IF($U$40=1,IF(OR(HideCodeLN_HPT=4,HideCodeLN_HPT=7,G32=0,G35=0,G42=0),0,AI39/G35),IF(OR(HideCodeLN_HPT=4,HideCodeLN_HPT=7,G32=0,G35=0),0,AI39/G35)),0) -> 0 | AJ41: =IF(H34=$E$344,IF($U$40=1,IF(OR(HideCodeLN_HPT=4,HideCodeLN_HPT=7,H32=0,H35=0,H42=0),0,AJ39/H35),IF(OR(HideCodeLN_HPT=4,HideCodeLN_HPT=7,H32=0,H35=0),0,AJ39/H35)),0) -> 0 | AK41: =IF(I34=$E$344,IF($U$40=1,IF(OR(HideCodeLN_HPT=4,HideCodeLN_HPT=7,I32=0,I35=0,I42=0),0,AK39/I35),IF(OR(HideCodeLN_HPT=4,HideCodeLN_HPT=7,I32=0,I35=0),0,AK39/I35)),0) -> 0 | AL41: =IF(J34=$E$344,IF($U$40=1,IF(OR(HideCodeLN_HPT=4,HideCodeLN_HPT=7,J32=0,J35=0,J42=0),0,AL39/J35),IF(OR(HideCodeLN_HPT=4,HideCodeLN_HPT=7,J32=0,J35=0),0,AL39/J35)),0) -> 0 | AM41: =IF(K34=$E$344,IF($U$40=1,IF(OR(HideCodeLN_HPT=4,HideCodeLN_HPT=7,K32=0,K35=0,K42=0),0,AM39/K35),IF(OR(HideCodeLN_HPT=4,HideCodeLN_HPT=7,K32=0,K35=0),0,AM39/K35)),0) -> 0 | AN41: =IF(L34=$E$344,IF($U$40=1,IF(OR(HideCodeLN_HPT=4,HideCodeLN_HPT=7,L32=0,L35=0,L42=0),0,AN39/L35),IF(OR(HideCodeLN_HPT=4,HideCodeLN_HPT=7,L32=0,L35=0),0,AN39/L35)),0) -> 0 | AO41: =IF(M34=$E$344,IF($U$40=1,IF(OR(HideCodeLN_HPT=4,HideCodeLN_HPT=7,M32=0,M35=0,M42=0),0,AO39/M35),IF(OR(HideCodeLN_HPT=4,HideCodeLN_HPT=7,M32=0,M35=0),0,AO39/M35)),0) -> 0 | ... AU41: =IF(S34=$E$344,IF($U$40=1,IF(OR(HideCodeLN_HPT=4,HideCodeLN_HPT=7,S32=0,S35=0,S42=0),0,AU39/S35),IF(OR(HideCodeLN_HPT=4,HideCodeLN_HPT=7,S32=0,S35=0),0,AU39/S35)),0) -> 0 | BA41: 41408
B42: =B16 -> Horas equivalentes à plena carga - aquecimento do processo | C42: =$AH$6 -> h | D42: =X44*1000/X39 -> #DIV/0! | AH42: =IF(AH32=0,0,IF($U$40=2,1,IF(F42>0,1,0))) -> 0 | AI42: =IF(AI32=0,0,IF($U$40=2,1,IF(G42>0,1,0))) -> 0 | AJ42: =IF(AJ32=0,0,IF($U$40=2,1,IF(H42>0,1,0))) -> 0 | AK42: =IF(AK32=0,0,IF($U$40=2,1,IF(I42>0,1,0))) -> 0 | AL42: =IF(AL32=0,0,IF($U$40=2,1,IF(J42>0,1,0))) -> 0 | AM42: =IF(AM32=0,0,IF($U$40=2,1,IF(K42>0,1,0))) -> 0 | AN42: =IF(AN32=0,0,IF($U$40=2,1,IF(L42>0,1,0))) -> 0 | AO42: =IF(AO32=0,0,IF($U$40=2,1,IF(M42>0,1,0))) -> 0 | ... AU42: =IF(AU32=0,0,IF($U$40=2,1,IF(S42>0,1,0))) -> 0 | BA42: 41408
B43: =Language!C282 -> Demanda aquecimento ambiente | C43: =C18 -> MWh | D43: =IF(Unit=TRUE,X43,Z43) -> 0 | F43: =IF(AH43=0,"-",IF(Unit=TRUE,AH43,AH43*$F$270)) -> - | G43: =IF(AI43=0,"-",IF(Unit=TRUE,AI43,AI43*$F$270)) -> - | H43: =IF(AJ43=0,"-",IF(Unit=TRUE,AJ43,AJ43*$F$270)) -> - | I43: =IF(AK43=0,"-",IF(Unit=TRUE,AK43,AK43*$F$270)) -> - | J43: =IF(AL43=0,"-",IF(Unit=TRUE,AL43,AL43*$F$270)) -> - | K43: =IF(AM43=0,"-",IF(Unit=TRUE,AM43,AM43*$F$270)) -> - | L43: =IF(AN43=0,"-",IF(Unit=TRUE,AN43,AN43*$F$270)) -> - | M43: =IF(AO43=0,"-",IF(Unit=TRUE,AO43,AO43*$F$270)) -> - | ... S43: =IF(AU43=0,"-",IF(Unit=TRUE,AU43,AU43*$F$270)) -> - | W43: MWh | X43: =SUMIF(AH32:AU32,">0",AH43:AU43) -> 0 | Y43: million Btu | Z43: =X43*$F$270 -> 0 | AH43: =IF(OR(AH37=0,AH32=0),0,(AH37*AH32*$E$336/1000)/1000) -> 0 | AI43: =IF(OR(AI37=0,AI32=0),0,(AI37*AI32*$E$336/1000)/1000) -> 0 | AJ43: =IF(OR(AJ37=0,AJ32=0),0,(AJ37*AJ32*$E$336/1000)/1000) -> 0 | AK43: =IF(OR(AK37=0,AK32=0),0,(AK37*AK32*$E$336/1000)/1000) -> 0 | AL43: =IF(OR(AL37=0,AL32=0),0,(AL37*AL32*$E$336/1000)/1000) -> 0 | AM43: =IF(OR(AM37=0,AM32=0),0,(AM37*AM32*$E$336/1000)/1000) -> 0 | AN43: =IF(OR(AN37=0,AN32=0),0,(AN37*AN32*$E$336/1000)/1000) -> 0 | AO43: =IF(OR(AO37=0,AO32=0),0,(AO37*AO32*$E$336/1000)/1000) -> 0 | ... AU43: =IF(OR(AU37=0,AU32=0),0,(AU37*AU32*$E$336/1000)/1000) -> 0 | BA43: 41410
B44: =Language!C283 -> Demanda p/ aquecimento do processo | C44: =C18 -> MWh | D44: =IF(Unit=TRUE,X44,Z44) -> 0 | F44: =IF(AH44=0,"-",IF(Unit=TRUE,AH44,AH44*$F$270)) -> - | G44: =IF(AI44=0,"-",IF(Unit=TRUE,AI44,AI44*$F$270)) -> - | H44: =IF(AJ44=0,"-",IF(Unit=TRUE,AJ44,AJ44*$F$270)) -> - | I44: =IF(AK44=0,"-",IF(Unit=TRUE,AK44,AK44*$F$270)) -> - | J44: =IF(AL44=0,"-",IF(Unit=TRUE,AL44,AL44*$F$270)) -> - | K44: =IF(AM44=0,"-",IF(Unit=TRUE,AM44,AM44*$F$270)) -> - | L44: =IF(AN44=0,"-",IF(Unit=TRUE,AN44,AN44*$F$270)) -> - | M44: =IF(AO44=0,"-",IF(Unit=TRUE,AO44,AO44*$F$270)) -> - | ... S44: =IF(AU44=0,"-",IF(Unit=TRUE,AU44,AU44*$F$270)) -> - | W44: MWh | X44: =G335+I335 -> 0 | Y44: million Btu | Z44: =AG44*$F$270 -> 0 | AG44: =SUMIF(AH32:AU32,">0",AH44:AU44) -> 0 | AH44: =IF(AH39=0,0,IF($U$40=1,AH39*F42/1000,AH39*$D$42/1000)) -> 0 | AI44: =IF(AI39=0,0,IF($U$40=1,AI39*G42/1000,AI39*$D$42/1000)) -> 0 | AJ44: =IF(AJ39=0,0,IF($U$40=1,AJ39*H42/1000,AJ39*$D$42/1000)) -> 0 | AK44: =IF(AK39=0,0,IF($U$40=1,AK39*I42/1000,AK39*$D$42/1000)) -> 0 | AL44: =IF(AL39=0,0,IF($U$40=1,AL39*J42/1000,AL39*$D$42/1000)) -> 0 | AM44: =IF(AM39=0,0,IF($U$40=1,AM39*K42/1000,AM39*$D$42/1000)) -> 0 | AN44: =IF(AN39=0,0,IF($U$40=1,AN39*L42/1000,AN39*$D$42/1000)) -> 0 | AO44: =IF(AO39=0,0,IF($U$40=1,AO39*M42/1000,AO39*$D$42/1000)) -> 0 | ... AU44: =IF(AU39=0,0,IF($U$40=1,AU39*S42/1000,AU39*$D$42/1000)) -> 0 | BA44: 41412
B45: =Language!C284 -> Demanda total p/ aquecimento | C45: =C18 -> MWh | D45: =IF(Unit=TRUE,X45,Z45) -> 0 | F45: =IF(AH45="","-",IF(Unit=TRUE,AH45,AH45*$F$270)) -> 0 | G45: =IF(AI45="","-",IF(Unit=TRUE,AI45,AI45*$F$270)) -> - | H45: =IF(AJ45="","-",IF(Unit=TRUE,AJ45,AJ45*$F$270)) -> - | I45: =IF(AK45="","-",IF(Unit=TRUE,AK45,AK45*$F$270)) -> - | J45: =IF(AL45="","-",IF(Unit=TRUE,AL45,AL45*$F$270)) -> - | K45: =IF(AM45="","-",IF(Unit=TRUE,AM45,AM45*$F$270)) -> - | L45: =IF(AN45="","-",IF(Unit=TRUE,AN45,AN45*$F$270)) -> - | M45: =IF(AO45="","-",IF(Unit=TRUE,AO45,AO45*$F$270)) -> - | ... S45: =IF(AU45="","-",IF(Unit=TRUE,AU45,AU45*$F$270)) -> - | W45: MWh | X45: =IF(OR(HideCodeLN_HPT=5,HideCodeLN_HPT=8),X44,IF(OR(HideCodeLN_HPT=4,HideCodeLN_HPT=7),X43,IF(OR(HideCodeLN_HPT=6,HideCodeLN_HPT=9),X43+X44,0))) -> 0 | Y45: million Btu | Z45: =X45*$F$270 -> 0 | AG45: 1 | AH45: =IF(AND(AH43="",AH44=""),"",IF(AH32=0,"",IF(OR(HideCodeLN_HPT=5,HideCodeLN_HPT=8),AH44*$AG$45,IF(OR(HideCodeLN_HPT=4,HideCodeLN_HPT=7),AH43,IF(OR(HideCodeLN_HPT=6,HideCodeLN_HPT=9),AH43+AH44*$AG$45,0))))) -> 0 | AI45: =IF(AND(AI43="",AI44=""),"",IF(AI32=0,"",IF(OR(HideCodeLN_HPT=5,HideCodeLN_HPT=8),AI44*$AG$45,IF(OR(HideCodeLN_HPT=4,HideCodeLN_HPT=7),AI43,IF(OR(HideCodeLN_HPT=6,HideCodeLN_HPT=9),AI43+AI44*$AG$45,0))))) | AJ45: =IF(AND(AJ43="",AJ44=""),"",IF(AJ32=0,"",IF(OR(HideCodeLN_HPT=5,HideCodeLN_HPT=8),AJ44*$AG$45,IF(OR(HideCodeLN_HPT=4,HideCodeLN_HPT=7),AJ43,IF(OR(HideCodeLN_HPT=6,HideCodeLN_HPT=9),AJ43+AJ44*$AG$45,0))))) | AK45: =IF(AND(AK43="",AK44=""),"",IF(AK32=0,"",IF(OR(HideCodeLN_HPT=5,HideCodeLN_HPT=8),AK44*$AG$45,IF(OR(HideCodeLN_HPT=4,HideCodeLN_HPT=7),AK43,IF(OR(HideCodeLN_HPT=6,HideCodeLN_HPT=9),AK43+AK44*$AG$45,0))))) | AL45: =IF(AND(AL43="",AL44=""),"",IF(AL32=0,"",IF(OR(HideCodeLN_HPT=5,HideCodeLN_HPT=8),AL44*$AG$45,IF(OR(HideCodeLN_HPT=4,HideCodeLN_HPT=7),AL43,IF(OR(HideCodeLN_HPT=6,HideCodeLN_HPT=9),AL43+AL44*$AG$45,0))))) | AM45: =IF(AND(AM43="",AM44=""),"",IF(AM32=0,"",IF(OR(HideCodeLN_HPT=5,HideCodeLN_HPT=8),AM44*$AG$45,IF(OR(HideCodeLN_HPT=4,HideCodeLN_HPT=7),AM43,IF(OR(HideCodeLN_HPT=6,HideCodeLN_HPT=9),AM43+AM44*$AG$45,0))))) | AN45: =IF(AND(AN43="",AN44=""),"",IF(AN32=0,"",IF(OR(HideCodeLN_HPT=5,HideCodeLN_HPT=8),AN44*$AG$45,IF(OR(HideCodeLN_HPT=4,HideCodeLN_HPT=7),AN43,IF(OR(HideCodeLN_HPT=6,HideCodeLN_HPT=9),AN43+AN44*$AG$45,0))))) | AO45: =IF(AND(AO43="",AO44=""),"",IF(AO32=0,"",IF(OR(HideCodeLN_HPT=5,HideCodeLN_HPT=8),AO44*$AG$45,IF(OR(HideCodeLN_HPT=4,HideCodeLN_HPT=7),AO43,IF(OR(HideCodeLN_HPT=6,HideCodeLN_HPT=9),AO43+AO44*$AG$45,0))))) | ... AU45: =IF(AND(AU43="",AU44=""),"",IF(AU32=0,"",IF(OR(HideCodeLN_HPT=5,HideCodeLN_HPT=8),AU44*$AG$45,IF(OR(HideCodeLN_HPT=4,HideCodeLN_HPT=7),AU43,IF(OR(HideCodeLN_HPT=6,HideCodeLN_HPT=9),AU43+AU44*$AG$45,0))))) | BA45: 41414
B46: =Language!C285 -> Carga total p/ aquecimento de ponta | C46: =C21 -> kW | D46: =IF(Unit=TRUE,X46,Z46) -> 0 | F46: =IF(AH46=0,"-",IF(Unit=TRUE,AH46,AH46*$E$270)) -> - | G46: =IF(AI46=0,"-",IF(Unit=TRUE,AI46,AI46*$E$270)) -> - | H46: =IF(AJ46=0,"-",IF(Unit=TRUE,AJ46,AJ46*$E$270)) -> - | I46: =IF(AK46=0,"-",IF(Unit=TRUE,AK46,AK46*$E$270)) -> - | J46: =IF(AL46=0,"-",IF(Unit=TRUE,AL46,AL46*$E$270)) -> - | K46: =IF(AM46=0,"-",IF(Unit=TRUE,AM46,AM46*$E$270)) -> - | L46: =IF(AN46=0,"-",IF(Unit=TRUE,AN46,AN46*$E$270)) -> - | M46: =IF(AO46=0,"-",IF(Unit=TRUE,AO46,AO46*$E$270)) -> - | ... S46: =IF(AU46=0,"-",IF(Unit=TRUE,AU46,AU46*$E$270)) -> - | W46: kW | X46: =SUMIF(AH32:AU32,">0",AH46:AU46) -> 0 | Y46: million Btu/h | Z46: =X46*$E$270 -> 0 | AH46: =IF(OR(HideCodeLN_HPT=4,HideCodeLN_HPT=7),AH32*AH37/1000,IF(OR(HideCodeLN_HPT=5,HideCodeLN_HPT=8),AH39*AH42,IF(OR(HideCodeLN_HPT=6,HideCodeLN_HPT=9),AH32*AH37/1000+AH39*AH42,0))) -> 0 | AI46: =IF(OR(HideCodeLN_HPT=4,HideCodeLN_HPT=7),AI32*AI37/1000,IF(OR(HideCodeLN_HPT=5,HideCodeLN_HPT=8),AI39*AI42,IF(OR(HideCodeLN_HPT=6,HideCodeLN_HPT=9),AI32*AI37/1000+AI39*AI42,0))) -> 0 | AJ46: =IF(OR(HideCodeLN_HPT=4,HideCodeLN_HPT=7),AJ32*AJ37/1000,IF(OR(HideCodeLN_HPT=5,HideCodeLN_HPT=8),AJ39*AJ42,IF(OR(HideCodeLN_HPT=6,HideCodeLN_HPT=9),AJ32*AJ37/1000+AJ39*AJ42,0))) -> 0 | AK46: =IF(OR(HideCodeLN_HPT=4,HideCodeLN_HPT=7),AK32*AK37/1000,IF(OR(HideCodeLN_HPT=5,HideCodeLN_HPT=8),AK39*AK42,IF(OR(HideCodeLN_HPT=6,HideCodeLN_HPT=9),AK32*AK37/1000+AK39*AK42,0))) -> 0 | AL46: =IF(OR(HideCodeLN_HPT=4,HideCodeLN_HPT=7),AL32*AL37/1000,IF(OR(HideCodeLN_HPT=5,HideCodeLN_HPT=8),AL39*AL42,IF(OR(HideCodeLN_HPT=6,HideCodeLN_HPT=9),AL32*AL37/1000+AL39*AL42,0))) -> 0 | AM46: =IF(OR(HideCodeLN_HPT=4,HideCodeLN_HPT=7),AM32*AM37/1000,IF(OR(HideCodeLN_HPT=5,HideCodeLN_HPT=8),AM39*AM42,IF(OR(HideCodeLN_HPT=6,HideCodeLN_HPT=9),AM32*AM37/1000+AM39*AM42,0))) -> 0 | AN46: =IF(OR(HideCodeLN_HPT=4,HideCodeLN_HPT=7),AN32*AN37/1000,IF(OR(HideCodeLN_HPT=5,HideCodeLN_HPT=8),AN39*AN42,IF(OR(HideCodeLN_HPT=6,HideCodeLN_HPT=9),AN32*AN37/1000+AN39*AN42,0))) -> 0 | AO46: =IF(OR(HideCodeLN_HPT=4,HideCodeLN_HPT=7),AO32*AO37/1000,IF(OR(HideCodeLN_HPT=5,HideCodeLN_HPT=8),AO39*AO42,IF(OR(HideCodeLN_HPT=6,HideCodeLN_HPT=9),AO32*AO37/1000+AO39*AO42,0))) -> 0 | ... AU46: =IF(OR(HideCodeLN_HPT=4,HideCodeLN_HPT=7),AU32*AU37/1000,IF(OR(HideCodeLN_HPT=5,HideCodeLN_HPT=8),AU39*AU42,IF(OR(HideCodeLN_HPT=6,HideCodeLN_HPT=9),AU32*AU37/1000+AU39*AU42,0))) -> 0 | BA46: 41416
B47: =Language!C357 -> Consumo de combustível - unitário | D47: - | F47: =IF(OR(F32="",F34=0),"-",VLOOKUP(F34,$E$340:$I$360,3,FALSE)) -> m³ | G47: =IF(OR(G32="",G34=0),"-",VLOOKUP(G34,$E$340:$I$360,3,FALSE)) -> - | H47: =IF(OR(H32="",H34=0),"-",VLOOKUP(H34,$E$340:$I$360,3,FALSE)) -> - | I47: =IF(OR(I32="",I34=0),"-",VLOOKUP(I34,$E$340:$I$360,3,FALSE)) -> - | J47: =IF(OR(J32="",J34=0),"-",VLOOKUP(J34,$E$340:$I$360,3,FALSE)) -> - | K47: =IF(OR(K32="",K34=0),"-",VLOOKUP(K34,$E$340:$I$360,3,FALSE)) -> - | L47: =IF(OR(L32="",L34=0),"-",VLOOKUP(L34,$E$340:$I$360,3,FALSE)) -> - | M47: =IF(OR(M32="",M34=0),"-",VLOOKUP(M34,$E$340:$I$360,3,FALSE)) -> - | ... S47: =IF(OR(S32="",S34=0),"-",VLOOKUP(S34,$E$340:$I$360,3,FALSE)) -> - | AG47: Pro MWh elect | AH47: =IF(F34=$E$344,IF(OR(F32=0,AH39=0,HideCodeLN_HPT=4,HideCodeLN_HPT=7),0,IF($U$40=1,AH39*F42/F35/1000,AH39*$H$336/F35/1000)),0) -> 0 | AI47: =IF(G34=$E$344,IF(OR(G32=0,AI39=0,HideCodeLN_HPT=4,HideCodeLN_HPT=7),0,IF($U$40=1,AI39*G42/G35/1000,AI39*$H$336/G35/1000)),0) -> 0 | AJ47: =IF(H34=$E$344,IF(OR(H32=0,AJ39=0,HideCodeLN_HPT=4,HideCodeLN_HPT=7),0,IF($U$40=1,AJ39*H42/H35/1000,AJ39*$H$336/H35/1000)),0) -> 0 | AK47: =IF(I34=$E$344,IF(OR(I32=0,AK39=0,HideCodeLN_HPT=4,HideCodeLN_HPT=7),0,IF($U$40=1,AK39*I42/I35/1000,AK39*$H$336/I35/1000)),0) -> 0 | AL47: =IF(J34=$E$344,IF(OR(J32=0,AL39=0,HideCodeLN_HPT=4,HideCodeLN_HPT=7),0,IF($U$40=1,AL39*J42/J35/1000,AL39*$H$336/J35/1000)),0) -> 0 | AM47: =IF(K34=$E$344,IF(OR(K32=0,AM39=0,HideCodeLN_HPT=4,HideCodeLN_HPT=7),0,IF($U$40=1,AM39*K42/K35/1000,AM39*$H$336/K35/1000)),0) -> 0 | AN47: =IF(L34=$E$344,IF(OR(L32=0,AN39=0,HideCodeLN_HPT=4,HideCodeLN_HPT=7),0,IF($U$40=1,AN39*L42/L35/1000,AN39*$H$336/L35/1000)),0) -> 0 | AO47: =IF(M34=$E$344,IF(OR(M32=0,AO39=0,HideCodeLN_HPT=4,HideCodeLN_HPT=7),0,IF($U$40=1,AO39*M42/M35/1000,AO39*$H$336/M35/1000)),0) -> 0 | ... AU47: =IF(S34=$E$344,IF(OR(S32=0,AU39=0,HideCodeLN_HPT=4,HideCodeLN_HPT=7),0,IF($U$40=1,AU39*S42/S35/1000,AU39*$H$336/S35/1000)),0) -> 0 | BA47: 41418
B48: =Language!C286 -> Consumo de combustível - anual | D48: - | F48: =IF(OR(AH$45="",F35="",F35=0),0,AH$45/VLOOKUP(F34,$E$340:$I$360,4,FALSE)*1000/F$35) -> 0 | G48: =IF(OR(AI$45="",G35="",G35=0),0,AI$45/VLOOKUP(G34,$E$340:$I$360,4,FALSE)*1000/G$35) -> 0 | H48: =IF(OR(AJ$45="",H35="",H35=0),0,AJ$45/VLOOKUP(H34,$E$340:$I$360,4,FALSE)*1000/H$35) -> 0 | I48: =IF(OR(AK$45="",I35="",I35=0),0,AK$45/VLOOKUP(I34,$E$340:$I$360,4,FALSE)*1000/I$35) -> 0 | J48: =IF(OR(AL$45="",J35="",J35=0),0,AL$45/VLOOKUP(J34,$E$340:$I$360,4,FALSE)*1000/J$35) -> 0 | K48: =IF(OR(AM$45="",K35="",K35=0),0,AM$45/VLOOKUP(K34,$E$340:$I$360,4,FALSE)*1000/K$35) -> 0 | L48: =IF(OR(AN$45="",L35="",L35=0),0,AN$45/VLOOKUP(L34,$E$340:$I$360,4,FALSE)*1000/L$35) -> 0 | M48: =IF(OR(AO$45="",M35="",M35=0),0,AO$45/VLOOKUP(M34,$E$340:$I$360,4,FALSE)*1000/M$35) -> 0 | ... R48: =IF(OR(AT$45="",R35="",R35=0),0,AT$45/VLOOKUP(R34,$E$340:$I$360,4,FALSE)*1000/R$35) -> 0 | S48: =IF(OR(AU$45="",S35="",S45=0),0,AU$45/VLOOKUP(S34,$E$340:$I$360,4,FALSE)*1000/S$35) -> 0 | BA48: 41420
B49: =Language!C359 -> Preço combustível - unidade | D49: - | F49: =IF(OR(F32="",F34=0),"-",VLOOKUP(F34,$E$340:$I$360,5,FALSE)) -> €/m³ | G49: =IF(OR(G32="",G34=0),"-",VLOOKUP(G34,$E$340:$I$360,5,FALSE)) -> - | H49: =IF(OR(H32="",H34=0),"-",VLOOKUP(H34,$E$340:$I$360,5,FALSE)) -> - | I49: =IF(OR(I32="",I34=0),"-",VLOOKUP(I34,$E$340:$I$360,5,FALSE)) -> - | J49: =IF(OR(J32="",J34=0),"-",VLOOKUP(J34,$E$340:$I$360,5,FALSE)) -> - | K49: =IF(OR(K32="",K34=0),"-",VLOOKUP(K34,$E$340:$I$360,5,FALSE)) -> - | L49: =IF(OR(L32="",L34=0),"-",VLOOKUP(L34,$E$340:$I$360,5,FALSE)) -> - | M49: =IF(OR(M32="",M34=0),"-",VLOOKUP(M34,$E$340:$I$360,5,FALSE)) -> - | ... S49: =IF(OR(S32="",S34=0),"-",VLOOKUP(S34,$E$340:$I$360,5,FALSE)) -> - | BA49: 41422
B50: =B23 -> Preço do combustível | D50: - | BA50: 2010108
B51: =Language!C287 -> Custo do combustível | D51: =IF(ISERROR(SUMIF(AH32:AU32,">0",F51:S51)),0,SUMIF(AH32:AU32,">0",F51:S51)) -> 0 | F51: =IF(OR(F48=0,F48="-",AH32=0),"-",IF(F$34=$E$344,F50*F48*1000,IF(F$34=$E$360,F50*F48,F50*F48))) -> - | G51: =IF(OR(G48=0,G48="-",AI32=0),"-",IF(G$34=$E$344,G50*G48*1000,IF(G$34=$E$360,G50*G48,G50*G48))) -> - | H51: =IF(OR(H48=0,H48="-",AJ32=0),"-",IF(H$34=$E$344,H50*H48*1000,IF(H$34=$E$360,H50*H48,H50*H48))) -> - | I51: =IF(OR(I48=0,I48="-",AK32=0),"-",IF(I$34=$E$344,I50*I48*1000,IF(I$34=$E$360,I50*I48,I50*I48))) -> - | J51: =IF(OR(J48=0,J48="-",AL32=0),"-",IF(J$34=$E$344,J50*J48*1000,IF(J$34=$E$360,J50*J48,J50*J48))) -> - | K51: =IF(OR(K48=0,K48="-",AM32=0),"-",IF(K$34=$E$344,K50*K48*1000,IF(K$34=$E$360,K50*K48,K50*K48))) -> - | L51: =IF(OR(L48=0,L48="-",AN32=0),"-",IF(L$34=$E$344,L50*L48*1000,IF(L$34=$E$360,L50*L48,L50*L48))) -> - | M51: =IF(OR(M48=0,M48="-",AO32=0),"-",IF(M$34=$E$344,M50*M48*1000,IF(M$34=$E$360,M50*M48,M50*M48))) -> - | ... S51: =IF(OR(S48=0,S48="-",AU32=0),"-",IF(S$34=$E$344,S50*S48*1000,IF(S$34=$E$360,S50*S48,S50*S48))) -> - | BA51: 5097210
A52: =Language!C288 -> Ações de eficiência energética do caso proposto | BA52: 41500
B53: =B26 -> Ações de eficiência energética no uso final | C53: =$C$13 -> % | D53: =IF(D54=0,0,1-D54/D46) -> 0 | W53: h | X53: =Tot_ht_en_demand/Tot_peak_ht_load*1000 -> #DIV/0! | BA53: 41501
B54: =Language!C290 -> Carga líquida de aquecimento de ponta | C54: =C21 -> kW | D54: =IF(Unit=TRUE,X54,Z54) -> 0 | F54: =IF(AH54=0,"-",IF(Unit=TRUE,AH54,AH54*$E$270)) -> - | G54: =IF(AI54=0,"-",IF(Unit=TRUE,AI54,AI54*$E$270)) -> - | H54: =IF(AJ54=0,"-",IF(Unit=TRUE,AJ54,AJ54*$E$270)) -> - | I54: =IF(AK54=0,"-",IF(Unit=TRUE,AK54,AK54*$E$270)) -> - | J54: =IF(AL54=0,"-",IF(Unit=TRUE,AL54,AL54*$E$270)) -> - | K54: =IF(AM54=0,"-",IF(Unit=TRUE,AM54,AM54*$E$270)) -> - | L54: =IF(AN54=0,"-",IF(Unit=TRUE,AN54,AN54*$E$270)) -> - | M54: =IF(AO54=0,"-",IF(Unit=TRUE,AO54,AO54*$E$270)) -> - | ... S54: =IF(AU54=0,"-",IF(Unit=TRUE,AU54,AU54*$E$270)) -> - | W54: kW | X54: =SUMIF(AH32:AU32,">0",AH54:AU54) -> 0 | Y54: million Btu/h | Z54: =X54*$E$270 -> 0 | AH54: =IF(AH46=0,0,AH46*(1-F53)) -> 0 | AI54: =IF(AI46=0,0,AI46*(1-G53)) -> 0 | AJ54: =IF(AJ46=0,0,AJ46*(1-H53)) -> 0 | AK54: =IF(AK46=0,0,AK46*(1-I53)) -> 0 | AL54: =IF(AL46=0,0,AL46*(1-J53)) -> 0 | AM54: =IF(AM46=0,0,AM46*(1-K53)) -> 0 | AN54: =IF(AN46=0,0,AN46*(1-L53)) -> 0 | AO54: =IF(AO46=0,0,AO46*(1-M53)) -> 0 | ... AU54: =IF(AU46=0,0,AU46*(1-S53)) -> 0 | BA54: 41502
B55: =Language!C291 -> Demanda líquida de aquecimento | C55: =C18 -> MWh | D55: =IF(Unit=TRUE,X55,Z55) -> 0 | F55: =IF(AH55=0,"-",IF(Unit=TRUE,AH55,AH55*$F$270)) -> - | G55: =IF(AI55=0,"-",IF(Unit=TRUE,AI55,AI55*$F$270)) -> - | H55: =IF(AJ55=0,"-",IF(Unit=TRUE,AJ55,AJ55*$F$270)) -> - | I55: =IF(AK55=0,"-",IF(Unit=TRUE,AK55,AK55*$F$270)) -> - | J55: =IF(AL55=0,"-",IF(Unit=TRUE,AL55,AL55*$F$270)) -> - | K55: =IF(AM55=0,"-",IF(Unit=TRUE,AM55,AM55*$F$270)) -> - | L55: =IF(AN55=0,"-",IF(Unit=TRUE,AN55,AN55*$F$270)) -> - | M55: =IF(AO55=0,"-",IF(Unit=TRUE,AO55,AO55*$F$270)) -> - | ... S55: =IF(AU55=0,"-",IF(Unit=TRUE,AU55,AU55*$F$270)) -> - | W55: MWh | X55: =SUMIF(AH32:AU32,">0",AH55:AU55) -> 0 | Y55: million Btu | Z55: =X55*$F$270 -> 0 | AH55: =IF(AH54=0,0,AH54*$X$53/1000) -> 0 | AI55: =IF(AI54=0,0,AI54*$X$53/1000) -> 0 | AJ55: =IF(AJ54=0,0,AJ54*$X$53/1000) -> 0 | AK55: =IF(AK54=0,0,AK54*$X$53/1000) -> 0 | AL55: =IF(AL54=0,0,AL54*$X$53/1000) -> 0 | AM55: =IF(AM54=0,0,AM54*$X$53/1000) -> 0 | AN55: =IF(AN54=0,0,AN54*$X$53/1000) -> 0 | AO55: =IF(AO54=0,0,AO54*$X$53/1000) -> 0 | ... AU55: =IF(AU54=0,0,AU54*$X$53/1000) -> 0 | BA55: 41504
BA56: 41000
A57: =Language!C300 -> Rede de aquecimento municipal do caso proposto | D57: =Language!C301 -> Estimado/Total | BA57: 42000
B58: =Language!C302 -> Critérios p/ projeto da rede de aquecimento | AG58: =18-Iniciar!P52 -> 14.7 | AH58: DEGREE-DAYS AND DESIGN AMBIENT TEMPERATURES | BA58: 42100
B59: =Language!C303 -> Temp. de fornecimento projetada | C59: °C | W59: °C | X59: =IF(C59=$D$262,D59,(D59-32)/1.8) -> 0 | Y59: °F | Z59: =X59*1.8+32 -> 32 | BA59: 42102
B60: =Language!C304 -> Temp. de retorno projetada | C60: °C | W60: °C | X60: =IF(C60=$D$262,D60,(D60-32)/1.8) -> 0 | Y60: °F | Z60: =X60*1.8+32 -> 32 | BA60: 42104
B61: =Language!C305 -> Diferencial de temperatura | C61: =IF(Unit=TRUE,Language!C1310,Language!C1313) -> °C | D61: =IF(Unit=TRUE,X61,Z61) -> 0 | W61: °C | X61: =X59-X60 -> 0 | Y61: °F | Z61: =Z59-Z60 -> 0 | BA61: 42106
B62: =Language!C306 -> Linha principal de distribuição de calor | BA62: 42200
B63: =Language!C307 -> Sobredimensiona. do tubo principal da rede | C63: =$C$13 -> % | BA63: 42202
B64: =Language!C308 -> Secções de tubos | C64: =Language!C309 -> Carga | D64: =Language!C310 -> Comprimento | E64: =Language!C311 -> Dimens. Tubo | F64: =Language!C312 -> O condomínio é atendido por esta secção de tubo ? (sim/não) | AH64: Including degree-day independent heating | BA64: 42204
C65: =C21 -> kW | D65: m | E65: =Language!C1392 -> mm | F65: 1 | G65: 2 | H65: 3 | I65: 4 | J65: 5 | K65: 6 | L65: 7 | M65: 8 | N65: 9 | O65: 10 | P65: 11 | Q65: 12 | R65: 13 | S65: 14 | W65: kW | X65: million Btu/h | Y65: m | AH65: DD independent | BA65: 42204
B66: =Language!$C$313&" 1" -> Secção 1 | C66: =IF(Unit=TRUE,W66,X66) -> 0 | D66: 1 | E66: =IF(OR($Y66=0,$W66=0),"",LOOKUP(($W66*(1+$D$63)),$D$286:$D$306,$H$286:$H$306)) | F66: Sim | W66: =SUMIF(F66:S66,$G$260,$AH$54:$AU$54)*IF(D66<>0,1,0) -> 0 | X66: =IF(W66="","",W66*$E$270) -> 0 | Y66: =IF($D$65=$D$264,D66,D66*$E$265) -> 1 | AH66: DD/day | AI66: Base Load | BA66: 42204
B67: =Language!$C$313&" 2" -> Secção 2 | C67: =IF(Unit=TRUE,W67,X67) -> 0 | E67: =IF(OR($Y67=0,$W67=0),"",LOOKUP(($W67*(1+$D$63)),$D$286:$D$306,$H$286:$H$306)) | W67: =SUMIF(F67:S67,$G$260,$AH$54:$AU$54)*IF(D67<>0,1,0) -> 0 | X67: =IF(W67="","",W67*$E$270) -> 0 | Y67: =IF($D$65=$D$264,D67,D67*$E$265) -> 0 | AH67: =Ann_heat_deg_days*AI67/(1-AI67)/365 -> 0 | AI67: =IF(AND(Set_Level=2,Iniciar!P4=0),IF(HideCodeLN_HPT<4,D13,D38),IF(AND(Set_Level=1,Iniciar!P4=0),IF(HideCodeLN_HPT<4,D13,D38),'Modelo Energético '!P909)) -> 0 | BA67: 42204
B68: =Language!$C$313&" 3" -> Secção 3 | C68: =IF(Unit=TRUE,W68,X68) -> 0 | E68: =IF(OR($Y68=0,$W68=0),"",LOOKUP(($W68*(1+$D$63)),$D$286:$D$306,$H$286:$H$306)) | W68: =SUMIF(F68:S68,$G$260,$AH$54:$AU$54)*IF(D68<>0,1,0) -> 0 | X68: =IF(W68="","",W68*$E$270) -> 0 | Y68: =IF($D$65=$D$264,D68,D68*$E$265) -> 0 | BA68: 42204
B69: =Language!$C$313&" 4" -> Secção 4 | C69: =IF(Unit=TRUE,W69,X69) -> 0 | E69: =IF(OR($Y69=0,$W69=0),"",LOOKUP(($W69*(1+$D$63)),$D$286:$D$306,$H$286:$H$306)) | W69: =SUMIF(F69:S69,$G$260,$AH$54:$AU$54)*IF(D69<>0,1,0) -> 0 | X69: =IF(W69="","",W69*$E$270) -> 0 | Y69: =IF($D$65=$D$264,D69,D69*$E$265) -> 0 | BA69: 42204
B70: =Language!$C$313&" 5" -> Secção 5 | C70: =IF(Unit=TRUE,W70,X70) -> 0 | E70: =IF(OR($Y70=0,$W70=0),"",LOOKUP(($W70*(1+$D$63)),$D$286:$D$306,$H$286:$H$306)) | W70: =SUMIF(F70:S70,$G$260,$AH$54:$AU$54)*IF(D70<>0,1,0) -> 0 | X70: =IF(W70="","",W70*$E$270) -> 0 | Y70: =IF($D$65=$D$264,D70,D70*$E$265) -> 0 | BA70: 42204
B71: =Language!$C$313&" 6" -> Secção 6 | C71: =IF(Unit=TRUE,W71,X71) -> 0 | E71: =IF(OR($Y71=0,$W71=0),"",LOOKUP(($W71*(1+$D$63)),$D$286:$D$306,$H$286:$H$306)) | W71: =SUMIF(F71:S71,$G$260,$AH$54:$AU$54)*IF(D71<>0,1,0) -> 0 | X71: =IF(W71="","",W71*$E$270) -> 0 | Y71: =IF($D$65=$D$264,D71,D71*$E$265) -> 0 | BA71: 42204
B72: =Language!$C$313&" 7" -> Secção 7 | C72: =IF(Unit=TRUE,W72,X72) -> 0 | E72: =IF(OR($Y72=0,$W72=0),"",LOOKUP(($W72*(1+$D$63)),$D$286:$D$306,$H$286:$H$306)) | W72: =SUMIF(F72:S72,$G$260,$AH$54:$AU$54)*IF(D72<>0,1,0) -> 0 | X72: =IF(W72="","",W72*$E$270) -> 0 | Y72: =IF($D$65=$D$264,D72,D72*$E$265) -> 0 | BA72: 42204
B73: =Language!$C$313&" 8" -> Secção 8 | C73: =IF(Unit=TRUE,W73,X73) -> 0 | E73: =IF(OR($Y73=0,$W73=0),"",LOOKUP(($W73*(1+$D$63)),$D$286:$D$306,$H$286:$H$306)) | W73: =SUMIF(F73:S73,$G$260,$AH$54:$AU$54)*IF(D73<>0,1,0) -> 0 | X73: =IF(W73="","",W73*$E$270) -> 0 | Y73: =IF($D$65=$D$264,D73,D73*$E$265) -> 0 | BA73: 42204
B74: =Language!$C$313&" 9" -> Secção 9 | C74: =IF(Unit=TRUE,W74,X74) -> 0 | E74: =IF(OR($Y74=0,$W74=0),"",LOOKUP(($W74*(1+$D$63)),$D$286:$D$306,$H$286:$H$306)) | W74: =SUMIF(F74:S74,$G$260,$AH$54:$AU$54)*IF(D74<>0,1,0) -> 0 | X74: =IF(W74="","",W74*$E$270) -> 0 | Y74: =IF($D$65=$D$264,D74,D74*$E$265) -> 0 | BA74: 42204
B75: =Language!$C$313&" 10" -> Secção 10 | C75: =IF(Unit=TRUE,W75,X75) -> 0 | E75: =IF(OR($Y75=0,$W75=0),"",LOOKUP(($W75*(1+$D$63)),$D$286:$D$306,$H$286:$H$306)) | W75: =SUMIF(F75:S75,$G$260,$AH$54:$AU$54)*IF(D75<>0,1,0) -> 0 | X75: =IF(W75="","",W75*$E$270) -> 0 | Y75: =IF($D$65=$D$264,D75,D75*$E$265) -> 0 | BA75: 42204
B76: =Language!$C$313&" 11" -> Secção 11 | C76: =IF(Unit=TRUE,W76,X76) -> 0 | E76: =IF(OR($Y76=0,$W76=0),"",LOOKUP(($W76*(1+$D$63)),$D$286:$D$306,$H$286:$H$306)) | W76: =SUMIF(F76:S76,$G$260,$AH$54:$AU$54)*IF(D76<>0,1,0) -> 0 | X76: =IF(W76="","",W76*$E$270) -> 0 | Y76: =IF($D$65=$D$264,D76,D76*$E$265) -> 0 | BA76: 42204
B77: =Language!$C$313&" 12" -> Secção 12 | C77: =IF(Unit=TRUE,W77,X77) -> 0 | E77: =IF(OR($Y77=0,$W77=0),"",LOOKUP(($W77*(1+$D$63)),$D$286:$D$306,$H$286:$H$306)) | W77: =SUMIF(F77:S77,$G$260,$AH$54:$AU$54)*IF(D77<>0,1,0) -> 0 | X77: =IF(W77="","",W77*$E$270) -> 0 | Y77: =IF($D$65=$D$264,D77,D77*$E$265) -> 0 | BA77: 42204
B78: =Language!$C$313&" 13" -> Secção 13 | C78: =IF(Unit=TRUE,W78,X78) -> 0 | E78: =IF(OR($Y78=0,$W78=0),"",LOOKUP(($W78*(1+$D$63)),$D$286:$D$306,$H$286:$H$306)) | W78: =SUMIF(F78:S78,$G$260,$AH$54:$AU$54)*IF(D78<>0,1,0) -> 0 | X78: =IF(W78="","",W78*$E$270) -> 0 | Y78: =IF($D$65=$D$264,D78,D78*$E$265) -> 0 | BA78: 42204
B79: =Language!C314 -> Comprimento total do tubo da linha de distribuição principal | C79: =IF(Unit=TRUE,Language!C1372,Language!C1327) -> m | D79: =IF(Unit=TRUE,X79,Z79) -> 1 | W79: m | X79: =SUM(Y66:Y78) -> 1 | Y79: ft | Z79: =X79/$E$265 -> 3.2808399 | BA79: 42206
B80: =Language!C315 -> Linha secundária de distribuição de calor | BA80: 42300
B81: =Language!C317 -> Sobredimens. tubo secundário da rede distrib. | C81: =$C$13 -> % | F81: =Language!C316 -> Comprimento do tubo da linha de distribuição secundária por condomínio | BA81: 42302
B82: =Language!C318 -> Comprimento da secção de tubo | C82: =C79 -> m | D82: =IF(Unit=TRUE,X82,Z82) -> 0 | E82: m | W82: m | X82: =SUMIF(AH32:AU32,">0",AH82:AU82) -> 0 | Y82: ft | Z82: =X82/$E$265 -> 0 | AH82: =IF($E$82=$D$264,F82,F82*$E$265) -> 0 | AI82: =IF($E$82=$D$264,G82,G82*$E$265) -> 0 | AJ82: =IF($E$82=$D$264,H82,H82*$E$265) -> 0 | AK82: =IF($E$82=$D$264,I82,I82*$E$265) -> 0 | AL82: =IF($E$82=$D$264,J82,J82*$E$265) -> 0 | AM82: =IF($E$82=$D$264,K82,K82*$E$265) -> 0 | AN82: =IF($E$82=$D$264,L82,L82*$E$265) -> 0 | AO82: =IF($E$82=$D$264,M82,M82*$E$265) -> 0 | ... AU82: =IF($E$82=$D$264,S82,S82*$E$265) -> 0 | BA82: 42304
B83: =E64 -> Dimens. Tubo | C83: =E65 -> mm | F83: =IF(AH$54=0,"-",LOOKUP(AH$54/F$33*(1+$D$81),$D$286:$D$306,$H$286:$H$306)) -> - | G83: =IF(AI$54=0,"-",LOOKUP(AI$54/G$33*(1+$D$81),$D$286:$D$306,$H$286:$H$306)) -> - | H83: =IF(AJ$54=0,"-",LOOKUP(AJ$54/H$33*(1+$D$81),$D$286:$D$306,$H$286:$H$306)) -> - | I83: =IF(AK$54=0,"-",LOOKUP(AK$54/I$33*(1+$D$81),$D$286:$D$306,$H$286:$H$306)) -> - | J83: =IF(AL$54=0,"-",LOOKUP(AL$54/J$33*(1+$D$81),$D$286:$D$306,$H$286:$H$306)) -> - | K83: =IF(AM$54=0,"-",LOOKUP(AM$54/K$33*(1+$D$81),$D$286:$D$306,$H$286:$H$306)) -> - | L83: =IF(AN$54=0,"-",LOOKUP(AN$54/L$33*(1+$D$81),$D$286:$D$306,$H$286:$H$306)) -> - | M83: =IF(AO$54=0,"-",LOOKUP(AO$54/M$33*(1+$D$81),$D$286:$D$306,$H$286:$H$306)) -> - | ... S83: =IF(AU$54=0,"-",LOOKUP(AU$54/S$33*(1+$D$81),$D$286:$D$306,$H$286:$H$306)) -> - | BA83: 42306
B84: =Language!C319 -> Custo da rede municipal de calor | BA84: 42400
B85: =Language!C320 -> Comprimento total de tubos | C85: =C79 -> m | D85: =IF(Unit=TRUE,X85,Z85) -> 1 | W85: m | X85: =X79+X82 -> 1 | Y85: ft | Z85: =X85/$E$265 -> 3.2808399 | BA85: 42402
B86: =Language!C321 -> Método de avaliação de custos | D86: Fórmula | U86: =IF(D86="",1,MATCH(D86,LN_FD,0))+20 -> 21 | W86: '=HideCodeLN_Heat_CM | BA86: 42404
B87: =Language!C322 -> Tipo de conexão - estação de transferência de energia | D87: Direto | BA87: 42406
B88: =Language!C323 -> Fator de custo - estação transferência de energia | BA88: 42408
B89: =Language!C324 -> Fator de custo - tubos linha principal de distribuição | BA89: 42410
B90: =Language!C325 -> Fator de custo - tubos linha secundária de distribuição | BA90: 42412
B91: =Language!C326 -> Taxa de câmbio | C91: =Currency&Language!C1292 -> €/CAD | BA91: 42414
F92: =Language!C327 -> Custos das redes de distribuição secundárias e ETEn por condomínio | BA92: 42400
B93: =Language!$C$328 -> Custo - estaçao(ões) transfer. de energia | D93: =SUM(F93:S93) -> 0 | F93: =IF(AH$54=0,"-",IF(AH$54/F$33>$E$314,$D$314*AH$54/F$33,IF(AH$54/F$33<$E$311,$D$311*AH$54/F$33,($D$312*LN(AH$54/F$33)+$D$313)*(AH$54/F$33)))*$F$276*$D$88*F$33*$D$91) -> - | G93: =IF(AI$54=0,"-",IF(AI$54/G$33>$E$314,$D$314*AI$54/G$33,IF(AI$54/G$33<$E$311,$D$311*AI$54/G$33,($D$312*LN(AI$54/G$33)+$D$313)*(AI$54/G$33)))*$F$276*$D$88*G$33*$D$91) -> - | H93: =IF(AJ$54=0,"-",IF(AJ$54/H$33>$E$314,$D$314*AJ$54/H$33,IF(AJ$54/H$33<$E$311,$D$311*AJ$54/H$33,($D$312*LN(AJ$54/H$33)+$D$313)*(AJ$54/H$33)))*$F$276*$D$88*H$33*$D$91) -> - | I93: =IF(AK$54=0,"-",IF(AK$54/I$33>$E$314,$D$314*AK$54/I$33,IF(AK$54/I$33<$E$311,$D$311*AK$54/I$33,($D$312*LN(AK$54/I$33)+$D$313)*(AK$54/I$33)))*$F$276*$D$88*I$33*$D$91) -> - | J93: =IF(AL$54=0,"-",IF(AL$54/J$33>$E$314,$D$314*AL$54/J$33,IF(AL$54/J$33<$E$311,$D$311*AL$54/J$33,($D$312*LN(AL$54/J$33)+$D$313)*(AL$54/J$33)))*$F$276*$D$88*J$33*$D$91) -> - | K93: =IF(AM$54=0,"-",IF(AM$54/K$33>$E$314,$D$314*AM$54/K$33,IF(AM$54/K$33<$E$311,$D$311*AM$54/K$33,($D$312*LN(AM$54/K$33)+$D$313)*(AM$54/K$33)))*$F$276*$D$88*K$33*$D$91) -> - | L93: =IF(AN$54=0,"-",IF(AN$54/L$33>$E$314,$D$314*AN$54/L$33,IF(AN$54/L$33<$E$311,$D$311*AN$54/L$33,($D$312*LN(AN$54/L$33)+$D$313)*(AN$54/L$33)))*$F$276*$D$88*L$33*$D$91) -> - | M93: =IF(AO$54=0,"-",IF(AO$54/M$33>$E$314,$D$314*AO$54/M$33,IF(AO$54/M$33<$E$311,$D$311*AO$54/M$33,($D$312*LN(AO$54/M$33)+$D$313)*(AO$54/M$33)))*$F$276*$D$88*M$33*$D$91) -> - | ... S93: =IF(AU$54=0,"-",IF(AU$54/S$33>$E$314,$D$314*AU$54/S$33,IF(AU$54/S$33<$E$311,$D$311*AU$54/S$33,($D$312*LN(AU$54/S$33)+$D$313)*(AU$54/S$33)))*$F$276*$D$88*S$33*$D$91) -> - | BA93: 42416
B94: =B93 -> Custo - estaçao(ões) transfer. de energia | D94: =SUMIF(AH32:AU32,">0",F94:S94) -> 0 | BA94: 42416
B95: =Language!C329 -> Custo - Tubo linha secundária distribuição | D95: =SUM(F95:S95) -> 0 | F95: =IF(AH$54=0,"-",(LOOKUP(AH$54*(1+$D$81),$D$286:$D$293,$G$286:$G$293)*AH$82*$D$90*$D$91)) -> - | G95: =IF(AI$54=0,"-",(LOOKUP(AI$54*(1+$D$81),$D$286:$D$293,$G$286:$G$293)*AI$82*$D$90*$D$91)) -> - | H95: =IF(AJ$54=0,"-",(LOOKUP(AJ$54*(1+$D$81),$D$286:$D$293,$G$286:$G$293)*AJ$82*$D$90*$D$91)) -> - | I95: =IF(AK$54=0,"-",(LOOKUP(AK$54*(1+$D$81),$D$286:$D$293,$G$286:$G$293)*AK$82*$D$90*$D$91)) -> - | J95: =IF(AL$54=0,"-",(LOOKUP(AL$54*(1+$D$81),$D$286:$D$293,$G$286:$G$293)*AL$82*$D$90*$D$91)) -> - | K95: =IF(AM$54=0,"-",(LOOKUP(AM$54*(1+$D$81),$D$286:$D$293,$G$286:$G$293)*AM$82*$D$90*$D$91)) -> - | L95: =IF(AN$54=0,"-",(LOOKUP(AN$54*(1+$D$81),$D$286:$D$293,$G$286:$G$293)*AN$82*$D$90*$D$91)) -> - | M95: =IF(AO$54=0,"-",(LOOKUP(AO$54*(1+$D$81),$D$286:$D$293,$G$286:$G$293)*AO$82*$D$90*$D$91)) -> - | ... S95: =IF(AU$54=0,"-",(LOOKUP(AU$54*(1+$D$81),$D$286:$D$293,$G$286:$G$293)*AU$82*$D$90*$D$91)) -> - | BA95: 42418
B96: =Language!C329 -> Custo - Tubo linha secundária distribuição | D96: =SUMIF(AH32:AU32,">0",F96:S96) -> 0 | BA96: 42418
B97: =Language!C330 -> Custo Total - conexão do condomínio | D97: =IF($D$86=$G$265,IF(X32>0,D94+D96,"-"),IF(X32>0,D93+D95,"-")) -> 0 | F97: =IF($D$86=$G$265,IF(AH32>0,F94+F96,"-"),IF(AH32>0,F93+F95,"-")) -> #VALUE! | G97: =IF($D$86=$G$265,IF(AI32>0,G94+G96,"-"),IF(AI32>0,G93+G95,"-")) -> - | H97: =IF($D$86=$G$265,IF(AJ32>0,H94+H96,"-"),IF(AJ32>0,H93+H95,"-")) -> - | I97: =IF($D$86=$G$265,IF(AK32>0,I94+I96,"-"),IF(AK32>0,I93+I95,"-")) -> - | J97: =IF($D$86=$G$265,IF(AL32>0,J94+J96,"-"),IF(AL32>0,J93+J95,"-")) -> - | K97: =IF($D$86=$G$265,IF(AM32>0,K94+K96,"-"),IF(AM32>0,K93+K95,"-")) -> - | L97: =IF($D$86=$G$265,IF(AN32>0,L94+L96,"-"),IF(AN32>0,L93+L95,"-")) -> - | M97: =IF($D$86=$G$265,IF(AO32>0,M94+M96,"-"),IF(AO32>0,M93+M95,"-")) -> - | ... S97: =IF($D$86=$G$265,IF(AU32>0,S94+S96,"-"),IF(AU32>0,S93+S95,"-")) -> - | BA97: 42420
B98: =Language!C330 -> Custo Total - conexão do condomínio | D98: =D96+D94 -> 0 | F98: =IF(AH$32=0,"",F94+F96) -> 0 | G98: =IF(AI$32=0,"",G94+G96) | H98: =IF(AJ$32=0,"",H94+H96) | I98: =IF(AK$32=0,"",I94+I96) | J98: =IF(AL$32=0,"",J94+J96) | K98: =IF(AM$32=0,"",K94+K96) | L98: =IF(AN$32=0,"",L94+L96) | M98: =IF(AO$32=0,"",M94+M96) | ... S98: =IF(AU$32=0,"",S94+S96) | BA98: 42420
BA99: 42400
F100: =Language!C335 -> Custo - tubos da linha principal de distribuiçao por categoria de dimensão | BA100: 42400
...

Sheet Modelo Energético 
A1: =Language!C866&'Análise de Emissões'!B188 -> Modelo Energético RETScreen - Projeto produção de Eletricidade | M1: =IF(ISERROR(SUM(M4:M1015)+HideCodeEM_1),6,SUM(M4:M1015)+HideCodeEM_1) -> 30881.192 | N1: 2000000 | Q1: 82490 | R1: =Set_Level -> 2 | S1: 1 | Z1: RadioButtons | AA1: row | AB1: col | AC1: lrow | AD1: lcol | AE1: value | AF1: group | AG1: mLine | AH1: srow | AI1: scol | AJ1: nextRow | AK1: nextCol | AO1: CheckBox | AP1: row | AQ1: columns | AR1: link row | AS1: link column | AT1: srow | AU1: scolumn
N2: 2000000 | R2: =Iniciar!P4 -> 0 | S2: 1 | AA2: 204 | AB2: 3 | AC2: 204 | AD2: 17 | AE2: TRUE | AF2: EE12-1 | AG2: TRUE | AH2: 204 | AI2: 4 | AJ2: 205 | AK2: 17 | AP2: 4 | AQ2: 3 | AR2: 4 | AS2: 13 | AT2: 4 | AU2: 4
A3: ='Análise de Emissões'!B188 -> Projeto produção de Eletricidade | N3: 2000000 | Q3: Project Type | R3: =HideCode_projectType -> 2 | AA3: 204 | AB3: 3 | AC3: 205 | AD3: 17 | AE3: TRUE | AF3: EE12-1 | AG3: TRUE | AH3: 204 | AI3: 4 | AJ3: 204 | AK3: 17 | AP3: 37 | AQ3: 3 | AR3: 37 | AS3: 13 | AT3: 37 | AU3: 4
A4: =Language!C1695 -> Combustíveis & horários | C4: þ | D4: =$G$384 -> Mostrar dado | M4: TRUE | N4: 4010000 | Q4: Latitude of project location | S4: °N | T4: =Iniciar!E49 -> 40.2 | U4: =T4*PI()/180 -> 0.70162236 | AA4: 543 | AB4: 3 | AC4: 542 | AD4: 17 | AE4: TRUE | AF4: EEM_SAH | AG4: FALSE | AP4: 39 | AQ4: 10 | AR4: 39 | AS4: 17 | AT4: 38 | AU4: 10
M5: =IF(EE1_Show1=TRUE,99,79) -> 99 | N5: 4010000 | AA5: 544 | AB5: 3 | AC5: 543 | AD5: 17 | AE5: TRUE | AF5: EEM_SAH | AG5: FALSE | AP5: 41 | AQ5: 10 | AR5: 41 | AS5: 17 | AT5: 41 | AU5: 9
B6: =Language!C574 -> Combustível | E6: =$B$801&" 1" -> Tipo de Combustível 1 | F6: =$B$801&" 2" -> Tipo de Combustível 2 | G6: =$B$801&" 3" -> Tipo de Combustível 3 | H6: =$B$801&" 4" -> Tipo de Combustível 4 | I6: =$B$801&" 5" -> Tipo de Combustível 5 | J6: =$B$801&" 6" -> Tipo de Combustível 6 | M6: =IF(ISERROR('Análise Financeira'!S14+'Análise Financeira'!S22+'Análise Financeira'!S36),3,'Análise Financeira'!S14+'Análise Financeira'!S22+'Análise Financeira'!S36) -> 7460.1915 | N6: 4010004 | AA6: 665 | AB6: 3 | AC6: 664 | AD6: 17 | AE6: TRUE | AF6: EEM-SWH | AG6: FALSE | AP6: 42 | AQ6: 10 | AR6: 42 | AS6: 17 | AT6: 42 | AU6: 9
B7: =$B$801 -> Tipo de Combustível | E7: =$F$1098 -> Eletricidade | N7: 2010106 | AA7: 666 | AB7: 3 | AC7: 665 | AD7: 17 | AE7: TRUE | AF7: EEM-SWH | AG7: FALSE | AP7: 43 | AQ7: 10 | AR7: 43 | AS7: 17 | AT7: 43 | AU7: 9
B8: =Language!C357 -> Consumo de combustível - unitário | E8: =VLOOKUP(E7,LN_FuelList,3,FALSE) -> MWh | F8: =VLOOKUP(F7,LN_FuelList,3,FALSE) -> #N/A | G8: =VLOOKUP(G7,LN_FuelList,3,FALSE) -> #N/A | H8: =VLOOKUP(H7,LN_FuelList,3,FALSE) -> #N/A | I8: =VLOOKUP(I7,LN_FuelList,3,FALSE) -> #N/A | J8: =VLOOKUP(J7,LN_FuelList,3,FALSE) -> #N/A | N8: 111632 | AA8: 827 | AB8: 2 | AC8: 826 | AD8: 17 | AE8: TRUE | AF8: EE_PS | AG8: FALSE | AP8: 44 | AQ8: 10 | AR8: 44 | AS8: 17 | AT8: 44 | AU8: 9
B9: =Language!C359 -> Preço combustível - unidade | E9: =VLOOKUP(E7,LN_FuelList,5,FALSE) -> €/kWh | F9: =VLOOKUP(F7,LN_FuelList,5,FALSE) -> #N/A | G9: =VLOOKUP(G7,LN_FuelList,5,FALSE) -> #N/A | H9: =VLOOKUP(H7,LN_FuelList,5,FALSE) -> #N/A | I9: =VLOOKUP(I7,LN_FuelList,5,FALSE) -> #N/A | J9: =VLOOKUP(J7,LN_FuelList,5,FALSE) -> #N/A | N9: 4010010 | AA9: 827 | AB9: 4 | AC9: 826 | AD9: 18 | AE9: TRUE | AF9: EE_PS | AG9: FALSE | AP9: 45 | AQ9: 10 | AR9: 45 | AS9: 17 | AT9: 45 | AU9: 9
B10: =$B$804 -> Preço do combustível | N10: 4010012 | AA10: 933 | AB10: 3 | AC10: 933 | AD10: 17 | AE10: TRUE | AF10: EEM_UserDef | AG10: FALSE | AP10: 47 | AQ10: 10 | AR10: 47 | AS10: 17 | AT10: 47 | AU10: 9
N11: 4010004 | AA11: 934 | AB11: 3 | AC11: 934 | AD11: 17 | AE11: TRUE | AF11: EEM_UserDef | AG11: FALSE | AP11: 48 | AQ11: 10 | AR11: 48 | AS11: 17 | AT11: 48 | AU11: 9
N12: 4010004 | AA12: 935 | AB12: 3 | AC12: 935 | AD12: 17 | AE12: TRUE | AF12: EEM_UserDef | AG12: FALSE | AP12: 49 | AQ12: 10 | AR12: 49 | AS12: 17 | AT12: 49 | AU12: 9
B13: =Language!C2469 -> Horário | C13: =C221 -> Unidade | E13: =B13&" 1" -> Horário 1 | F13: =B13&" 2" -> Horário 2 | G13: =B13&" 3" -> Horário 3 | H13: =B13&" 4" -> Horário 4 | I13: =B13&" 5" -> Horário 5 | J13: =B13&" 6" -> Horário 6 | N13: 4010014 | AP13: 50 | AQ13: 10 | AR13: 50 | AS13: 17 | AT13: 50 | AU13: 9
B14: =B206 -> Descrição | E14: =Language!C2316 -> 24/7 | N14: 4010016 | AP14: 51 | AQ14: 10 | AR14: 51 | AS14: 17 | AT14: 51 | AU14: 9
F15: =Language!C2445 -> Ocupado | G15: =$F$15 -> Ocupado | H15: =$F$15 -> Ocupado | I15: =$F$15 -> Ocupado | J15: =$F$15 -> Ocupado | N15: 4010014 | AP15: 53 | AQ15: 10 | AR15: 53 | AS15: 17 | AT15: 53 | AU15: 9
B16: =Language!C2019 -> Temperatura - aquecimento ambiental | C16: °C | N16: 4010018 | P16: =IF(OR(C16=$C$1178,C16=""),1,5/9) -> 1 | Q16: =$P16*(E16+40)-40 -> 0 | R16: =$P16*(F16+40)-40 -> 0 | S16: =$P16*(G16+40)-40 -> 0 | T16: =$P16*(H16+40)-40 -> 0 | U16: =$P16*(I16+40)-40 -> 0 | V16: =$P16*(J16+40)-40 -> 0 | AP16: 54 | AQ16: 10 | AR16: 54 | AS16: 17 | AT16: 54 | AU16: 9
B17: =Language!C2018 -> Temperatura - refrigeração ambiental | C17: °C | N17: 4010020 | P17: =IF(OR(C17=$C$1178,C17=""),1,5/9) -> 1 | Q17: =$P17*(E17+40)-40 -> 0 | R17: =$P17*(F17+40)-40 -> 0 | S17: =$P17*(G17+40)-40 -> 0 | T17: =$P17*(H17+40)-40 -> 0 | U17: =$P17*(I17+40)-40 -> 0 | V17: =$P17*(J17+40)-40 -> 0 | AP17: 55 | AQ17: 10 | AR17: 55 | AS17: 17 | AT17: 55 | AU17: 9
F18: =Language!C2507 -> Desocupado | G18: =$F$18 -> Desocupado | H18: =$F$18 -> Desocupado | I18: =$F$18 -> Desocupado | J18: =$F$18 -> Desocupado | N18: 4010014 | AP18: 56 | AQ18: 10 | AR18: 56 | AS18: 17 | AT18: 56 | AU18: 9
B19: =Language!C2020 -> Temperatura - desocupado | C19: +/-°C | N19: 4010022 | P19: =IF(OR(C19=$F$1174,C19=""),1,5/9) -> 1 | R19: =$P19*(F19) -> 0 | S19: =$P19*(G19) -> 0 | T19: =$P19*(H19) -> 0 | U19: =$P19*(I19) -> 0 | V19: =$P19*(J19) -> 0 | AP19: 57 | AQ19: 10 | AR19: 57 | AS19: 17 | AT19: 57 | AU19: 9
F20: =F15 -> Ocupado | G20: =G15 -> Ocupado | H20: =H15 -> Ocupado | I20: =I15 -> Ocupado | J20: =J15 -> Ocupado | N20: 4010014 | AP20: 59 | AQ20: 10 | AR20: 59 | AS20: 17 | AT20: 59 | AU20: 9
B21: =Language!C2444 -> Taxa de ocupação - diária | E21: =Language!C2208 -> h/d | F21: =$E$21 -> h/d | G21: =$E$21 -> h/d | H21: =$E$21 -> h/d | I21: =$E$21 -> h/d | J21: =$E$21 -> h/d | N21: 4010024 | AP21: 60 | AQ21: 10 | AR21: 60 | AS21: 17 | AT21: 60 | AU21: 9
B22: =Language!C2429 -> Segunda Feira | E22: 24 | N22: 4010024 | AP22: 61 | AQ22: 10 | AR22: 61 | AS22: 17 | AT22: 61 | AU22: 9
B23: =Language!C2502 -> Terça feira | E23: 24 | N23: 4010024 | AP23: 62 | AQ23: 10 | AR23: 62 | AS23: 17 | AT23: 62 | AU23: 9
B24: =Language!C2519 -> Quarta feira | E24: 24 | N24: 4010024 | AP24: 63 | AQ24: 10 | AR24: 63 | AS24: 17 | AT24: 63 | AU24: 9
B25: =Language!C2500 -> Quinta feira | E25: 24 | N25: 4010024 | AP25: 65 | AQ25: 10 | AR25: 65 | AS25: 17 | AT25: 65 | AU25: 9
B26: =Language!C2379 -> Sexta feira | E26: 24 | N26: 4010024 | AP26: 66 | AQ26: 10 | AR26: 66 | AS26: 17 | AT26: 66 | AU26: 9
B27: =Language!C2468 -> Sábado | E27: 24 | N27: 4010024 | AP27: 67 | AQ27: 10 | AR27: 67 | AS27: 17 | AT27: 67 | AU27: 9
B28: =Language!C2492 -> Domingo | E28: 24 | N28: 4010024 | AP28: 68 | AQ28: 10 | AR28: 68 | AS28: 17 | AT28: 68 | AU28: 9
B29: =Language!C2443 -> Taxa de ocupação - anual | C29: =Language!C2210 -> h/ano | E29: 8760 | F29: =SUM(F22:F28)*8760/24/7 -> 0 | G29: =SUM(G22:G28)*8760/24/7 -> 0 | H29: =SUM(H22:H28)*8760/24/7 -> 0 | I29: =SUM(I22:I28)*8760/24/7 -> 0 | J29: =SUM(J22:J28)*8760/24/7 -> 0 | N29: 4010026 | AP29: 69 | AQ29: 10 | AR29: 69 | AS29: 17 | AT29: 69 | AU29: 9
C30: =$C$254 -> % | E30: 1 | F30: =F29/8760 -> 0 | G30: =G29/8760 -> 0 | H30: =H29/8760 -> 0 | I30: =I29/8760 -> 0 | J30: =J29/8760 -> 0 | N30: 4010026 | AP30: 71 | AQ30: 10 | AR30: 71 | AS30: 17 | AT30: 71 | AU30: 9
N31: 4010014 | AP31: 72 | AQ31: 10 | AR31: 72 | AS31: 17 | AT31: 72 | AU31: 9
B32: =Language!C1722 -> Temperatura de comutação aquec./ refrigeração | C32: °C | D32: 16 | N32: 4010028 | P32: =IF(OR(C32=$C$1178,C32=""),1,5/9) -> 1 | Q32: =$P32*(D32+40)-40 -> 16 | AP32: 73 | AQ32: 10 | AR32: 73 | AS32: 17 | AT32: 73 | AU32: 9
B33: =Language!C1779 -> Duração da estação de calor | C33: =Language!C2197 -> d | D33: =365-D34 -> 166 | N33: 4010030 | AP33: 74 | AQ33: 10 | AR33: 74 | AS33: 17 | AT33: 74 | AU33: 9
B34: =Language!C1778 -> Duração da estação de frio | C34: =C33 -> d | D34: ='EET2'!D73 -> 199 | N34: 4010032 | S34: =Language!C1688 -> Consumo de combustível - caso de referência | T34: 1 | AP34: 75 | AQ34: 10 | AR34: 75 | AS34: 17 | AT34: 75 | AU34: 9
N35: 4010000 | S35: =Language!C1690 -> Consumo de combustível - caso proposto | T35: 3 | V35: =VLOOKUP(C39,W35:X37,2,FALSE) -> 3.6 | W35: =R182 -> MWh | X35: 1 | AP35: 77 | AQ35: 10 | AR35: 77 | AS35: 17 | AT35: 77 | AU35: 9
M36: =IF(M37=TRUE,90,79) -> 90 | N36: 12000 | S36: =Language!C1693 -> Economia de combustível | T36: 2 | W36: =R184 -> GJ | X36: 3.6 | AP36: 78 | AQ36: 10 | AR36: 78 | AS36: 17 | AT36: 78 | AU36: 9
A37: =Language!C1646 -> Caracarterísticas da instalação | C37: þ | D37: =$G$384 -> Mostrar dado | M37: TRUE | N37: 4020000 | S37: =Language!C2605 -> Demanda de energia - caso de referência | T37: 4 | W37: =Language!C1382 -> milhão Btu | X37: 3.4121416 | AP37: 79 | AQ37: 10 | AR37: 79 | AS37: 17 | AT37: 79 | AU37: 9
B38: =Language!C1969 -> Mostrar: | C38: =C172 -> Aquecimento | D38: =D172 -> Refrigeração | E38: =$F$1098 -> Eletricidade | F38: =$G$244 -> Custo inicial incremental | G38: =Language!C2382 -> Economia - custo de combustível | H38: =Language!C2403 -> Economia de O&M incremental | I38: =B1013 -> Retorno simples | J38: =Language!C1745 -> Inclui a medida ? | M38: =Iniciar!N22 -> 4 | N38: 4020000 | S38: =Language!C2606 -> Demanda de energia - caso proposto | T38: 5 | AP38: 80 | AQ38: 10 | AR38: 80 | AS38: 17 | AT38: 80 | AU38: 9
B39: Economia de combustível | C39: GJ | D39: =$C$39 -> GJ | E39: =$C$39 -> GJ | F39: =Currency -> € | G39: =Currency -> € | H39: =Currency -> € | I39: =C1014 -> ano | J39: ¨ | M39: =EET!BU15 -> 0 | N39: 4020000 | Q39: FALSE | R39: =IF(ISERROR(VLOOKUP(B39,S34:T45,2,FALSE)),4,VLOOKUP(B39,S34:T45,2,FALSE)) -> 2 | S39: =Language!C1635 -> Economia de energia | T39: 6 | AP39: 81 | AQ39: 10 | AR39: 81 | AS39: 17 | AT39: 81 | AU39: 9
B40: =Language!C1283 -> Sistema de Aquecimento | N40: 12100 | Q40: =COUNTIF(Q41:Q148,FALSE) -> 0 | AP40: 83 | AQ40: 10 | AR40: 83 | AS40: 17 | AT40: 83 | AU40: 9
B41: =IF(EET!D16="","",EET!D16) | C41: =IF($R$39=1,0,IF($R$39=2,EET!AL16,0))*$V$35 -> 0 | D41: - | E41: - | F41: =EET!E16 -> 0 | G41: =EET!F16 -> 0 | H41: =EET!G16 -> 0 | I41: =IF(ISERROR(F41/(G41+H41)),"-",F41/(G41+H41)) -> - | J41: þ | M41: =IF(OR(EET!BU16>0,Q41=""),1,0) -> 0 | N41: 12100 | Q41: TRUE | V41: TRUE | W41: TRUE | AP41: 84 | AQ41: 10 | AR41: 84 | AS41: 17 | AT41: 84 | AU41: 9
B42: =IF(EET!D17="","",EET!D17) | C42: =IF($R$39=1,0,IF($R$39=2,EET!AL17,0))*$V$35 -> 0 | D42: - | E42: - | F42: =EET!E17 -> 0 | G42: =EET!F17 -> 0 | H42: =EET!G17 -> 0 | I42: =IF(ISERROR(F42/(G42+H42)),"-",F42/(G42+H42)) -> - | J42: þ | M42: =IF(OR(EET!BU17>0,Q42=""),1,0) -> 0 | N42: 12100 | Q42: TRUE | V42: TRUE | W42: TRUE | AP42: 85 | AQ42: 10 | AR42: 85 | AS42: 17 | AT42: 85 | AU42: 9
B43: =IF(EET!D18="","",EET!D18) | C43: =IF($R$39=1,0,IF($R$39=2,EET!AL18,0))*$V$35 -> 0 | D43: - | E43: - | F43: =EET!E18 -> 0 | G43: =EET!F18 -> 0 | H43: =EET!G18 -> 0 | I43: =IF(ISERROR(F43/(G43+H43)),"-",F43/(G43+H43)) -> - | J43: þ | M43: =IF(OR(EET!BU18>0,Q43=""),1,0) -> 0 | N43: 12100 | Q43: TRUE | V43: TRUE | W43: TRUE | AP43: 86 | AQ43: 10 | AR43: 86 | AS43: 17 | AT43: 86 | AU43: 9
B44: =IF(EET!D19="","",EET!D19) | C44: =IF($R$39=1,0,IF($R$39=2,EET!AL19,0))*$V$35 -> 0 | D44: - | E44: - | F44: =EET!E19 -> 0 | G44: =EET!F19 -> 0 | H44: =EET!G19 -> 0 | I44: =IF(ISERROR(F44/(G44+H44)),"-",F44/(G44+H44)) -> - | J44: þ | M44: =IF(OR(EET!BU19>0,Q44=""),1,0) -> 0 | N44: 12100 | Q44: TRUE | V44: TRUE | W44: TRUE | AP44: 87 | AQ44: 10 | AR44: 87 | AS44: 17 | AT44: 87 | AU44: 9
B45: =IF(EET!D20="","",EET!D20) | C45: =IF($R$39=1,0,IF($R$39=2,EET!AL20,0))*$V$35 -> 0 | D45: - | E45: - | F45: =EET!E20 -> 0 | G45: =EET!F20 -> 0 | H45: =EET!G20 -> 0 | I45: =IF(ISERROR(F45/(G45+H45)),"-",F45/(G45+H45)) -> - | J45: þ | M45: =IF(OR(EET!BU20>0,Q45=""),1,0) -> 0 | N45: 12100 | Q45: TRUE | V45: TRUE | W45: TRUE | AP45: 89 | AQ45: 10 | AR45: 89 | AS45: 17 | AT45: 89 | AU45: 9
B46: =Language!C542 -> Sistema de refrigeração | M46: =IF(OR(EET!BU21>0,Q46=""),1,0) -> 1 | N46: 12110 | AP46: 90 | AQ46: 10 | AR46: 90 | AS46: 17 | AT46: 90 | AU46: 9
B47: =IF(EET!D22="","",EET!D22) | C47: - | D47: =IF($R$39=1,0,IF($R$39=2,EET!AL22,0))*$V$35 -> 0 | E47: - | F47: =EET!E22 -> 0 | G47: =EET!F22 -> 0 | H47: =EET!G22 -> 0 | I47: =IF(ISERROR(F47/(G47+H47)),"-",F47/(G47+H47)) -> - | J47: þ | M47: =IF(OR(EET!BU22>0,Q47=""),1,0) -> 0 | N47: 12110 | Q47: TRUE | V47: TRUE | W47: TRUE | AP47: 91 | AQ47: 10 | AR47: 91 | AS47: 17 | AT47: 91 | AU47: 9
B48: =IF(EET!D23="","",EET!D23) | C48: - | D48: =IF($R$39=1,0,IF($R$39=2,EET!AL23,0))*$V$35 -> 0 | E48: - | F48: =EET!E23 -> 0 | G48: =EET!F23 -> 0 | H48: =EET!G23 -> 0 | I48: =IF(ISERROR(F48/(G48+H48)),"-",F48/(G48+H48)) -> - | J48: þ | M48: =IF(OR(EET!BU23>0,Q48=""),1,0) -> 0 | N48: 12110 | Q48: TRUE | V48: TRUE | W48: TRUE | AP48: 92 | AQ48: 10 | AR48: 92 | AS48: 17 | AT48: 92 | AU48: 9
B49: =IF(EET!D24="","",EET!D24) | C49: - | D49: =IF($R$39=1,0,IF($R$39=2,EET!AL24,0))*$V$35 -> 0 | E49: - | F49: =EET!E24 -> 0 | G49: =EET!F24 -> 0 | H49: =EET!G24 -> 0 | I49: =IF(ISERROR(F49/(G49+H49)),"-",F49/(G49+H49)) -> - | J49: þ | M49: =IF(OR(EET!BU24>0,Q49=""),1,0) -> 0 | N49: 12110 | Q49: TRUE | V49: TRUE | W49: TRUE | AP49: 93 | AQ49: 10 | AR49: 93 | AS49: 17 | AT49: 93 | AU49: 9
B50: =IF(EET!D25="","",EET!D25) | C50: - | D50: =IF($R$39=1,0,IF($R$39=2,EET!AL25,0))*$V$35 -> 0 | E50: - | F50: =EET!E25 -> 0 | G50: =EET!F25 -> 0 | H50: =EET!G25 -> 0 | I50: =IF(ISERROR(F50/(G50+H50)),"-",F50/(G50+H50)) -> - | J50: þ | M50: =IF(OR(EET!BU25>0,Q50=""),1,0) -> 0 | N50: 12110 | Q50: TRUE | V50: TRUE | W50: TRUE | AP50: 95 | AQ50: 10 | AR50: 95 | AS50: 17 | AT50: 95 | AU50: 9
B51: =IF(EET!D26="","",EET!D26) | C51: - | D51: =IF($R$39=1,0,IF($R$39=2,EET!AL26,0))*$V$35 -> 0 | E51: - | F51: =EET!E26 -> 0 | G51: =EET!F26 -> 0 | H51: =EET!G26 -> 0 | I51: =IF(ISERROR(F51/(G51+H51)),"-",F51/(G51+H51)) -> - | J51: þ | M51: =IF(OR(EET!BU26>0,Q51=""),1,0) -> 0 | N51: 12110 | Q51: TRUE | V51: TRUE | W51: TRUE | AP51: 96 | AQ51: 10 | AR51: 96 | AS51: 17 | AT51: 96 | AU51: 9
B52: =Language!C2328 -> Invólucro do prédio | M52: =IF(OR(EET!BU27>0,Q52=""),1,0) -> 1 | N52: 12120 | AP52: 97 | AQ52: 10 | AR52: 97 | AS52: 17 | AT52: 97 | AU52: 9
B53: =IF(EET!D28="","",EET!D28) | C53: =IF($R$39=1,EET!X28,IF($R$39=2,EET!AG28,IF($R$39=3,EET!AF28,IF($R$39=4,EET!T28,IF($R$39=5,EET!AB28,EET!T28-EET!AB28)))))*$V$35 -> 0 | D53: =IF($R$39=1,EET!AS28,IF($R$39=2,EET!BB28,IF($R$39=3,EET!BA28,IF($R$39=4,EET!AO28,IF($R$39=5,EET!AW28,EET!AO28-EET!AW28)))))*$V$35 -> 0 | E53: - | F53: =EET!E28 -> 0 | G53: =EET!F28 -> 0 | H53: =EET!G28 -> 0 | I53: =IF(ISERROR(F53/(G53+H53)),"-",F53/(G53+H53)) -> - | J53: þ | M53: =IF(OR(EET!BU28>0,Q53=""),1,0) -> 0 | N53: 12120 | Q53: TRUE | V53: TRUE | W53: TRUE | AP53: 98 | AQ53: 10 | AR53: 98 | AS53: 17 | AT53: 98 | AU53: 9
B54: =IF(EET!D29="","",EET!D29) | C54: =IF($R$39=1,EET!X29,IF($R$39=2,EET!AG29,IF($R$39=3,EET!AF29,IF($R$39=4,EET!T29,IF($R$39=5,EET!AB29,EET!T29-EET!AB29)))))*$V$35 -> 0 | D54: =IF($R$39=1,EET!AS29,IF($R$39=2,EET!BB29,IF($R$39=3,EET!BA29,IF($R$39=4,EET!AO29,IF($R$39=5,EET!AW29,EET!AO29-EET!AW29)))))*$V$35 -> 0 | E54: - | F54: =EET!E29 -> 0 | G54: =EET!F29 -> 0 | H54: =EET!G29 -> 0 | I54: =IF(ISERROR(F54/(G54+H54)),"-",F54/(G54+H54)) -> - | J54: þ | M54: =IF(OR(EET!BU29>0,Q54=""),1,0) -> 0 | N54: 12120 | Q54: TRUE | V54: TRUE | W54: TRUE | AP54: 99 | AQ54: 10 | AR54: 99 | AS54: 17 | AT54: 99 | AU54: 9
B55: =IF(EET!D30="","",EET!D30) | C55: =IF($R$39=1,EET!X30,IF($R$39=2,EET!AG30,IF($R$39=3,EET!AF30,IF($R$39=4,EET!T30,IF($R$39=5,EET!AB30,EET!T30-EET!AB30)))))*$V$35 -> 0 | D55: =IF($R$39=1,EET!AS30,IF($R$39=2,EET!BB30,IF($R$39=3,EET!BA30,IF($R$39=4,EET!AO30,IF($R$39=5,EET!AW30,EET!AO30-EET!AW30)))))*$V$35 -> 0 | E55: - | F55: =EET!E30 -> 0 | G55: =EET!F30 -> 0 | H55: =EET!G30 -> 0 | I55: =IF(ISERROR(F55/(G55+H55)),"-",F55/(G55+H55)) -> - | J55: þ | M55: =IF(OR(EET!BU30>0,Q55=""),1,0) -> 0 | N55: 12120 | Q55: TRUE | V55: TRUE | W55: TRUE | AP55: 101 | AQ55: 10 | AR55: 101 | AS55: 17 | AT55: 101 | AU55: 9
B56: =IF(EET!D31="","",EET!D31) | C56: =IF($R$39=1,EET!X31,IF($R$39=2,EET!AG31,IF($R$39=3,EET!AF31,IF($R$39=4,EET!T31,IF($R$39=5,EET!AB31,EET!T31-EET!AB31)))))*$V$35 -> 0 | D56: =IF($R$39=1,EET!AS31,IF($R$39=2,EET!BB31,IF($R$39=3,EET!BA31,IF($R$39=4,EET!AO31,IF($R$39=5,EET!AW31,EET!AO31-EET!AW31)))))*$V$35 -> 0 | E56: - | F56: =EET!E31 -> 0 | G56: =EET!F31 -> 0 | H56: =EET!G31 -> 0 | I56: =IF(ISERROR(F56/(G56+H56)),"-",F56/(G56+H56)) -> - | J56: þ | M56: =IF(OR(EET!BU31>0,Q56=""),1,0) -> 0 | N56: 12120 | Q56: TRUE | V56: TRUE | W56: TRUE | AP56: 102 | AQ56: 10 | AR56: 102 | AS56: 17 | AT56: 102 | AU56: 9
B57: =IF(EET!D32="","",EET!D32) | C57: =IF($R$39=1,EET!X32,IF($R$39=2,EET!AG32,IF($R$39=3,EET!AF32,IF($R$39=4,EET!T32,IF($R$39=5,EET!AB32,EET!T32-EET!AB32)))))*$V$35 -> 0 | D57: =IF($R$39=1,EET!AS32,IF($R$39=2,EET!BB32,IF($R$39=3,EET!BA32,IF($R$39=4,EET!AO32,IF($R$39=5,EET!AW32,EET!AO32-EET!AW32)))))*$V$35 -> 0 | E57: - | F57: =EET!E32 -> 0 | G57: =EET!F32 -> 0 | H57: =EET!G32 -> 0 | I57: =IF(ISERROR(F57/(G57+H57)),"-",F57/(G57+H57)) -> - | J57: þ | M57: =IF(OR(EET!BU32>0,Q57=""),1,0) -> 0 | N57: 12120 | Q57: TRUE | V57: TRUE | W57: TRUE | AP57: 103 | AQ57: 10 | AR57: 103 | AS57: 17 | AT57: 103 | AU57: 9
B58: =Language!C2062 -> Ventilação | M58: =IF(OR(EET!BU33>0,Q58=""),1,0) -> 1 | N58: 12130 | AP58: 104 | AQ58: 10 | AR58: 104 | AS58: 17 | AT58: 104 | AU58: 9
B59: =IF(EET!D34="","",EET!D34) | C59: =IF($R$39=1,EET!X34,IF($R$39=2,EET!AG34,IF($R$39=3,EET!AF34,IF($R$39=4,EET!T34,IF($R$39=5,EET!AB34,EET!T34-EET!AB34)))))*$V$35 -> 0 | D59: =IF($R$39=1,EET!AS34,IF($R$39=2,EET!BB34,IF($R$39=3,EET!BA34,IF($R$39=4,EET!AO34,IF($R$39=5,EET!AW34,EET!AO34-EET!AW34)))))*$V$35 -> 0 | E59: - | F59: =EET!E34 -> 0 | G59: =EET!F34 -> 0 | H59: =EET!G34 -> 0 | I59: =IF(ISERROR(F59/(G59+H59)),"-",F59/(G59+H59)) -> - | J59: þ | M59: =IF(OR(EET!BU34>0,Q59=""),1,0) -> 0 | N59: 12130 | Q59: TRUE | V59: TRUE | W59: TRUE | AP59: 105 | AQ59: 10 | AR59: 105 | AS59: 17 | AT59: 105 | AU59: 9
B60: =IF(EET!D35="","",EET!D35) | C60: =IF($R$39=1,EET!X35,IF($R$39=2,EET!AG35,IF($R$39=3,EET!AF35,IF($R$39=4,EET!T35,IF($R$39=5,EET!AB35,EET!T35-EET!AB35)))))*$V$35 -> 0 | D60: =IF($R$39=1,EET!AS35,IF($R$39=2,EET!BB35,IF($R$39=3,EET!BA35,IF($R$39=4,EET!AO35,IF($R$39=5,EET!AW35,EET!AO35-EET!AW35)))))*$V$35 -> 0 | E60: - | F60: =EET!E35 -> 0 | G60: =EET!F35 -> 0 | H60: =EET!G35 -> 0 | I60: =IF(ISERROR(F60/(G60+H60)),"-",F60/(G60+H60)) -> - | J60: þ | M60: =IF(OR(EET!BU35>0,Q60=""),1,0) -> 0 | N60: 12130 | Q60: TRUE | V60: TRUE | W60: TRUE | AP60: 107 | AQ60: 10 | AR60: 107 | AS60: 17 | AT60: 107 | AU60: 9
B61: =IF(EET!D36="","",EET!D36) | C61: =IF($R$39=1,EET!X36,IF($R$39=2,EET!AG36,IF($R$39=3,EET!AF36,IF($R$39=4,EET!T36,IF($R$39=5,EET!AB36,EET!T36-EET!AB36)))))*$V$35 -> 0 | D61: =IF($R$39=1,EET!AS36,IF($R$39=2,EET!BB36,IF($R$39=3,EET!BA36,IF($R$39=4,EET!AO36,IF($R$39=5,EET!AW36,EET!AO36-EET!AW36)))))*$V$35 -> 0 | E61: - | F61: =EET!E36 -> 0 | G61: =EET!F36 -> 0 | H61: =EET!G36 -> 0 | I61: =IF(ISERROR(F61/(G61+H61)),"-",F61/(G61+H61)) -> - | J61: þ | M61: =IF(OR(EET!BU36>0,Q61=""),1,0) -> 0 | N61: 12130 | Q61: TRUE | V61: TRUE | W61: TRUE | AP61: 108 | AQ61: 10 | AR61: 108 | AS61: 17 | AT61: 108 | AU61: 9
B62: =IF(EET!D37="","",EET!D37) | C62: =IF($R$39=1,EET!X37,IF($R$39=2,EET!AG37,IF($R$39=3,EET!AF37,IF($R$39=4,EET!T37,IF($R$39=5,EET!AB37,EET!T37-EET!AB37)))))*$V$35 -> 0 | D62: =IF($R$39=1,EET!AS37,IF($R$39=2,EET!BB37,IF($R$39=3,EET!BA37,IF($R$39=4,EET!AO37,IF($R$39=5,EET!AW37,EET!AO37-EET!AW37)))))*$V$35 -> 0 | E62: - | F62: =EET!E37 -> 0 | G62: =EET!F37 -> 0 | H62: =EET!G37 -> 0 | I62: =IF(ISERROR(F62/(G62+H62)),"-",F62/(G62+H62)) -> - | J62: þ | M62: =IF(OR(EET!BU37>0,Q62=""),1,0) -> 0 | N62: 12130 | Q62: TRUE | V62: TRUE | W62: TRUE | AP62: 109 | AQ62: 10 | AR62: 109 | AS62: 17 | AT62: 109 | AU62: 9
B63: =IF(EET!D38="","",EET!D38) | C63: =IF($R$39=1,EET!X38,IF($R$39=2,EET!AG38,IF($R$39=3,EET!AF38,IF($R$39=4,EET!T38,IF($R$39=5,EET!AB38,EET!T38-EET!AB38)))))*$V$35 -> 0 | D63: =IF($R$39=1,EET!AS38,IF($R$39=2,EET!BB38,IF($R$39=3,EET!BA38,IF($R$39=4,EET!AO38,IF($R$39=5,EET!AW38,EET!AO38-EET!AW38)))))*$V$35 -> 0 | E63: - | F63: =EET!E38 -> 0 | G63: =EET!F38 -> 0 | H63: =EET!G38 -> 0 | I63: =IF(ISERROR(F63/(G63+H63)),"-",F63/(G63+H63)) -> - | J63: þ | M63: =IF(OR(EET!BU38>0,Q63=""),1,0) -> 0 | N63: 12130 | Q63: TRUE | V63: TRUE | W63: TRUE | AP63: 110 | AQ63: 10 | AR63: 110 | AS63: 17 | AT63: 110 | AU63: 9
B64: =Language!C2422 -> Lâmpadas | M64: =IF(OR(EET!BU39>0,Q64=""),1,0) -> 1 | N64: 12140 | AP64: 111 | AQ64: 10 | AR64: 111 | AS64: 17 | AT64: 111 | AU64: 9
B65: =IF(EET!D40="","",EET!D40) | C65: - | D65: - | E65: =IF(OR($R$39=1,$R$39=4),EET!BI40,IF(OR($R$39=6,$R$39=2),EET!BI40-EET!BK40,EET!BK40))*$V$35 -> 0 | F65: =EET!E40 -> 0 | G65: =EET!F40 -> 0 | H65: =EET!G40 -> 0 | I65: =IF(ISERROR(F65/(G65+H65)),"-",F65/(G65+H65)) -> - | J65: þ | M65: =IF(OR(EET!BU40>0,Q65=""),1,0) -> 0 | N65: 12140 | Q65: TRUE | V65: TRUE | W65: TRUE | AP65: 113 | AQ65: 10 | AR65: 113 | AS65: 17 | AT65: 113 | AU65: 9
B66: =IF(EET!D41="","",EET!D41) | C66: - | D66: - | E66: =IF(OR($R$39=1,$R$39=4),EET!BI41,IF(OR($R$39=6,$R$39=2),EET!BI41-EET!BK41,EET!BK41))*$V$35 -> 0 | F66: =EET!E41 -> 0 | G66: =EET!F41 -> 0 | H66: =EET!G41 -> 0 | I66: =IF(ISERROR(F66/(G66+H66)),"-",F66/(G66+H66)) -> - | J66: þ | M66: =IF(OR(EET!BU41>0,Q66=""),1,0) -> 0 | N66: 12140 | Q66: TRUE | V66: TRUE | W66: TRUE | AP66: 114 | AQ66: 10 | AR66: 114 | AS66: 17 | AT66: 114 | AU66: 9
B67: =IF(EET!D42="","",EET!D42) | C67: - | D67: - | E67: =IF(OR($R$39=1,$R$39=4),EET!BI42,IF(OR($R$39=6,$R$39=2),EET!BI42-EET!BK42,EET!BK42))*$V$35 -> 0 | F67: =EET!E42 -> 0 | G67: =EET!F42 -> 0 | H67: =EET!G42 -> 0 | I67: =IF(ISERROR(F67/(G67+H67)),"-",F67/(G67+H67)) -> - | J67: þ | M67: =IF(OR(EET!BU42>0,Q67=""),1,0) -> 0 | N67: 12140 | Q67: TRUE | V67: TRUE | W67: TRUE | AP67: 115 | AQ67: 10 | AR67: 115 | AS67: 17 | AT67: 115 | AU67: 9
B68: =IF(EET!D43="","",EET!D43) | C68: - | D68: - | E68: =IF(OR($R$39=1,$R$39=4),EET!BI43,IF(OR($R$39=6,$R$39=2),EET!BI43-EET!BK43,EET!BK43))*$V$35 -> 0 | F68: =EET!E43 -> 0 | G68: =EET!F43 -> 0 | H68: =EET!G43 -> 0 | I68: =IF(ISERROR(F68/(G68+H68)),"-",F68/(G68+H68)) -> - | J68: þ | M68: =IF(OR(EET!BU43>0,Q68=""),1,0) -> 0 | N68: 12140 | Q68: TRUE | V68: TRUE | W68: TRUE | AP68: 116 | AQ68: 10 | AR68: 116 | AS68: 17 | AT68: 116 | AU68: 9
B69: =IF(EET!D44="","",EET!D44) | C69: - | D69: - | E69: =IF(OR($R$39=1,$R$39=4),EET!BI44,IF(OR($R$39=6,$R$39=2),EET!BI44-EET!BK44,EET!BK44))*$V$35 -> 0 | F69: =EET!E44 -> 0 | G69: =EET!F44 -> 0 | H69: =EET!G44 -> 0 | I69: =IF(ISERROR(F69/(G69+H69)),"-",F69/(G69+H69)) -> - | J69: þ | M69: =IF(OR(EET!BU44>0,Q69=""),1,0) -> 0 | N69: 12140 | Q69: TRUE | V69: TRUE | W69: TRUE | AP69: 117 | AQ69: 10 | AR69: 117 | AS69: 17 | AT69: 117 | AU69: 9
B70: =Language!C2582 -> Equipamento elétrico | M70: =IF(OR(EET!BU45>0,Q70=""),1,0) -> 1 | N70: 12150 | AP70: 119 | AQ70: 10 | AR70: 119 | AS70: 17 | AT70: 119 | AU70: 9
B71: =IF(EET!D46="","",EET!D46) | C71: - | D71: - | E71: =IF(OR($R$39=1,$R$39=4),EET!BI46,IF(OR($R$39=6,$R$39=2),EET!BI46-EET!BK46,EET!BK46))*$V$35 -> 0 | F71: =EET!E46 -> 0 | G71: =EET!F46 -> 0 | H71: =EET!G46 -> 0 | I71: =IF(ISERROR(F71/(G71+H71)),"-",F71/(G71+H71)) -> - | J71: þ | M71: =IF(OR(EET!BU46>0,Q71=""),1,0) -> 0 | N71: 12150 | Q71: TRUE | V71: TRUE | W71: TRUE | AP71: 120 | AQ71: 10 | AR71: 120 | AS71: 17 | AT71: 120 | AU71: 9
B72: =IF(EET!D47="","",EET!D47) | C72: - | D72: - | E72: =IF(OR($R$39=1,$R$39=4),EET!BI47,IF(OR($R$39=6,$R$39=2),EET!BI47-EET!BK47,EET!BK47))*$V$35 -> 0 | F72: =EET!E47 -> 0 | G72: =EET!F47 -> 0 | H72: =EET!G47 -> 0 | I72: =IF(ISERROR(F72/(G72+H72)),"-",F72/(G72+H72)) -> - | J72: þ | M72: =IF(OR(EET!BU47>0,Q72=""),1,0) -> 0 | N72: 12150 | Q72: TRUE | V72: TRUE | W72: TRUE | AP72: 121 | AQ72: 10 | AR72: 121 | AS72: 17 | AT72: 121 | AU72: 9
B73: =IF(EET!D48="","",EET!D48) | C73: - | D73: - | E73: =IF(OR($R$39=1,$R$39=4),EET!BI48,IF(OR($R$39=6,$R$39=2),EET!BI48-EET!BK48,EET!BK48))*$V$35 -> 0 | F73: =EET!E48 -> 0 | G73: =EET!F48 -> 0 | H73: =EET!G48 -> 0 | I73: =IF(ISERROR(F73/(G73+H73)),"-",F73/(G73+H73)) -> - | J73: þ | M73: =IF(OR(EET!BU48>0,Q73=""),1,0) -> 0 | N73: 12150 | Q73: TRUE | V73: TRUE | W73: TRUE | AP73: 122 | AQ73: 10 | AR73: 122 | AS73: 17 | AT73: 122 | AU73: 9
B74: =IF(EET!D49="","",EET!D49) | C74: - | D74: - | E74: =IF(OR($R$39=1,$R$39=4),EET!BI49,IF(OR($R$39=6,$R$39=2),EET!BI49-EET!BK49,EET!BK49))*$V$35 -> 0 | F74: =EET!E49 -> 0 | G74: =EET!F49 -> 0 | H74: =EET!G49 -> 0 | I74: =IF(ISERROR(F74/(G74+H74)),"-",F74/(G74+H74)) -> - | J74: þ | M74: =IF(OR(EET!BU49>0,Q74=""),1,0) -> 0 | N74: 12150 | Q74: TRUE | V74: TRUE | W74: TRUE | AP74: 123 | AQ74: 10 | AR74: 123 | AS74: 17 | AT74: 123 | AU74: 9
B75: =IF(EET!D50="","",EET!D50) | C75: - | D75: - | E75: =IF(OR($R$39=1,$R$39=4),EET!BI50,IF(OR($R$39=6,$R$39=2),EET!BI50-EET!BK50,EET!BK50))*$V$35 -> 0 | F75: =EET!E50 -> 0 | G75: =EET!F50 -> 0 | H75: =EET!G50 -> 0 | I75: =IF(ISERROR(F75/(G75+H75)),"-",F75/(G75+H75)) -> - | J75: þ | M75: =IF(OR(EET!BU50>0,Q75=""),1,0) -> 0 | N75: 12150 | Q75: TRUE | V75: TRUE | W75: TRUE | AP75: 125 | AQ75: 10 | AR75: 125 | AS75: 17 | AT75: 125 | AU75: 9
B76: =Language!C149 -> Água quente | M76: =IF(OR(EET!BU51>0,Q76=""),1,0) -> 1 | N76: 12160 | AP76: 126 | AQ76: 10 | AR76: 126 | AS76: 17 | AT76: 126 | AU76: 9
B77: =IF(EET!D52="","",EET!D52) | C77: =IF($R$39=1,EET!X52,IF($R$39=2,EET!AG52,IF($R$39=3,EET!AF52,IF($R$39=4,EET!T52,IF($R$39=5,EET!AB52,EET!T52-EET!AB52)))))*$V$35 -> 0 | D77: - | E77: - | F77: =EET!E52 -> 0 | G77: =EET!F52 -> 0 | H77: =EET!G52 -> 0 | I77: =IF(ISERROR(F77/(G77+H77)),"-",F77/(G77+H77)) -> - | J77: þ | M77: =IF(OR(EET!BU52>0,Q77=""),1,0) -> 0 | N77: 12160 | Q77: TRUE | V77: TRUE | W77: TRUE | AP77: 127 | AQ77: 10 | AR77: 127 | AS77: 17 | AT77: 127 | AU77: 9
B78: =IF(EET!D53="","",EET!D53) | C78: =IF($R$39=1,EET!X53,IF($R$39=2,EET!AG53,IF($R$39=3,EET!AF53,IF($R$39=4,EET!T53,IF($R$39=5,EET!AB53,EET!T53-EET!AB53)))))*$V$35 -> 0 | D78: - | E78: - | F78: =EET!E53 -> 0 | G78: =EET!F53 -> 0 | H78: =EET!G53 -> 0 | I78: =IF(ISERROR(F78/(G78+H78)),"-",F78/(G78+H78)) -> - | J78: þ | M78: =IF(OR(EET!BU53>0,Q78=""),1,0) -> 0 | N78: 12160 | Q78: TRUE | V78: TRUE | W78: TRUE | AP78: 128 | AQ78: 10 | AR78: 128 | AS78: 17 | AT78: 128 | AU78: 9
B79: =IF(EET!D54="","",EET!D54) | C79: =IF($R$39=1,EET!X54,IF($R$39=2,EET!AG54,IF($R$39=3,EET!AF54,IF($R$39=4,EET!T54,IF($R$39=5,EET!AB54,EET!T54-EET!AB54)))))*$V$35 -> 0 | D79: - | E79: - | F79: =EET!E54 -> 0 | G79: =EET!F54 -> 0 | H79: =EET!G54 -> 0 | I79: =IF(ISERROR(F79/(G79+H79)),"-",F79/(G79+H79)) -> - | J79: þ | M79: =IF(OR(EET!BU54>0,Q79=""),1,0) -> 0 | N79: 12160 | Q79: TRUE | V79: TRUE | W79: TRUE | AP79: 129 | AQ79: 10 | AR79: 129 | AS79: 17 | AT79: 129 | AU79: 9
B80: =IF(EET!D55="","",EET!D55) | C80: =IF($R$39=1,EET!X55,IF($R$39=2,EET!AG55,IF($R$39=3,EET!AF55,IF($R$39=4,EET!T55,IF($R$39=5,EET!AB55,EET!T55-EET!AB55)))))*$V$35 -> 0 | D80: - | E80: - | F80: =EET!E55 -> 0 | G80: =EET!F55 -> 0 | H80: =EET!G55 -> 0 | I80: =IF(ISERROR(F80/(G80+H80)),"-",F80/(G80+H80)) -> - | J80: þ | M80: =IF(OR(EET!BU55>0,Q80=""),1,0) -> 0 | N80: 12160 | Q80: TRUE | S80: Check EET sheet coulmn C link | V80: TRUE | W80: TRUE | AP80: 131 | AQ80: 10 | AR80: 131 | AS80: 17 | AT80: 131 | AU80: 9
B81: =IF(EET!D56="","",EET!D56) | C81: =IF($R$39=1,EET!X56,IF($R$39=2,EET!AG56,IF($R$39=3,EET!AF56,IF($R$39=4,EET!T56,IF($R$39=5,EET!AB56,EET!T56-EET!AB56)))))*$V$35 -> 0 | D81: - | E81: - | F81: =EET!E56 -> 0 | G81: =EET!F56 -> 0 | H81: =EET!G56 -> 0 | I81: =IF(ISERROR(F81/(G81+H81)),"-",F81/(G81+H81)) -> - | J81: þ | M81: =IF(OR(EET!BU56>0,Q81=""),1,0) -> 0 | N81: 12160 | Q81: TRUE | T81: old | V81: TRUE | W81: TRUE | AP81: 132 | AQ81: 10 | AR81: 132 | AS81: 17 | AT81: 132 | AU81: 9
B82: =Language!C1924 -> Bombas | M82: =IF($M$38<R82,0,IF(OR(EET!BU57>0,Q82=""),1,0)) -> 1 | N82: 12170 | R82: 2 | T82: 4 | AP82: 133 | AQ82: 10 | AR82: 133 | AS82: 17 | AT82: 133 | AU82: 9
B83: =IF(EET!D58="","",EET!D58) | C83: - | D83: - | E83: =IF(OR($R$39=1,$R$39=4),EET!BI58,IF(OR($R$39=6,$R$39=2),EET!BI58-EET!BK58,EET!BK58))*$V$35 -> 0 | F83: =EET!E58 -> 0 | G83: =EET!F58 -> 0 | H83: =EET!G58 -> 0 | I83: =IF(ISERROR(F83/(G83+H83)),"-",F83/(G83+H83)) -> - | J83: þ | M83: =IF($M$38<R83,0,IF(OR(EET!BU58>0,Q83=""),1,0)) -> 0 | N83: 12170 | Q83: TRUE | R83: 2 | T83: 4 | V83: TRUE | W83: TRUE | AP83: 134 | AQ83: 10 | AR83: 134 | AS83: 17 | AT83: 134 | AU83: 9
B84: =IF(EET!D59="","",EET!D59) | C84: - | D84: - | E84: =IF(OR($R$39=1,$R$39=4),EET!BI59,IF(OR($R$39=6,$R$39=2),EET!BI59-EET!BK59,EET!BK59))*$V$35 -> 0 | F84: =EET!E59 -> 0 | G84: =EET!F59 -> 0 | H84: =EET!G59 -> 0 | I84: =IF(ISERROR(F84/(G84+H84)),"-",F84/(G84+H84)) -> - | J84: þ | M84: =IF($M$38<R84,0,IF(OR(EET!BU59>0,Q84=""),1,0)) -> 0 | N84: 12170 | Q84: TRUE | R84: 2 | T84: 4 | V84: TRUE | W84: TRUE | AP84: 135 | AQ84: 10 | AR84: 135 | AS84: 17 | AT84: 135 | AU84: 9
B85: =IF(EET!D60="","",EET!D60) | C85: - | D85: - | E85: =IF(OR($R$39=1,$R$39=4),EET!BI60,IF(OR($R$39=6,$R$39=2),EET!BI60-EET!BK60,EET!BK60))*$V$35 -> 0 | F85: =EET!E60 -> 0 | G85: =EET!F60 -> 0 | H85: =EET!G60 -> 0 | I85: =IF(ISERROR(F85/(G85+H85)),"-",F85/(G85+H85)) -> - | J85: þ | M85: =IF($M$38<R85,0,IF(OR(EET!BU60>0,Q85=""),1,0)) -> 0 | N85: 12170 | Q85: TRUE | R85: 2 | T85: 4 | V85: TRUE | W85: TRUE | AP85: 137 | AQ85: 10 | AR85: 137 | AS85: 17 | AT85: 137 | AU85: 9
B86: =IF(EET!D61="","",EET!D61) | C86: - | D86: - | E86: =IF(OR($R$39=1,$R$39=4),EET!BI61,IF(OR($R$39=6,$R$39=2),EET!BI61-EET!BK61,EET!BK61))*$V$35 -> 0 | F86: =EET!E61 -> 0 | G86: =EET!F61 -> 0 | H86: =EET!G61 -> 0 | I86: =IF(ISERROR(F86/(G86+H86)),"-",F86/(G86+H86)) -> - | J86: þ | M86: =IF($M$38<R86,0,IF(OR(EET!BU61>0,Q86=""),1,0)) -> 0 | N86: 12170 | Q86: TRUE | R86: 2 | T86: 4 | V86: TRUE | W86: TRUE | AP86: 138 | AQ86: 10 | AR86: 138 | AS86: 17 | AT86: 138 | AU86: 9
B87: =IF(EET!D62="","",EET!D62) | C87: - | D87: - | E87: =IF(OR($R$39=1,$R$39=4),EET!BI62,IF(OR($R$39=6,$R$39=2),EET!BI62-EET!BK62,EET!BK62))*$V$35 -> 0 | F87: =EET!E62 -> 0 | G87: =EET!F62 -> 0 | H87: =EET!G62 -> 0 | I87: =IF(ISERROR(F87/(G87+H87)),"-",F87/(G87+H87)) -> - | J87: þ | M87: =IF($M$38<R87,0,IF(OR(EET!BU62>0,Q87=""),1,0)) -> 0 | N87: 12170 | Q87: TRUE | R87: 2 | T87: 4 | V87: TRUE | W87: TRUE | AP87: 139 | AQ87: 10 | AR87: 139 | AS87: 17 | AT87: 139 | AU87: 9
B88: =Language!C1652 -> Ventiladores | M88: =IF($M$38<R88,0,IF(OR(EET!BU63>0,Q88=""),1,0)) -> 1 | N88: 12180 | R88: 2 | T88: 4 | AP88: 140 | AQ88: 10 | AR88: 140 | AS88: 17 | AT88: 140 | AU88: 9
B89: =IF(EET!D64="","",EET!D64) | C89: - | D89: - | E89: =IF(OR($R$39=1,$R$39=4),EET!BI64,IF(OR($R$39=6,$R$39=2),EET!BI64-EET!BK64,EET!BK64))*$V$35 -> 0 | F89: =EET!E64 -> 0 | G89: =EET!F64 -> 0 | H89: =EET!G64 -> 0 | I89: =IF(ISERROR(F89/(G89+H89)),"-",F89/(G89+H89)) -> - | J89: þ | M89: =IF($M$38<R89,0,IF(OR(EET!BU64>0,Q89=""),1,0)) -> 0 | N89: 12180 | Q89: TRUE | R89: 2 | T89: 4 | V89: TRUE | W89: TRUE | AP89: 141 | AQ89: 10 | AR89: 141 | AS89: 17 | AT89: 141 | AU89: 9
B90: =IF(EET!D65="","",EET!D65) | C90: - | D90: - | E90: =IF(OR($R$39=1,$R$39=4),EET!BI65,IF(OR($R$39=6,$R$39=2),EET!BI65-EET!BK65,EET!BK65))*$V$35 -> 0 | F90: =EET!E65 -> 0 | G90: =EET!F65 -> 0 | H90: =EET!G65 -> 0 | I90: =IF(ISERROR(F90/(G90+H90)),"-",F90/(G90+H90)) -> - | J90: þ | M90: =IF($M$38<R90,0,IF(OR(EET!BU65>0,Q90=""),1,0)) -> 0 | N90: 12180 | Q90: TRUE | R90: 2 | T90: 4 | V90: TRUE | W90: TRUE | AP90: 143 | AQ90: 10 | AR90: 143 | AS90: 17 | AT90: 143 | AU90: 9
B91: =IF(EET!D66="","",EET!D66) | C91: - | D91: - | E91: =IF(OR($R$39=1,$R$39=4),EET!BI66,IF(OR($R$39=6,$R$39=2),EET!BI66-EET!BK66,EET!BK66))*$V$35 -> 0 | F91: =EET!E66 -> 0 | G91: =EET!F66 -> 0 | H91: =EET!G66 -> 0 | I91: =IF(ISERROR(F91/(G91+H91)),"-",F91/(G91+H91)) -> - | J91: þ | M91: =IF($M$38<R91,0,IF(OR(EET!BU66>0,Q91=""),1,0)) -> 0 | N91: 12180 | Q91: TRUE | R91: 2 | T91: 4 | V91: TRUE | W91: TRUE | AP91: 144 | AQ91: 10 | AR91: 144 | AS91: 17 | AT91: 144 | AU91: 9
B92: =IF(EET!D67="","",EET!D67) | C92: - | D92: - | E92: =IF(OR($R$39=1,$R$39=4),EET!BI67,IF(OR($R$39=6,$R$39=2),EET!BI67-EET!BK67,EET!BK67))*$V$35 -> 0 | F92: =EET!E67 -> 0 | G92: =EET!F67 -> 0 | H92: =EET!G67 -> 0 | I92: =IF(ISERROR(F92/(G92+H92)),"-",F92/(G92+H92)) -> - | J92: þ | M92: =IF($M$38<R92,0,IF(OR(EET!BU67>0,Q92=""),1,0)) -> 0 | N92: 12180 | Q92: TRUE | R92: 2 | T92: 4 | V92: TRUE | W92: TRUE | AP92: 145 | AQ92: 10 | AR92: 145 | AS92: 17 | AT92: 145 | AU92: 9
B93: =IF(EET!D68="","",EET!D68) | C93: - | D93: - | E93: =IF(OR($R$39=1,$R$39=4),EET!BI68,IF(OR($R$39=6,$R$39=2),EET!BI68-EET!BK68,EET!BK68))*$V$35 -> 0 | F93: =EET!E68 -> 0 | G93: =EET!F68 -> 0 | H93: =EET!G68 -> 0 | I93: =IF(ISERROR(F93/(G93+H93)),"-",F93/(G93+H93)) -> - | J93: þ | M93: =IF($M$38<R93,0,IF(OR(EET!BU68>0,Q93=""),1,0)) -> 0 | N93: 12180 | Q93: TRUE | R93: 2 | T93: 4 | V93: TRUE | W93: TRUE | AP93: 146 | AQ93: 10 | AR93: 146 | AS93: 17 | AT93: 146 | AU93: 9
B94: =Language!C1824 -> Motores | M94: =IF($M$38<R94,0,IF(OR(EET!BU69>0,Q94=""),1,0)) -> 1 | N94: 12190 | R94: 2 | T94: 2 | AP94: 147 | AQ94: 10 | AR94: 147 | AS94: 17 | AT94: 147 | AU94: 9
B95: =IF(EET!D70="","",EET!D70) | C95: - | D95: - | E95: =IF(OR($R$39=1,$R$39=4),EET!BI70,IF(OR($R$39=6,$R$39=2),EET!BI70-EET!BK70,EET!BK70))*$V$35 -> 0 | F95: =EET!E70 -> 0 | G95: =EET!F70 -> 0 | H95: =EET!G70 -> 0 | I95: =IF(ISERROR(F95/(G95+H95)),"-",F95/(G95+H95)) -> - | J95: þ | M95: =IF($M$38<R95,0,IF(OR(EET!BU70>0,Q95=""),1,0)) -> 0 | N95: 12190 | Q95: TRUE | R95: 2 | T95: 2 | V95: TRUE | W95: TRUE | AP95: 151 | AQ95: 3 | AR95: 151 | AS95: 13 | AT95: 151 | AU95: 4
B96: =IF(EET!D71="","",EET!D71) | C96: - | D96: - | E96: =IF(OR($R$39=1,$R$39=4),EET!BI71,IF(OR($R$39=6,$R$39=2),EET!BI71-EET!BK71,EET!BK71))*$V$35 -> 0 | F96: =EET!E71 -> 0 | G96: =EET!F71 -> 0 | H96: =EET!G71 -> 0 | I96: =IF(ISERROR(F96/(G96+H96)),"-",F96/(G96+H96)) -> - | J96: þ | M96: =IF($M$38<R96,0,IF(OR(EET!BU71>0,Q96=""),1,0)) -> 0 | N96: 12190 | Q96: TRUE | R96: 2 | T96: 2 | V96: TRUE | W96: TRUE | AP96: 229 | AQ96: 1 | AR96: 228 | AS96: 17 | AT96: 229 | AU96: 2
B97: =IF(EET!D72="","",EET!D72) | C97: - | D97: - | E97: =IF(OR($R$39=1,$R$39=4),EET!BI72,IF(OR($R$39=6,$R$39=2),EET!BI72-EET!BK72,EET!BK72))*$V$35 -> 0 | F97: =EET!E72 -> 0 | G97: =EET!F72 -> 0 | H97: =EET!G72 -> 0 | I97: =IF(ISERROR(F97/(G97+H97)),"-",F97/(G97+H97)) -> - | J97: þ | M97: =IF($M$38<R97,0,IF(OR(EET!BU72>0,Q97=""),1,0)) -> 0 | N97: 12190 | Q97: TRUE | R97: 2 | T97: 2 | V97: TRUE | W97: TRUE | AP97: 277 | AQ97: 1 | AR97: 277 | AS97: 13 | AT97: 277 | AU97: 2
B98: =IF(EET!D73="","",EET!D73) | C98: - | D98: - | E98: =IF(OR($R$39=1,$R$39=4),EET!BI73,IF(OR($R$39=6,$R$39=2),EET!BI73-EET!BK73,EET!BK73))*$V$35 -> 0 | F98: =EET!E73 -> 0 | G98: =EET!F73 -> 0 | H98: =EET!G73 -> 0 | I98: =IF(ISERROR(F98/(G98+H98)),"-",F98/(G98+H98)) -> - | J98: þ | M98: =IF($M$38<R98,0,IF(OR(EET!BU73>0,Q98=""),1,0)) -> 0 | N98: 12190 | Q98: TRUE | R98: 2 | T98: 2 | V98: TRUE | W98: TRUE | AP98: 316 | AQ98: 4 | AR98: 271 | AS98: 13 | AT98: 316 | AU98: 5
B99: =IF(EET!D74="","",EET!D74) | C99: - | D99: - | E99: =IF(OR($R$39=1,$R$39=4),EET!BI74,IF(OR($R$39=6,$R$39=2),EET!BI74-EET!BK74,EET!BK74))*$V$35 -> 0 | F99: =EET!E74 -> 0 | G99: =EET!F74 -> 0 | H99: =EET!G74 -> 0 | I99: =IF(ISERROR(F99/(G99+H99)),"-",F99/(G99+H99)) -> - | J99: þ | M99: =IF($M$38<R99,0,IF(OR(EET!BU74>0,Q99=""),1,0)) -> 0 | N99: 12190 | Q99: TRUE | R99: 2 | T99: 2 | V99: TRUE | W99: TRUE | AP99: 354 | AQ99: 1 | AR99: 354 | AS99: 13 | AT99: 354 | AU99: 2
B100: =Language!C2456 -> Eletricidade de processo | M100: =IF($M$38<R100,0,IF(OR(EET!BU75>0,Q100=""),1,0)) -> 1 | N100: 12200 | R100: 3 | T100: 3 | AP100: 384 | AQ100: 6 | AR100: 384 | AS100: 13 | AT100: 384 | AU100: 7
...

Sheet Modelo Energético
A1: =Language!C866&'Análise de Emissões'!B188 -> Modelo Energético RETScreen - Projeto produção de Eletricidade | AO1: 2000000
J2: =Language!C491 -> Mostrar outras unidades | M2: =IF(ISERROR(SUM(M3:N1032)),2,SUM(M3:M1032)+SUM(N3:N1032)*3) -> 27475 | N2: 27475 | O2: HideCodeES | P2: HideCodeES_mem | R2: SI units | S2: SI value | T2: IP units or alternate | U2: IP value or alternate | V2: Additional calculations and conditional formats | AO2: 2000000 | AP2: radiobutton | AQ2: row | AR2: col | AS2: lrow | AT2: lcol | AU2: value | AV2: group | AW2: mLine | AX2: srow | AY2: scol | AZ2: nextRow | BA2: nextCol | BC2: checkbox | BD2: row | BE2: columns | BF2: link row | BG2: link column | BH2: srow | BI2: scolumn
M3: FALSE | O3: Offgrid | P3: =IF(AND(M31=2,EM_gridtype=5),IF(OR(Set_C=1,Set_C>6),5,0),0) -> 0 | Q3: =EM_gridtype -> 1 | X3: =IF(HideCode_projectType3=7,0,IF(AND(HideCode_projectType3=6,HideCodeES_Cool_BL<>1),0,1)) -> 1 | AO3: 2000000 | AQ3: 224 | AR3: 3 | AS3: 226 | AT3: 19 | AU3: TRUE | AV3: EM_Wind | AW3: TRUE | AX3: 224 | AY3: 4 | AZ3: 226 | BA3: 20 | BD3: 228 | BE3: 5 | BF3: 229 | BG3: 13 | BH3: 228 | BI3: 6
A4: =Language!C397 -> Sistema de refrigeração do caso proposto | F4: =Language!C1746 -> Custo inicial incremental | M4: =IF(P4=1,5310,0) -> 0 | O4: level | P4: =Set_Level -> 2 | X4: =IF(HideCode_projectType3=7,0,IF(AND(HideCode_projectType3=6,HideCodeES_Cool_PL<>1),0,100)) -> 100 | AO4: 2010000 | AQ4: 224 | AR4: 3 | AS4: 226 | AT4: 20 | AU4: TRUE | AV4: EM_Wind | AW4: TRUE | AX4: 224 | AY4: 4 | AZ4: 226 | BA4: 21 | BD4: 266 | BE4: 2 | BF4: 266 | BG4: 13 | BH4: 266 | BI4: 3
B5: =Language!C222 -> Carga base do sistema de refrigeração | O5: Internal load | P5: =IF(OR(HideCode_projectType3=2,HideCode_projectType3=10),0,1)+IF(OR(EM_gridtype=1,EM_gridtype=3),0,1) -> 0 | X5: =Language!C131 -> Carga Base do Sistema | AO5: 2010100 | AQ5: 224 | AR5: 3 | AS5: 226 | AT5: 21 | AU5: TRUE | AV5: EM_Wind | AW5: TRUE | AX5: 224 | AY5: 4 | AZ5: 226 | BA5: 19 | BD5: 296 | BE5: 6 | BF5: 296 | BG5: 13 | BH5: 296 | BI5: 7
B6: =Language!C2015 -> Tecnologia | C6: Bomba de calor | K6: =$K$268 -> Mostrar figura | M6: =IF(C6="",1,VLOOKUP(C6,$G$1076:$H$1081,2,FALSE)) -> 1 | O6: HideCodeES_Cool_BL | AO6: 2010102 | AQ6: 313 | AR6: 3 | AS6: 312 | AT6: 13 | AU6: TRUE | AV6: EM_Hydro | AW6: TRUE | AX6: 313 | AY6: 4 | AZ6: 313 | BA6: 13 | BD6: 453 | BE6: 2 | BF6: 453 | BG6: 13 | BH6: 453 | BI6: 3
B7: =Language!C398 -> Fonte de energia | D7: =IF(HideCodeES_Cool_BL=1,K1197,IF(OR(C6=$G$1078,C6=$G$1079),K1198,K1196)) -> Sistema de produção de eletricidade | M7: =IF(D7=K1196,0,1) -> 1 | O7: HideES_Cool_FreeBL | X7: =IF(HideCodeEM_Heat_Peak=0,13,7) -> 13 | AO7: 2010104 | AQ7: 313 | AR7: 3 | AS7: 313 | AT7: 13 | AU7: TRUE | AV7: EM_Hydro | AW7: TRUE | AX7: 313 | AY7: 4 | AZ7: 312 | BA7: 13 | BD7: 967 | BE7: 1 | BF7: 967 | BG7: 16 | BH7: 967 | BI7: 2
B8: =Language!C211 -> Tipo de Combustível | C8: Eletricidade | AO8: 2010106 | AQ8: 446 | AR8: 3 | AS8: 447 | AT8: 13 | AU8: TRUE | AV8: EM-PV | AW8: TRUE | AX8: 446 | AY8: 4 | AZ8: 448 | BA8: 13
B9: =I42 -> Preço do combustível | C9: =VLOOKUP(C8,$B$1176:$F$1289,3,FALSE) -> €/MWh | AO9: 2010108 | AQ9: 446 | AR9: 3 | AS9: 448 | AT9: 13 | AU9: TRUE | AV9: EM-PV | AW9: TRUE | AX9: 446 | AY9: 4 | AZ9: 447 | BA9: 13
B10: =Language!C202 -> Capacidade | C10: kW | E10: =S10/$R$866 -> #DIV/0! | I10: =Language!C61 -> Ver banco de dados de produtos | P10: =IF(CapaUnit_Cooling1=$Z$1086,$Z$1086,$Z$1087) -> kW | R10: kWch | S10: =IF(C10=$Z$1086,D10,IF(C10=$Z$1087,D10/$AA$1087,D10/$AA$1088)) -> 0 | AO10: 2010110
B11: =Language!C1544 -> Coeficiente de desempenho - sazonal | AO11: 2010112
B12: =Language!C1157 -> Fabricante | AO12: 2050012
B13: =Language!C1160 -> Modelo | F13: =Equip_NbUnits & Lang_Unit -> 1 unidade(s) | AO13: 2050014
B14: =Language!C204 -> Frio fornecido | C14: =IF(Unit=TRUE,R14,T14) -> MWh | D14: =IF(Unit=TRUE,S14,U14) -> 0 | E14: =S14/$R$867 -> #DIV/0! | F14: =IF($M$3=FALSE,"",IF(Unit=FALSE,R14,T14)) | G14: =IF($M$3=FALSE,"",IF(Unit=FALSE,S14,U14)) | R14: =Language!C1396 -> MWh | S14: ='Carga e Rede'!AN335 -> 0 | T14: =Z1103 -> TRh | U14: =S14*$AA$1088*1000 -> 0 | AO14: 2010118
B15: =Language!C223 -> Carga de ponta do sistema de refrigeração | C15: =IF(AND(Equip_CoolType2=G1081,S20>0),G1086,IF(S21<S20,Language!C235,IF(S20=0,IF(Equip_CoolType2=G1081,"",G1087),""))) -> Sistema de ponta não requerido | M15: =IF(ISERROR(S20),0,IF(AND(C16=G1081,S20=0),0,100)) -> 100 | O15: HideCodeES_Cool_Peak | AO15: 2010101
B16: =B6 -> Tecnologia | C16: Compressor | M16: =IF(C16="",1,VLOOKUP(C16,$G$1076:$H$1081,2,FALSE)) -> 1 | O16: HideCodeES_Cool_PL | AO16: 2010103
B17: =Language!C398 -> Fonte de energia | C17: =IF(HideCodeES_Cool_PL=1,K1197,IF(OR(C16=$G$1078,C16=$G$1079),K1198,K1196)) -> Sistema de produção de eletricidade | M17: =IF(C17=K1196,0,1) -> 1 | O17: HideES_Cool_FreePL | AO17: 2010104
B18: =B8 -> Tipo de Combustível | C18: Eletricidade | O18: =G1087 -> Sistema de ponta não requerido | AO18: 2010106
B19: =I42 -> Preço do combustível | C19: =VLOOKUP(C18,$B$1176:$F$1289,3,FALSE) -> €/MWh | AO19: 2010108
B20: =Language!C215 -> Capacidade sugerida | C20: =IF(Unit=TRUE,R20,T20) -> kW | D20: =IF(Unit=TRUE,S20,U20) -> 0 | F20: =IF($M$3=FALSE,"",IF(Unit=FALSE,R20,T20)) | G20: =IF($M$3=FALSE,"",IF(Unit=FALSE,S20,U20)) | R20: =Language!C1364 -> kW | S20: =IF(R866-S10<0,0,R866-S10) -> 0 | T20: =Z1099 -> TR | U20: =S20*$AA$1088 -> 0 | AO20: 2010109
B21: =Language!C202 -> Capacidade | C21: kW | E21: =S21/$R$866 -> #DIV/0! | I21: =Language!C61 -> Ver banco de dados de produtos | P21: =IF(CapaUnit_Cooling2=$Z$1086,$Z$1086,$Z$1087) -> kW | R21: kWch | S21: =IF(C21=$Z$1086,D21,IF(C21=$Z$1087,D21/$AA$1087,D21/$AA$1088)) -> 0 | AO21: 2010111
B22: =B11 -> Coeficiente de desempenho - sazonal | AO22: 2010112
B23: =B12 -> Fabricante | AO23: 2050012
B24: =B13 -> Modelo | F24: =$J$1063 & Lang_Unit -> 1 unidade(s) | AO24: 2050014
B25: =B14 -> Frio fornecido | C25: =IF(Unit=TRUE,R25,T25) -> MWh | D25: =IF(Unit=TRUE,S25,U25) -> 0 | E25: =S25/$R$867 -> #DIV/0! | F25: =IF($M$3=FALSE,"",IF(Unit=FALSE,R25,T25)) | G25: =IF($M$3=FALSE,"",IF(Unit=FALSE,S25,U25)) | R25: =$R$14 -> MWh | S25: ='Carga e Rede'!AO335 -> 0 | T25: =T14 -> TRh | U25: =S25*$AA$1088*1000 -> 0 | AO25: 2010118
AO26: 2000000
A27: =Language!C407 -> Sitema de aquecimento do caso proposto | H27: =F4 -> Custo inicial incremental | M27: =HideCode_projectType -> 2 | O27: HideCode_projectType3 | AO27: 2020000
B28: =Language!C408 -> Seleção do Sistema | C28: Carga Base do Sistema | M28: =IF(C28="",1,MATCH(C28,ES_TypeBI,0)) -> 1 | O28: HideCodeES_HSS | AO28: 2020002
A29: =Language!C409 -> Sistema de eletricidade do caso proposto | H29: =F4 -> Custo inicial incremental | M29: =HideCodeEM_1+HideCodeES_PSS*123 -> 21056 | O29: Min Cap | P29: =IF(OR(EM_gridtype=1,EM_gridtype=3),100,0)+M31 -> 102 | AO29: 2030000
B30: =Language!C408 -> Seleção do Sistema | C30: Carga Base do Sistema | M30: =IF(C30=G1074,2,1) -> 1 | O30: HideCodeES_PSS | AO30: 2030002
B31: =IF(M31=2,"",IF(M31=10,IF(C854=E1094,Language!C199,Language!C209),(IF(OR(HideCode_projectType3=1,HideCode_projectType3=6),Language!C218,IF(C30=G1073,Language!C199,IF(C854=E1094,Language!C199,Language!C209)))))) | M31: =Iniciar!P20 -> 2 | AO31: 2020004
B32: =B6 -> Tecnologia | C32: Sistema à biomassa | M32: =IF(C32="",1,IF(ISERROR(MATCH(C32,E1079:E1084,0)),1,MATCH(C32,E1079:E1084,0))) -> 1 | O32: HideCodeES_HeatST1 | AO32: 2020104
B33: =Language!C2015 -> Tecnologia | C33: Fotovoltaica | M33: =IF(OR(Equip_PowerType="",Equip_PowerType=Iniciar!D121),1,MATCH(Equip_PowerType,ES_PowerType,0)) -> 9 | O33: HideCodeES_PowerST1 | AO33: 2030008
B34: =B33 -> Tecnologia | C34: =Equip_PowerType -> Fotovoltaica | M34: =HideCodeES_PowerST1*123 -> 1107 | AO34: 2030008
B35: =Language!C410 -> Disponibilidade | C35: % | F35: =IF(C35=$Z$1105,FIXED(U35*100,1)&T35,FIXED(S35,0)&" "&R35) -> 8 760 h | R35: =Language!C1339 -> h | S35: =IF(OR(M33=7,M33=8,M33=9,M33>10),8760,IF(C35=Z1105,D35,E35*8760)) -> 8760 | T35: =Language!C1306 -> % | U35: =S35/8760 -> 1 | AO35: 2030010
AO36: 2030100
B37: =Language!C411 -> Método-seleção de combustível | C37: Combustível único | K37: =IF(Ferramentas!E411<1,G1097,"") | M37: =IF(C37="",1,MATCH(C37,ES_FuelMethod,0)) -> 1 | O37: HideCodeES_Fuel1 | AO37: 2030100
B38: =B8 -> Tipo de Combustível | C38: Gas natural - m³ | K38: =Language!C62 -> Completar planilha Ferramentas | M38: =M37*100 -> 100 | R38: MJ/kg | S38: =VLOOKUP(C38,$B$1176:$F$1289,4,FALSE) -> 47.856 | T38: Btu/lb | U38: =S38*$AA$1092 -> 20574.377 | V38: =SUMIF($B$1102:$B$1105,C38,$A$1102:$A$1105) -> 0 | X38: Conditional format | AO38: 2010106
B39: =I42 -> Preço do combustível | C39: =VLOOKUP(C38,$B$1176:$F$1289,3,FALSE) -> €/m³ | R39: $/MWh | S39: =1000/S38/VLOOKUP(C38,$B$1176:$F$1289,5,FALSE)*D39*3.6 -> 0 | AO39: 2010108
AO40: 2030008
AO41: 2030200
C42: =B8 -> Tipo de Combustível | E42: =Language!C412 -> Mix do combustível | F42: =Language!C357 -> Consumo de combustível - unitário | G42: =Language!C413 -> Consumo de combustível | H42: =Language!C359 -> Preço combustível - unidade | I42: =Language!C212 -> Preço do combustível | J42: =Language!C287 -> Custo do combustível | O42: As-fired calorific value of fuel MJ/kg | P42: As-fired calorific value of fuel Btu/lb | Q42: GJ | AO42: 2030200
B43: =Language!C146 -> Combustível #1 | C43: Biomassa | E43: =IF(Q43=0,"",Q43/$Q$46) | F43: =IF(O43="","",VLOOKUP($C43,$B$1176:$F$1289,2,FALSE)) -> t | G43: =IF(OR(C43="",E43=""),"",Q43*1000/O43/VLOOKUP($C43,$B$1176:$F$1289,5,FALSE)) | H43: =IF(F43="","",VLOOKUP($C43,$B$1176:$F$1289,3,FALSE)) -> €/t | J43: =IF(OR(O43="",G43=""),"",G43*I43) | K43: =Language!C62 -> Completar planilha Ferramentas | O43: =IF(C43="","",VLOOKUP($C43,$B$1176:$F$1289,4,FALSE)) -> 18.444144 | P43: =O43*$AA$1092 -> 7929.5544 | Q43: =IF(SUM($S$49:$S$60)=0,SUM(S49:S62),SUMIF($C$49:$C$60,B43,$S$49:$S$62)*$U$35*SUM($S$49:$S$62)/SUM($S$49:$S$60)) -> 0 | R43: =SUMIF($B$1102:$B$1105,C43,$A$1102:$A$1105) -> 0 | S43: Fuel type #1 | AO43: 2030200
B44: =Language!C147 -> Combustível #2 | E44: =IF(Q44=0,"",Q44/$Q$46) | F44: =IF(O44="","",VLOOKUP($C44,$B$1176:$F$1289,2,FALSE)) | G44: =IF(OR(C44="",E44=""),"",Q44*1000/O44/VLOOKUP($C44,$B$1176:$F$1289,5,FALSE)) | H44: =IF(F44="","",VLOOKUP($C44,$B$1176:$F$1289,3,FALSE)) | J44: =IF(OR(O44="",G44=""),"",G44*I44) | O44: =IF(C44="","",VLOOKUP($C44,$B$1176:$F$1289,4,FALSE)) | P44: =O44*$AA$1092 -> #VALUE! | Q44: =IF(SUM($S$49:$S$60)=0,0,SUMIF($C$49:$C$60,B44,$S$49:$S$62)*$U$35*SUM($S$49:$S$62)/SUM($S$49:$S$60)) -> 0 | R44: =SUMIF($B$1102:$B$1105,C44,$A$1102:$A$1105) -> 0 | S44: Fuel type #2 | AO44: 2030200
B45: =Language!C148 -> Combustível #3 | E45: =IF(Q45=0,"",Q45/$Q$46) | F45: =IF(O45="","",VLOOKUP($C45,$B$1176:$F$1289,2,FALSE)) | G45: =IF(OR(C45="",E45=""),"",Q45*1000/O45/VLOOKUP($C45,$B$1176:$F$1289,5,FALSE)) | H45: =IF(F45="","",VLOOKUP($C45,$B$1176:$F$1289,3,FALSE)) | J45: =IF(OR(O45="",G45=""),"",G45*I45) | O45: =IF(C45="","",VLOOKUP($C45,$B$1176:$F$1289,4,FALSE)) | P45: =O45*$AA$1092 -> #VALUE! | Q45: =IF(SUM($S$49:$S$60)=0,0,SUMIF($C$49:$C$60,B45,$S$49:$S$62)*$U$35*SUM($S$49:$S$62)/SUM($S$49:$S$60)) -> 0 | R45: =SUMIF($B$1102:$B$1105,C45,$A$1102:$A$1105) -> 0 | S45: Fuel type #3 | AO45: 2030200
E46: =SUM(E43:E45) -> 0 | H46: =Currency&Language!C1302 -> €/MWh | I46: =IF(Q46=0,0,J46/Q46)*3.6 -> 0 | J46: =SUM(J43:J45) -> 0 | Q46: =SUM(Q43:Q45) -> 0 | R46: =SUM(R43:R45) -> 0 | AO46: 2030200
AO47: 2030200
C48: =B8 -> Tipo de Combustível | D48: =Language!C415 -> Consumo de combustível MWh | O48: lookup row | Q48: Load MJ/h | S48: =S564 -> Consumo de combustível MWh | AO48: 2030200
B49: =Language!C251 -> Janeiro | C49: Combustível #1 | D49: =S49/3.6 -> 0 | O49: 8 | Q49: =IF(OR(HideCode_projectType3=1,HideCode_projectType3=6)=TRUE,IF($C$28=$G$1073,K1139,H1139)/$N$1109*3.6,IF($C$30=$G$1073,HLOOKUP($N$863,$T$1132:$BZ$1151,O49,FALSE),IF($G$1120=1,$C$1127,HLOOKUP($N$863,$T$1132:$BZ$1151,O49,FALSE)))) -> 0 | S49: =Q49*C1139/1000 -> 0 | AO49: 2030200
B50: =Language!C252 -> Fevereiro | C50: Combustível #1 | D50: =S50/3.6 -> 0 | O50: 9 | Q50: =IF(OR(HideCode_projectType3=1,HideCode_projectType3=6)=TRUE,IF($C$28=$G$1073,K1140,H1140)/$N$1109*3.6,IF($C$30=$G$1073,HLOOKUP($N$863,$T$1132:$BZ$1151,O50,FALSE),IF($G$1120=1,$C$1127,HLOOKUP($N$863,$T$1132:$BZ$1151,O50,FALSE)))) -> 0 | S50: =Q50*C1140/1000 -> 0 | AO50: 2030200
B51: =Language!C253 -> Março | C51: Combustível #1 | D51: =S51/3.6 -> 0 | O51: 10 | Q51: =IF(OR(HideCode_projectType3=1,HideCode_projectType3=6)=TRUE,IF($C$28=$G$1073,K1141,H1141)/$N$1109*3.6,IF($C$30=$G$1073,HLOOKUP($N$863,$T$1132:$BZ$1151,O51,FALSE),IF($G$1120=1,$C$1127,HLOOKUP($N$863,$T$1132:$BZ$1151,O51,FALSE)))) -> 0 | S51: =Q51*C1141/1000 -> 0 | AO51: 2030200
B52: =Language!C254 -> Abril | C52: Combustível #1 | D52: =S52/3.6 -> 0 | O52: 11 | Q52: =IF(OR(HideCode_projectType3=1,HideCode_projectType3=6)=TRUE,IF($C$28=$G$1073,K1142,H1142)/$N$1109*3.6,IF($C$30=$G$1073,HLOOKUP($N$863,$T$1132:$BZ$1151,O52,FALSE),IF($G$1120=1,$C$1127,HLOOKUP($N$863,$T$1132:$BZ$1151,O52,FALSE)))) -> 0 | S52: =Q52*C1142/1000 -> 0 | AO52: 2030200
B53: =Language!C255 -> Maio | C53: Combustível #1 | D53: =S53/3.6 -> 0 | O53: 12 | Q53: =IF(OR(HideCode_projectType3=1,HideCode_projectType3=6)=TRUE,IF($C$28=$G$1073,K1143,H1143)/$N$1109*3.6,IF($C$30=$G$1073,HLOOKUP($N$863,$T$1132:$BZ$1151,O53,FALSE),IF($G$1120=1,$C$1127,HLOOKUP($N$863,$T$1132:$BZ$1151,O53,FALSE)))) -> 0 | S53: =Q53*C1143/1000 -> 0 | AO53: 2030200
B54: =Language!C256 -> Junho | C54: Combustível #1 | D54: =S54/3.6 -> 0 | O54: 13 | Q54: =IF(OR(HideCode_projectType3=1,HideCode_projectType3=6)=TRUE,IF($C$28=$G$1073,K1144,H1144)/$N$1109*3.6,IF($C$30=$G$1073,HLOOKUP($N$863,$T$1132:$BZ$1151,O54,FALSE),IF($G$1120=1,$C$1127,HLOOKUP($N$863,$T$1132:$BZ$1151,O54,FALSE)))) -> 0 | S54: =Q54*C1144/1000 -> 0 | AO54: 2030200
B55: =Language!C257 -> Julho | C55: Combustível #1 | D55: =S55/3.6 -> 0 | O55: 14 | Q55: =IF(OR(HideCode_projectType3=1,HideCode_projectType3=6)=TRUE,IF($C$28=$G$1073,K1145,H1145)/$N$1109*3.6,IF($C$30=$G$1073,HLOOKUP($N$863,$T$1132:$BZ$1151,O55,FALSE),IF($G$1120=1,$C$1127,HLOOKUP($N$863,$T$1132:$BZ$1151,O55,FALSE)))) -> 0 | S55: =Q55*C1145/1000 -> 0 | AO55: 2030200
B56: =Language!C258 -> Agosto | C56: Combustível #1 | D56: =S56/3.6 -> 0 | O56: 15 | Q56: =IF(OR(HideCode_projectType3=1,HideCode_projectType3=6)=TRUE,IF($C$28=$G$1073,K1146,H1146)/$N$1109*3.6,IF($C$30=$G$1073,HLOOKUP($N$863,$T$1132:$BZ$1151,O56,FALSE),IF($G$1120=1,$C$1127,HLOOKUP($N$863,$T$1132:$BZ$1151,O56,FALSE)))) -> 0 | S56: =Q56*C1146/1000 -> 0 | AO56: 2030200
B57: =Language!C259 -> Setembro | C57: Combustível #1 | D57: =S57/3.6 -> 0 | O57: 16 | Q57: =IF(OR(HideCode_projectType3=1,HideCode_projectType3=6)=TRUE,IF($C$28=$G$1073,K1147,H1147)/$N$1109*3.6,IF($C$30=$G$1073,HLOOKUP($N$863,$T$1132:$BZ$1151,O57,FALSE),IF($G$1120=1,$C$1127,HLOOKUP($N$863,$T$1132:$BZ$1151,O57,FALSE)))) -> 0 | S57: =Q57*C1147/1000 -> 0 | AO57: 2030200
B58: =Language!C260 -> Outubro | C58: Combustível #1 | D58: =S58/3.6 -> 0 | O58: 17 | Q58: =IF(OR(HideCode_projectType3=1,HideCode_projectType3=6)=TRUE,IF($C$28=$G$1073,K1148,H1148)/$N$1109*3.6,IF($C$30=$G$1073,HLOOKUP($N$863,$T$1132:$BZ$1151,O58,FALSE),IF($G$1120=1,$C$1127,HLOOKUP($N$863,$T$1132:$BZ$1151,O58,FALSE)))) -> 0 | S58: =Q58*C1148/1000 -> 0 | AO58: 2030200
B59: =Language!C261 -> Novembro | C59: Combustível #1 | D59: =S59/3.6 -> 0 | O59: 18 | Q59: =IF(OR(HideCode_projectType3=1,HideCode_projectType3=6)=TRUE,IF($C$28=$G$1073,K1149,H1149)/$N$1109*3.6,IF($C$30=$G$1073,HLOOKUP($N$863,$T$1132:$BZ$1151,O59,FALSE),IF($G$1120=1,$C$1127,HLOOKUP($N$863,$T$1132:$BZ$1151,O59,FALSE)))) -> 0 | S59: =Q59*C1149/1000 -> 0 | AO59: 2030200
B60: =Language!C262 -> Dezembro | C60: Combustível #1 | D60: =S60/3.6 -> 0 | O60: 19 | Q60: =IF(OR(HideCode_projectType3=1,HideCode_projectType3=6)=TRUE,IF($C$28=$G$1073,K1150,H1150)/$N$1109*3.6,IF($C$30=$G$1073,HLOOKUP($N$863,$T$1132:$BZ$1151,O60,FALSE),IF($G$1120=1,$C$1127,HLOOKUP($N$863,$T$1132:$BZ$1151,O60,FALSE)))) -> 0 | S60: =Q60*C1150/1000 -> 0 | AO60: 2030200
C61: =Language!C233 -> Total | D61: =SUM(D49:D60) -> 0 | O61: 20 | AO61: 2030200
O62: 20 | Q62: =IF(OR(HideCode_projectType3=1,HideCode_projectType3=6)=TRUE,IF($C$28=$G$1073,K1151,H1151)/$N$1109*3.6,IF($C$30=$G$1073,HLOOKUP($N$863,$T$1132:$BZ$1151,O61,FALSE),IF($G$1120=1,$C$1127,HLOOKUP($N$863,$T$1132:$BZ$1151,O61,FALSE)))) -> 0 | S62: =Q62*C1151/1000 -> 0 | AO62: 2030200
AO63: 2030300
C64: =C42 -> Tipo de Combustível | E64: =E42 -> Mix do combustível | F64: =F42 -> Consumo de combustível - unitário | G64: =G42 -> Consumo de combustível | H64: =H42 -> Preço combustível - unidade | I64: =I42 -> Preço do combustível | J64: =J42 -> Custo do combustível | O64: As-fired calorific value of fuel MJ/kg | P64: As-fired calorific value of fuel Btu/lb | AO64: 2030300
B65: =B43 -> Combustível #1 | C65: Biomassa | E65: 1 | F65: =IF(O65="","",VLOOKUP($C65,$B$1176:$F$1289,2,FALSE)) -> t | G65: =IF(OR(C65="",E65=""),"",$Q$46*E65*1000/O65/VLOOKUP($C65,$B$1176:$F$1289,5,FALSE)) -> 0 | H65: =IF(F65="","",VLOOKUP($C65,$B$1176:$F$1289,3,FALSE)) -> €/t | J65: =IF(OR(O65="",G65=0,G65=""),"",G65*I65) | K65: =Language!C62 -> Completar planilha Ferramentas | O65: =IF(C65="","",VLOOKUP($C65,$B$1176:$F$1289,4,FALSE)) -> 18.444144 | P65: =O65*$AA$1092 -> 7929.5544 | R65: =SUMIF($B$1102:$B$1105,C65,$A$1102:$A$1105) -> 0 | AO65: 2030300
B66: =B44 -> Combustível #2 | F66: =IF(O66="","",VLOOKUP($C66,$B$1176:$F$1289,2,FALSE)) | G66: =IF(OR(C66="",E66=""),"",$Q$46*E66*1000/O66/VLOOKUP($C66,$B$1176:$F$1289,5,FALSE)) | H66: =IF(F66="","",VLOOKUP($C66,$B$1176:$F$1289,3,FALSE)) | J66: =IF(OR(O66="",G66=0,G66=""),"",G66*I66) | O66: =IF(C66="","",VLOOKUP($C66,$B$1176:$F$1289,4,FALSE)) | P66: =O66*$AA$1092 -> #VALUE! | R66: =SUMIF($B$1102:$B$1105,C66,$A$1102:$A$1105) -> 0 | AO66: 2030300
B67: =B45 -> Combustível #3 | F67: =IF(O67="","",VLOOKUP($C67,$B$1176:$F$1289,2,FALSE)) | G67: =IF(OR(C67="",E67=""),"",$Q$46*E67*1000/O67/VLOOKUP($C67,$B$1176:$F$1289,5,FALSE)) | H67: =IF(F67="","",VLOOKUP($C67,$B$1176:$F$1289,3,FALSE)) | J67: =IF(OR(O67="",G67=0,G67=""),"",G67*I67) | O67: =IF(C67="","",VLOOKUP($C67,$B$1176:$F$1289,4,FALSE)) | P67: =O67*$AA$1092 -> #VALUE! | R67: =SUMIF($B$1102:$B$1105,C67,$A$1102:$A$1105) -> 0 | AO67: 2030300
E68: =SUM(E65:E67) -> 1 | H68: =H46 -> €/MWh | I68: =IF(Q46=0,0,J68/Q46)*3.6 -> 0 | J68: =SUM(J65:J67) -> 0 | R68: =SUM(R65:R67) -> 0 | AO68: 2030300
AO69: 2030300
B70: =Equip_HeatingType -> Sistema à biomassa | AO70: 2020104
AO71: 2020104
B72: =Language!C202 -> Capacidade | C72: kW | E72: =S72/$Q$866 -> #DIV/0! | H72: 0 | I72: =$I$79 -> Ver banco de dados de produtos | R72: kW | S72: =IF(C72=$Z$1086,D72,D72/$AA$1087) -> 0 | AO72: 2020200
B73: =Language!C203 -> Calor fornecido | C73: =IF(Unit=TRUE,R73,T73) -> MWh | D73: =IF(Unit=TRUE,S73,U73) -> 0 | E73: =S73/$Q$867 -> #DIV/0! | F73: =IF($M$3=FALSE,"",IF(Unit=FALSE,R73,T73)) | G73: =IF($M$3=FALSE,"",IF(Unit=FALSE,S73,U73)) | R73: =$R$25 -> MWh | S73: =G1109 -> 0 | T73: =Language!C1382 -> milhão Btu | U73: =S73*$AB$1087 -> 0 | AO73: 2020202
B74: =B12 -> Fabricante | AO74: 2050012
B75: =B13 -> Modelo | F75: =$J$1065 & Lang_Unit -> 1 unidade(s) | AO75: 2050014
B76: =B919 -> Eficiência Sazonal | C76: =$T$35 -> % | AO76: 2020208
B77: =Language!C426 -> Combustível necessário | C77: =IF(Unit=TRUE,R77,T77) -> GJ/h | D77: =IF(Unit=TRUE,S77,U77) -> #DIV/0! | F77: =IF($M$3=FALSE,"",IF(Unit=FALSE,R77,T77)) | G77: =IF($M$3=FALSE,"",IF(Unit=FALSE,S77,U77)) | R77: =Language!C1336 -> GJ/h | S77: =S72/D76*3.6/1000 -> #DIV/0! | T77: =Language!C1383 -> milhão Btu/h | U77: =S77/$AA$1082 -> #DIV/0! | AO77: 2020222
B78: =Equip_HeatingType -> Sistema à biomassa | AO78: 2020104
B79: =Language!C202 -> Capacidade | C79: kW | E79: =S79/$Q$866 -> #DIV/0! | I79: =Language!C61 -> Ver banco de dados de produtos | R79: kW | S79: =IF(C79=$Z$1086,D79,D79/$AA$1087) -> 0 | AO79: 2020200
B80: =B73 -> Calor fornecido | C80: =IF(Unit=TRUE,R80,T80) -> MWh | D80: =IF(Unit=TRUE,S80,U80) -> 0 | E80: =S80/$Q$867 -> #DIV/0! | F80: =IF($M$3=FALSE,"",IF(Unit=FALSE,R80,T80)) | G80: =IF($M$3=FALSE,"",IF(Unit=FALSE,S80,U80)) | R80: =$R$25 -> MWh | S80: =G1109 -> 0 | T80: =$T$73 -> milhão Btu | U80: =S80*$AB$1087 -> 0 | AO80: 2020202
B81: =B12 -> Fabricante | AO81: 2050012
B82: =B13 -> Modelo | F82: =$J$1064 & Lang_Unit -> 1 unidade(s) | AO82: 2050014
B83: =B919 -> Eficiência Sazonal | C83: =$T$35 -> % | AO83: 2020208
B84: =Language!C422 -> Tipo de Caldeira | D84: Água quente | M84: =IF(D84="",1,MATCH(D84,ES_BoilerT,0)) -> 1 | O84: HideCodeES_Boiler1 | AO84: 2020210
B85: =Language!C423 -> Pressão de Operação | C85: bar | K85: =IF(V86=SteamP*1000,$G$1088,"") | AO85: 2020212
B86: =Language!C424 -> Temperatura de saturação | C86: =IF(Unit=TRUE,R86,T86) -> °C | D86: =IF(Unit=TRUE,S86,U86) -> -273.15 | F86: =IF($M$3=FALSE,"",IF(Unit=FALSE,R86,T86)) | G86: =IF($M$3=FALSE,"",IF(Unit=FALSE,S86,U86)) | R86: =Language!C1310 -> °C | S86: =Tsat(V86/1000)-$AA$1090 -> -273.15 | T86: =Language!C1313 -> °F | U86: =S86*1.8+32 -> -459.67 | V86: =IF(IF(C85=$Z$1067,D85,IF(C85=$Z$1068,D85*100,IF(C85=$Z$1069,(D85+$AA$1069)/$Y$1069*100,IF(C85=$Z$1070,D85/$Y$1069*100))))<SteamP,SteamP,IF(C85=$Z$1067,D85,IF(C85=$Z$1068,D85*100,IF(C85=$Z$1069,(D85+$AA$1069)/$Y$1069*100,IF(C85=$Z$1070,D85/$Y$1069*100))))) -> 0.00111 | W86: kPa | AO86: 2060010
B87: =Language!C425 -> Temperatura superaquecimento | C87: °C | R87: =IF(C87=$Z$1107,D87,(D87-32)/1.8) -> 0 | S87: C | V87: =EnthalpyV(IF(V86/1000<SteamP,SteamP,V86/1000),R87+$AA$1090) -> 2500.3977 | W87: kJ/kg | AO87: 2020216
B88: =B156 -> Temp. de retorno | C88: °C | R88: =IF(C88=$Z$1107,D88,(D88-32)/1.8) -> 0 | S88: C | V88: =EnthalpyF(0.1,R88+$AA$1090) -> 0.059662252 | W88: kJ/kg | AO88: 2020218
B89: =B131 -> Fluxo de vapor | C89: =IF(Unit=TRUE,R89,T89) -> kg/h | D89: =IF(Unit=TRUE,S89,U89) -> 0 | F89: =IF($M$3=FALSE,"",IF(Unit=FALSE,R89,T89)) | G89: =IF($M$3=FALSE,"",IF(Unit=FALSE,S89,U89)) | R89: =Language!C1355 -> kg/h | S89: =S79/V89*3600 -> 0 | T89: =Language!C1368 -> lb/h | U89: =S89/$AA$1085 -> 0 | V89: =V87-V88 -> 2500.3381 | W89: kJ/kg | AO89: 2020220
B90: =B77 -> Combustível necessário | C90: =IF(Unit=TRUE,R90,T90) -> GJ/h | D90: =IF(Unit=TRUE,S90,U90) -> #DIV/0! | F90: =IF($M$3=FALSE,"",IF(Unit=FALSE,R90,T90)) | G90: =IF($M$3=FALSE,"",IF(Unit=FALSE,S90,U90)) | R90: =$R$77 -> GJ/h | S90: =S79/D83*3.6/1000 -> #DIV/0! | T90: =$T$77 -> milhão Btu/h | U90: =S90/$AA$1082 -> #DIV/0! | AO90: 2020222
B91: =IF(HideCodeES_PSS=1,Language!C133,Language!C133&" #1") -> Motor recíproco | AO91: 2040022
B92: =Language!C427 -> Potência elétrica | C92: =Language!C1364 -> kW | E92: =IF($P$866=0,"",D92/$P$866) | I92: =Language!C61 -> Ver banco de dados de produtos | AO92: 2050002
B93: =Language!C429 -> Capac. Mínima | C93: =$T$35 -> % | K93: =IF(S93>0,$G$1095&S93&$G$1096,"") | R93: months | S93: {=IF(AND(HideCodeES_PSS=2,$C$854=$E$1094),SUM(IF($D$1139:$D$1150<D92*M1114,1,0)),SUM(IF($I$1139:$I$1150<D92*M1114,1,0)))*IF(SUM($D$1139:$D$1150)=0,0,1)} -> 0 | AO93: 2050006
B94: =Language!C205 -> Eletricidade fornecida à carga | C94: =R14 -> MWh | D94: =IF(HideCodeES_PSS=1,$G$1107,IF($C$854=$E$1094,$G$1107,$G$1108)) -> 0 | E94: =IF($P$867=0,"",D94/$P$867) | AO94: 2050008
B95: =Language!C206 -> Eletricidade exportada p/ rede | C95: =R14 -> MWh | D95: =IF(HideCodeES_PSS=1,$J$1107,IF($C$854=$E$1094,$J$1107,$J$1108)) -> 5.3903326 | AO95: 2050010
B96: =B12 -> Fabricante | AO96: 2050012
B97: =B13 -> Modelo | F97: =$J$1071 & Lang_Unit -> 1 unidade(s) | AO97: 2050014
B98: =Language!C216 -> Preço do calor | C98: kJ/kWh | R98: kJ/kWh | S98: =IF(C98=$Z$1081,D98,D98*$AA$1082) -> 0 | AO98: 2050018
B99: =Language!C430 -> Taxa de recuperação de calor | C99: =$T$35 -> % | AO99: 2050028
B100: =B77 -> Combustível necessário | C100: =IF(Unit=TRUE,R100,T100) -> GJ/h | D100: =IF(Unit=TRUE,S100,U100) -> 0 | F100: =IF($M$3=FALSE,"",IF(Unit=FALSE,R100,T100)) | G100: =IF($M$3=FALSE,"",IF(Unit=FALSE,S100,U100)) | R100: =$R$77 -> GJ/h | S100: =D92*S98/10^6 -> 0 | T100: =$T$77 -> milhão Btu/h | U100: =S100/$AA$1082 -> 0 | AO100: 2050032
...

Sheet Análise de Custos
A1: =Language!C869&'Análise de Emissões'!B188 -> Análise de Custos RETScreen - Projeto produção de Eletricidade | U1: 60000
O2: =IF(ISERROR(SUM(O3:P256)),3,1+SUM(O3:P256)) -> 21329 | P2: 21329 | U2: 60000 | V2: Currency Range
O3: =IF(R5=TRUE,IF(G6="",2,MATCH(G6,D266:D267,0)),100) -> 1 | U3: 60000 | V3: Name | W3: Sign
A4: =Language!C494 -> Opções | O4: =Iniciar!O28 -> 20912 | Q4: Left buttons | R4: Right buttons | U4: 60100 | V4: $ | W4: $
C5: =Language!C1811 -> Método 1 | D5: =Language!C48 -> Notas/faixa | H5: =Language!C496 -> Segunda moeda | I5: $ | O5: =IF(Currency2_name="",1,MATCH(Currency2_name,currency_list,0)) -> 1 | Q5: FALSE | R5: TRUE | S5: 60106 | T5: 60108 | U5: 60100 | V5: Euro | W5: €
C6: =Language!C1812 -> Método 2 | D6: =Language!C496 -> Segunda moeda | F6: =D5 -> Notas/faixa | G6: Nenhum | I6: =Language!C497 -> Símbolo | M6: =D267 -> Definido pelo usuário | O6: =IF(Q6=TRUE,13,5)+IF(R5=TRUE,7,11)+IF(R7=TRUE,22,45) -> 65 | Q6: TRUE | R6: FALSE | S6: 60106 | T6: 60110 | U6: 60100 | V6: £ | W6: £
D7: =Language!C1568 -> Alocação de custo | I7: =Language!C498&Currency&"/"&Currency2 -> Preço: €/$ | J7: 1 | O7: =HideCodeCA_ProjectT*123 -> 0 | Q7: FALSE | R7: FALSE | S7: 60106 | T7: 60112 | U7: 60100 | V7: ¥ | W7: ¥
O8: =IF($Q$6=FALSE,IF(Q5=TRUE,2,1),0) -> 0 | Q8: Multiplicative currency rate | U8: 60000 | V8: Y | W8: Y
A9: =Language!C500 -> Custos iniciais (créditos) | D9: =Language!C180 -> Unidade | E9: =Language!C501 -> Quantidade | F9: =Language!C502 -> Custo unitário | G9: =Language!C226 -> Quantidade | H9: =Language!C503 -> Custos relativos | I9: =$D$192 -> % | J9: =G9 -> Quantidade | M9: =D5 -> Notas/faixa | O9: =HideCode_projectType*100 -> 200 | Q9: =IF(R7=TRUE,1,J7) -> 1 | U9: 61000 | V9: Rs | W9: Rs
B10: =Language!C683 -> Custos iniciais | U10: 60000 | V10: Definido pelo usuário
C11: =Language!C1284 -> Sistema de produção de eletricidade | D11: =D61 -> kW | E11: ='Modelo Energético'!V870 -> 3.795 | G11: =E11*F11*O11 -> 0 | O11: =IF(OR(HideCode_projectType=1,HideCode_projectType=3,HideCode_projectType=6,HideCode_projectType>7),0,1) -> 1 | U11: 60000 | V11: Nenhum | W11: -
C12: =Language!C1283 -> Sistema de Aquecimento | D12: =IF(Set_OpenClose=10702,'Modelo Energético '!C649,D74) -> kW | E12: ='Modelo Energético'!S895 -> 0 | G12: =E12*F12*O12 -> 0 | O12: =IF(OR(HideCode_projectType=2,HideCode_projectType=3,HideCode_projectType=5,HideCode_projectType>7),0,1)*(1-O13) -> 0 | U12: 60000 | V12: Afganistão | W12: AFA
C13: =C12 -> Sistema de Aquecimento | G13: =G73 -> 0 | O13: =IF(HideCodeCA_SWH=1,1,0) -> 0 | U13: 60000 | V13: África do Sul | W13: ZAR
C14: =Language!C542 -> Sistema de refrigeração | D14: =D87 -> kW | E14: ='Modelo Energético'!S927 -> 0 | G14: =E14*F14*O14 -> 0 | O14: =IF(OR(HideCode_projectType=1,HideCode_projectType=2,HideCode_projectType=4,HideCode_projectType>7),0,1) -> 0 | U14: 60000 | V14: Albania | W14: ALL
C15: =Language!C1746 -> Custo inicial incremental | G15: ='Modelo Energético '!G1091 -> 0 | O15: =IF(G15=0,0,1) -> 0 | U15: 60000 | V15: Alemanha | W15: EUR
G16: =IF(D16=$C$261,-1,1)*E16*F16 -> 0 | U16: 60000 | V16: Andorra | W16: EUR
C17: =B97 -> Ações de Eficiência energética | D17: custo | G17: =IF(D17=$C$261,-1,1)*E17*F17 -> 0 | U17: 60000 | V17: Angola | W17: AOA
C18: =C196 -> Contingências | D18: =$D$192 -> % | F18: =SUM(G11:G17) -> 0 | G18: =E18*F18 -> 0 | U18: 60000 | V18: Anguila | W18: XCD
C19: =C197 -> Juros durante a construçaõ | F19: =F18+G18 -> 0 | G19: =F19*D19*E19/12/2 -> 0 | U19: 60000 | V19: Antigua e Barbuda | W19: XCD
A20: =A199 -> Total de custos de investimento | U20: 60000 | V20: Antilhas Holandesas | W20: ANG
U21: 60000 | V21: Arábia Saudita | W21: SAR
B22: =Language!C508 -> Estudo de viabilidade | U22: 61100 | V22: Argélia | W22: DZD
C23: =Language!C509 -> Pesquisa de campo | D23: =Language!C1397 -> d-p | G23: =E23*F23 -> 0 | J23: =G23/$Q$9*I23 -> 0 | O23: =IF(Currency_name="",1,MATCH(Currency_name,currency_list,0)) -> 2 | U23: 61102 | V23: Argentina | W23: ARS
C24: =Language!C510 -> Avaliação de recursos | D24: =$D$28 -> projeto | G24: =E24*F24 -> 0 | J24: =G24/$Q$9*I24 -> 0 | U24: 61118 | V24: Armenia | W24: AMD
C25: =Language!C511 -> Avaliação Ambiental | D25: =$D$23 -> d-p | G25: =E25*F25 -> 0 | J25: =G25/$Q$9*I25 -> 0 | U25: 61128 | V25: Aruba | W25: AWG
C26: =Language!C512 -> Projeto preliminar | D26: =$D$23 -> d-p | G26: =E26*F26 -> 0 | J26: =G26/$Q$9*I26 -> 0 | U26: 61130 | V26: Austrália | W26: AUD
C27: =Language!C513 -> Estimativa detalhada de custos | D27: =$D$23 -> d-p | G27: =E27*F27 -> 0 | J27: =G27/$Q$9*I27 -> 0 | U27: 61132 | V27: Áustria | W27: EUR
C28: =Language!C514 -> Estudo da linha de base e PS dos GEE | D28: =Language!C1399 -> projeto | G28: =E28*F28 -> 0 | J28: =G28/$Q$9*I28 -> 0 | U28: 61134 | V28: Azerbaijão | W28: AZM
C29: =Language!C515 -> Preparação de relatório | D29: =$D$23 -> d-p | G29: =E29*F29 -> 0 | J29: =G29/$Q$9*I29 -> 0 | U29: 61136 | V29: Bahamas | W29: BSD
C30: =Language!C516 -> Gestão do Projeto | D30: =$D$23 -> d-p | G30: =E30*F30 -> 0 | J30: =G30/$Q$9*I30 -> 0 | U30: 61138 | V30: Bahrain | W30: BHD
C31: =Language!C517 -> Viagem & Acomodação | D31: =Language!C1402 -> p-viagem | G31: =E31*F31 -> 0 | J31: =G31/$Q$9*I31 -> 0 | U31: 61140 | V31: Bangladesh | W31: BDT
C32: =F273 -> Definido pelo usuário | D32: custo | G32: =IF(D32=$C$261,-1,1)*E32*F32 -> 0 | J32: =G32/$Q$9*I32 -> 0 | U32: 61142 | V32: Barbados | W32: BBD
G33: =IF(D33=$C$261,-1,1)*E33*F33 -> 0 | J33: =G33/$Q$9*I33 -> 0 | U33: 61142 | V33: Bélgica | W33: EUR
C34: =B22 -> Estudo de viabilidade | D34: custo | G34: =IF(D34=$C$261,-1,1)*E34*F34 -> 0 | J34: =G34/$Q$9*I34 -> 0 | U34: 61100 | V34: Belize | W34: BZD
C35: =Language!C518 -> Subtotal | G35: =IF($Q$6<>TRUE,SUM(G23:G33),G34) -> 0 | H35: =IF(G199=0,"",G35/$G$199) -> 0 | I35: =IF(J35=0,0,J35*$Q$9/G35) -> 0 | J35: =IF($Q$6<>TRUE,SUM(J23:J33),J34) -> 0 | U35: 61100 | V35: Benin | W35: XOF
B36: =Language!C519 -> Desenvolvimento | U36: 61200 | V36: Bermuda | W36: BMD
C37: =Language!C520 -> Negociação do contrato | D37: =$D$23 -> d-p | G37: =E37*F37 -> 0 | J37: =G37/$Q$9*I37 -> 0 | U37: 61202 | V37: Bielorussia | W37: BYR
C38: =Language!C521 -> Licenças e aprovações | D38: =$D$23 -> d-p | G38: =E38*F38 -> 0 | J38: =G38/$Q$9*I38 -> 0 | U38: 61204 | V38: Bolívia | W38: BOB
C39: =Language!C522 -> Visita de campo e registros | D39: =$D$23 -> d-p | G39: =E39*F39 -> 0 | J39: =G39/$Q$9*I39 -> 0 | U39: 61206 | V39: Bosnia-Herzegovina | W39: BAM
C40: =Language!C523 -> Validação e Registro do GEE | D40: =$D$28 -> projeto | G40: =E40*F40 -> 0 | J40: =G40/$Q$9*I40 -> 0 | U40: 61208 | V40: Botswana | W40: BWP
C41: =Language!C524 -> Financiam. do projeto | D41: =$D$23 -> d-p | G41: =E41*F41 -> 0 | J41: =G41/$Q$9*I41 -> 0 | U41: 61210 | V41: Brasil | W41: BRL
C42: =Language!C525 -> Serviços jurídicos e contáveis | D42: =$D$23 -> d-p | G42: =E42*F42 -> 0 | J42: =G42/$Q$9*I42 -> 0 | U42: 61212 | V42: Brunei Darussalam | W42: BND
C43: =C30 -> Gestão do Projeto | D43: =$D$23 -> d-p | G43: =E43*F43 -> 0 | J43: =G43/$Q$9*I43 -> 0 | U43: 61214 | V43: Bulgária | W43: BGL
C44: =C31 -> Viagem & Acomodação | D44: =$D$31 -> p-viagem | G44: =E44*F44 -> 0 | J44: =G44/$Q$9*I44 -> 0 | U44: 61216 | V44: Burkina Faso | W44: XOF
C45: =F273 -> Definido pelo usuário | D45: custo | G45: =IF(D45=$C$261,-1,1)*E45*F45 -> 0 | J45: =G45/$Q$9*I45 -> 0 | U45: 61142 | V45: Burundi | W45: BIF
G46: =IF(D46=$C$261,-1,1)*E46*F46 -> 0 | J46: =G46/$Q$9*I46 -> 0 | U46: 61142 | V46: Butão | W46: BTN
C47: =B36 -> Desenvolvimento | D47: custo | E47: 1 | F47: 100 | G47: =IF(D47=$C$261,-1,1)*E47*F47 -> 100 | J47: =G47/$Q$9*I47 -> 0 | U47: 61200 | V47: Cabo Verde | W47: CVE
C48: =Language!C518 -> Subtotal | G48: =IF($Q$6<>TRUE,SUM(G37:G46),G47) -> 100 | H48: =IF(G199=0,"",G48/$G$199) -> 0.016441622 | I48: =IF(J48=0,0,J48*$Q$9/G48) -> 0 | J48: =IF($Q$6<>TRUE,SUM(J37:J46),J47) -> 0 | U48: 61200 | V48: Camarões | W48: XAF
B49: =Language!C526 -> Engenharia | U49: 61300 | V49: Camboja | W49: KHR
C50: =Language!C527 -> Projeto do prédio | D50: =$D$23 -> d-p | G50: =E50*F50 -> 0 | J50: =G50/$Q$9*I50 -> 0 | U50: 61302 | V50: Canada | W50: CAD
C51: =Language!C528 -> Projeto mecânico | D51: =$D$23 -> d-p | G51: =E51*F51 -> 0 | J51: =G51/$Q$9*I51 -> 0 | U51: 61316 | V51: Catar | W51: QAR
C52: =Language!C529 -> Projeto elétrico | D52: =$D$23 -> d-p | G52: =E52*F52 -> 0 | J52: =G52/$Q$9*I52 -> 0 | U52: 61328 | V52: Cazaquistão | W52: KZT
C53: =Language!C530 -> Projeto civil | D53: =$D$23 -> d-p | G53: =E53*F53 -> 0 | J53: =G53/$Q$9*I53 -> 0 | U53: 61336 | V53: Chade | W53: XAF
C54: =Language!C531 -> Licitação & contratação | D54: =$D$23 -> d-p | G54: =E54*F54 -> 0 | J54: =G54/$Q$9*I54 -> 0 | U54: 61338 | V54: Chile | W54: CLP
C55: =Language!C532 -> Supervisão da construção | D55: =D43 -> d-p | G55: =E55*F55 -> 0 | J55: =G55/$Q$9*I55 -> 0 | U55: 61342 | V55: China | W55: CNY
C56: =F273 -> Definido pelo usuário | D56: custo | G56: =IF(D56=$C$261,-1,1)*E56*F56 -> 0 | J56: =G56/$Q$9*I56 -> 0 | U56: 61142 | V56: Chipre | W56: CYP
G57: =IF(D57=$C$261,-1,1)*E57*F57 -> 0 | J57: =G57/$Q$9*I57 -> 0 | U57: 61142 | V57: Cingapura | W57: SGD
C58: =B49 -> Engenharia | D58: custo | G58: =IF(D58=$C$261,-1,1)*E58*F58 -> 0 | J58: =G58/$Q$9*I58 -> 0 | U58: 61300 | V58: Colombia | W58: COP
C59: =Language!C518 -> Subtotal | G59: =IF($Q$6<>TRUE,SUM(G50:G57),G58) -> 0 | H59: =IF(G199=0,"",G59/$G$199) -> 0 | I59: =IF(J59=0,0,J59*$Q$9/G59) -> 0 | J59: =IF($Q$6<>TRUE,SUM(J50:J57),J58) -> 0 | U59: 61300 | V59: Comores | W59: KMF
B60: =Language!C1284 -> Sistema de produção de eletricidade | U60: 61400 | V60: Congo, Rep. Democ. do | W60: CDF
C61: =IF(HideCodeCA_PowerInt+HideCA_Power_Peak=0,'Modelo Energético'!D868,Language!C231&" - "&'Modelo Energético'!D868) -> Fotovoltaica | D61: =Language!C1364 -> kW | E61: =IF($P$61=0,0,'Modelo Energético'!V870) -> 3.795 | F61: 1500 | G61: =IF(HideCodeCA_power=0,0,IF(E61="",0,E61*F61)) -> 5692.5 | J61: =G61/$Q$9*I61 -> 0 | P61: =IF(HideCodeCA_ProjectT=2,0,IF(OR(HideCode_projectType=2,HideCode_projectType=4,HideCode_projectType=5,HideCode_projectType=7)=TRUE,1,0)) -> 1 | Q61: HideCodeCA_power | U61: 61402 | V61: Congo, Rep. do | W61: XAF
C62: =Language!C241&" - "&'Modelo Energético'!D874 -> Carga Intermediária - | D62: =$D$61 -> kW | E62: =IF($P$61=0,0,'Modelo Energético'!V876) -> 0 | G62: =IF(HideCodeCA_power=0,0,IF(E62="",0,E62*F62)) -> 0 | J62: =G62/$Q$9*I62 -> 0 | O62: =IF(ISERROR(E62),0,IF(OR(E62="",E62=0)=TRUE,0,1)) -> 0 | U62: 61402 | V62: Corea do Norte | W62: KPW
C63: =IF(Iniciar!P3=1,Language!C534&'Modelo Energético '!C530,Language!C534&'Modelo Energético'!Q880) -> Carga de Ponta - Eletricidade da Rede | D63: =$D$61 -> kW | E63: =IF($P$61=0,0,'Modelo Energético'!H946) -> 0 | G63: =IF(HideCodeCA_power=0,0,IF(E63="",0,E63*F63)) -> 0 | J63: =G63/$Q$9*I63 -> 0 | O63: =IF(ISERROR(E63),0,IF(OR(E63="",E63=0)=TRUE,0,1)) -> 0 | P63: =HideCodeEM_Power_Peak -> 2 | Q63: =HideCodeEM_Power_Peak | U63: 61402 | V63: Coréa do Sul | W63: KRW
C64: =Language!C535&'Modelo Energético'!D890 -> Reserva - | D64: =$D$61 -> kW | E64: =IF($P$61=0,"",'Modelo Energético'!D891) -> 0 | G64: =IF(HideCodeCA_power=0,0,IF(E64="",0,E64*F64)) -> 0 | J64: =G64/$Q$9*I64 -> 0 | O64: =IF(ISERROR(E64),0,IF(OR(E64="",E64=0)=TRUE,0,1)) -> 0 | P64: =HideCodeEM_Power_Back -> 0 | Q64: =HideCodeEM_Power_Back | U64: 61402 | V64: Costa do Marfim | W64: XOF
C65: =Language!C536 -> Construção de estrada | D65: km | G65: =E65*F65*$O$65 -> 0 | J65: =G65/$Q$9*I65 -> 0 | O65: =IF(OR(HideCode_projectType=1,HideCode_projectType=3,HideCode_projectType=6),0,1) -> 1 | U65: 61404 | V65: Costa Rica | W65: CRC
C66: =Language!C537 -> Linha de Transmissão | D66: km | G66: =E66*F66*$O$65 -> 0 | J66: =G66/$Q$9*I66 -> 0 | U66: 61406 | V66: Croácia | W66: HRK
C67: =Language!C538 -> Subestação | D67: =$D$28 -> projeto | G67: =E67*F67*$O$65 -> 0 | J67: =G67/$Q$9*I67 -> 0 | U67: 61408 | V67: Cuba | W67: CUP
C68: =Language!C234 -> Ações de Eficiência energética | D68: =$D$28 -> projeto | G68: =E68*F68*$O$65 -> 0 | J68: =G68/$Q$9*I68 -> 0 | U68: 61410 | V68: Dinamarca | W68: DKK
C69: =F273 -> Definido pelo usuário | D69: custo | G69: =IF(D69=$C$261,-1,1)*E69*F69 -> 0 | J69: =G69/$Q$9*I69 -> 0 | U69: 61142 | V69: Djibuti | W69: DJF
G70: =IF(D70=$C$261,-1,1)*E70*F70 -> 0 | J70: =G70/$Q$9*I70 -> 0 | U70: 61142 | V70: Dominica | W70: XCD
C71: =Language!C518 -> Subtotal | G71: =SUM(G61:G70)*HideCodeCA_power -> 5692.5 | H71: =IF(G199=0,"",G71/$G$199) -> 0.93593933 | I71: =IF(J71=0,0,J71*$Q$9/G71) -> 0 | J71: =SUM(J61:J70)*HideCodeCA_power -> 0 | U71: 61400 | V71: Egito | W71: EGP
B72: =Language!C1283 -> Sistema de Aquecimento | U72: 61500 | V72: El Salvador | W72: SVC
C73: =Set_T1 -> Sistema à biomassa | G73: ='Modelo Energético '!G1083 -> 0 | J73: =G73/$Q$9*I73 -> 0 | O73: =IF('Modelo Energético '!EE_HS_CB=TRUE,1,0) -> 0 | U73: 61510 | V73: Emirados Árabes | W73: AED
C74: =Language!C231&" - "&'Modelo Energético'!D894 -> Carga de base - Sistema à biomassa | D74: kW | E74: =IF(D74=$D$261,1,1/E262)*'Modelo Energético'!S895 -> 0 | G74: =IF(HideCodeCA_heat=0,0,IF(E74="",0,E74*F74*O74)) -> 0 | J74: =G74/$Q$9*I74 -> 0 | O74: =IF(HideCodeCA_SWH=1,0,1) -> 1 | P74: =IF(HideCodeCA_ProjectT=2,0,IF(OR(HideCode_projectType=1,HideCode_projectType=4,HideCode_projectType=6,HideCode_projectType=7)=TRUE,1,0)) -> 0 | Q74: HideCodeCA_heat | U74: 61502 | V74: Equador | W74: USD
C75: =Language!C241&" - "&'Modelo Energético'!D898 -> Carga Intermediária - | D75: kW | E75: =IF(D75=$D$261,1,1/E262)*'Modelo Energético'!S899 -> 0 | G75: =IF(HideCodeCA_heat=0,0,IF(E75="",0,E75*F75)) -> 0 | J75: =G75/$Q$9*I75 -> 0 | O75: =IF(ISERROR(E75),0,IF(OR(E75="",E75=0)=TRUE,0,1)) -> 0 | U75: 61502 | V75: Eritréia | W75: ERN
C76: ='Modelo Energético'!O903&" - "&EM_HeatType1 -> Carga Intermediária # 2 - Não necessário | D76: kW | E76: =IF(D76=$D$261,1,1/E262)*'Modelo Energético'!V905*'Modelo Energético'!M902 -> 0 | G76: =IF(HideCodeCA_heat=0,0,IF(E76="",0,E76*F76)) -> 0 | J76: =G76/$Q$9*I76 -> 0 | O76: =IF(ISERROR(E76),0,IF(OR(E76="",E76=0),0,'Modelo Energético'!M902)) -> 0 | U76: 61502 | V76: Eslováquia | W76: SKK
C77: =Language!C534&EM_HeatType2 -> Carga de Ponta - Caldeira | D77: kW | E77: =IF('Modelo Energético'!S916=0,'Modelo Energético'!V915,IF(D77=$D$261,1,1/E262)*'Modelo Energético'!V915*'Modelo Energético'!M911/100) -> 0 | G77: =IF(HideCodeCA_heat=0,0,IF(E77="",0,E77*F77))*HideCA_Heat_Peak/100 -> 0 | J77: =G77/$Q$9*I77 -> 0 | O77: =IF(ISERROR(E77),0,IF(OR(E77="",E77=0)=TRUE,0,1))*P77*IF(HideCodeCA_SWH=1,0,1) -> 0 | P77: =HideCodeEM_Heat_Peak -> 0 | Q77: =HideCodeEM_Heat_Peak | U77: 61502 | V77: Eslovênia | W77: SIT
C78: =Language!C535&'Modelo Energético'!D921 -> Reserva - | D78: kW | E78: =IF(D78=$D$261,1,1/E262)*'Modelo Energético'!S922 -> 0 | G78: =IF(HideCodeCA_heat=0,0,IF(E78="",0,E78*F78)) -> 0 | J78: =G78/$Q$9*I78 -> 0 | O78: =IF(ISERROR(E78),0,IF(OR(E78="",E78=0)=TRUE,0,1)) -> 0 | U78: 61502 | V78: Espanha | W78: EUR
C79: =Language!C539 -> Estação(ões) transfer. de energia | D79: =Language!C1309 -> prédio | E79: ='Carga e Rede'!D33 -> 1 | F79: - | G79: =IF(OR(ISERROR('Carga e Rede'!D93),ISERROR('Carga e Rede'!D98),ISERROR('Carga e Rede'!D96)),0,IF('Carga e Rede'!$D$86='Carga e Rede'!$G$264,'Carga e Rede'!D93,'Carga e Rede'!D98-'Carga e Rede'!D96))*HideCodeCA_Heat_ETS -> 0 | J79: =G79/$Q$9*I79 -> 0 | O79: =IF(OR(HideCode_projectType2=2,HideCode_projectType2=3,HideCode_projectType2=5),0,IF(Iniciar!P4=0,IF(HideCodeLN_HPT<7,0,1),0)) -> 0 | U79: 61504 | V79: Estados Unidos da América | W79: USD
C80: =Language!C541 -> Tubo principal da rede de aquecimento | D80: ='Carga e Rede'!C79 -> m | E80: ='Carga e Rede'!D79 -> 1 | F80: - | G80: =IF('Carga e Rede'!$D$86='Carga e Rede'!$G$264,'Carga e Rede'!D103,'Carga e Rede'!D104)*HideCodeCA_Heat_ETS -> 0 | J80: =G80/$Q$9*I80 -> 0 | U80: 61506 | V80: Estônia | W80: EEK
C81: =Language!C540 -> Tubo - rede de aquecimento secundária | D81: ='Carga e Rede'!C82 -> m | E81: ='Carga e Rede'!D82 -> 0 | F81: - | G81: =IF('Carga e Rede'!$D$86='Carga e Rede'!$G$264,'Carga e Rede'!D95,'Carga e Rede'!D96)*HideCodeCA_Heat_ETS -> 0 | J81: =G81/$Q$9*I81 -> 0 | U81: 61508 | V81: Etiópia | W81: ETB
C82: =C68 -> Ações de Eficiência energética | D82: =$D$28 -> projeto | G82: =E82*F82*HideCodeCA_heat*O82 -> 0 | J82: =G82/$Q$9*I82 -> 0 | O82: =IF(HideCodeCA_SWH=1,0,1) -> 1 | U82: 61512 | V82: Fiji | W82: FJD
C83: =F273 -> Definido pelo usuário | D83: custo | G83: =IF(D83=$C$261,-1,1)*E83*F83 -> 0 | J83: =G83/$Q$9*I83 -> 0 | U83: 61142 | V83: Filipinas | W83: PHP
G84: =IF(D84=$C$261,-1,1)*E84*F84 -> 0 | J84: =G84/$Q$9*I84 -> 0 | U84: 61142 | V84: Finlândia | W84: EUR
C85: =Language!C518 -> Subtotal | G85: =SUM(G73:G84)*HideCodeCA_heat -> 0 | H85: =IF(G199=0,"",G85/$G$199) -> 0 | I85: =IF(J85=0,0,J85*$Q$9/G85) -> 0 | J85: =SUM(J73:J84)*HideCodeCA_heat -> 0 | U85: 61500 | V85: França | W85: EUR
B86: =Language!C542 -> Sistema de refrigeração | U86: 61600 | V86: Gabão | W86: XAF
C87: =Language!C231&" - "&'Modelo Energético'!D925 -> Carga de base - Bomba de calor | D87: kW | E87: =IF(D87=$D$261,1,IF(D87=$D$262,1/E262,E263))*'Modelo Energético'!S927 -> 0 | G87: =IF(HideCodeCA_cool=0,0,IF(E87="",0,E87*F87)) -> 0 | J87: =G87/$Q$9*I87 -> 0 | P87: =IF(HideCodeCA_ProjectT=2,0,IF(OR(HideCode_projectType=3,HideCode_projectType=5,HideCode_projectType=6,HideCode_projectType=7)=TRUE,1,0)) -> 0 | Q87: HideCodeCA_cool | U87: 61602 | V87: Gâmbia | W87: GMD
C88: =Language!C534&'Modelo Energético'!D930 -> Carga de Ponta - Compressor | D88: kW | E88: =IF(D88=$D$261,1,IF(D88=$D$262,1/E262,E263))*IF(P88=0,0,'Modelo Energético'!S932) -> 0 | G88: =IF(HideCodeCA_cool=0,0,IF(E88="",0,E88*F88)) -> 0 | J88: =G88/$Q$9*I88 -> 0 | O88: =IF(ISERROR(E88),0,IF(OR(E88="",E88=0)=TRUE,0,1)) -> 0 | P88: =HideCodeES_Cool_Peak -> 100 | Q88: =HideCodeES_Cool_Peak | U88: 61602 | V88: Gana | W88: GHC
C89: =Language!C535&'Modelo Energético'!D935 -> Reserva - | D89: kW | E89: =IF(D89=$D$261,1,IF(D89=$D$262,1/E262,E263))*'Modelo Energético'!S936 -> 0 | G89: =IF(HideCodeCA_cool=0,0,IF(E89="",0,E89*F89)) -> 0 | J89: =G89/$Q$9*I89 -> 0 | O89: =IF(ISERROR(E89),0,IF(OR(E89="",E89=0)=TRUE,0,1)) -> 0 | U89: 61602 | V89: Georgia | W89: GEL
C90: =C79 -> Estação(ões) transfer. de energia | D90: =D79 -> prédio | E90: ='Carga e Rede'!D138 -> 1 | F90: - | G90: =IF(OR(ISERROR('Carga e Rede'!D198),ISERROR('Carga e Rede'!D203),ISERROR('Carga e Rede'!D201)),0,IF('Carga e Rede'!$D$191='Carga e Rede'!$G$264,'Carga e Rede'!D198,'Carga e Rede'!D203-'Carga e Rede'!D201))*HideCodeCA_Cool_ETS -> 0 | J90: =G90/$Q$9*I90 -> 0 | O90: =IF(OR(HideCode_projectType2<3,HideCode_projectType2=4),0,IF(HideCodeLN_CPT<7,0,1)) -> 0 | U90: 61604 | V90: Gibraltar | W90: GIP
C91: =Language!C544 -> Tubo principal da rede de resfriamento | D91: ='Carga e Rede'!C184 -> m | E91: ='Carga e Rede'!D184 -> 1 | F91: - | G91: =IF('Carga e Rede'!$D$191='Carga e Rede'!$G$264,'Carga e Rede'!D208,'Carga e Rede'!D209)*HideCodeCA_Cool_ETS -> 0 | J91: =G91/$Q$9*I91 -> 0 | U91: 61606 | V91: Grécia | W91: EUR
C92: =Language!C543 -> Tubo - rede de resfriamento secundario | D92: ='Carga e Rede'!C187 -> m | E92: ='Carga e Rede'!D187 -> 0 | F92: - | G92: =IF('Carga e Rede'!$D$191='Carga e Rede'!$G$264,'Carga e Rede'!D200,'Carga e Rede'!D201)*HideCodeCA_Cool_ETS -> 0 | J92: =G92/$Q$9*I92 -> 0 | U92: 61608 | V92: Grenada | W92: XCD
C93: =C68 -> Ações de Eficiência energética | D93: =$D$28 -> projeto | G93: =E93*F93*HideCodeCA_cool -> 0 | J93: =G93/$Q$9*I93 -> 0 | U93: 61610 | V93: Groenlândia | W93: DKK
C94: =F273 -> Definido pelo usuário | D94: custo | G94: =IF(D94=$C$261,-1,1)*E94*F94 -> 0 | J94: =G94/$Q$9*I94 -> 0 | U94: 61142 | V94: Guadalupe | W94: EUR
G95: =IF(D95=$C$261,-1,1)*E95*F95 -> 0 | J95: =G95/$Q$9*I95 -> 0 | U95: 61142 | V95: Guam | W95: USD
C96: =Language!C518 -> Subtotal | G96: =SUM(G87:G95)*HideCodeCA_cool -> 0 | H96: =IF(G199=0,"",G96/$G$199) -> 0 | I96: =IF(J96=0,0,J96*$Q$9/G96) -> 0 | J96: =SUM(J87:J95)*HideCodeCA_cool -> 0 | Q96: =IF(HideCodeCA_ProjectT=1,IF(D100="",10,VLOOKUP(D100,F261:G272,2,FALSE)),10) -> 10 | R96: HideCodeCA_BP | U96: 61600 | V96: Guatemala | W96: GTQ
B97: =IF(O9=900,F270,C68) -> Ações de Eficiência energética | Q97: =Q98 -> 0 | U97: 61690 | V97: Guiana | W97: GYD
C98: =C15 -> Custo inicial incremental | G98: =G15 -> 0 | H98: =IF(G199=0,"",G98/$G$199) -> 0 | J98: =G98/$Q$9*I98 -> 0 | Q98: =O15*IF(HideCodeCA_ProjectT=2,0,1) -> 0 | U98: 61692 | V98: Guiana Francesa | W98: EUR
B99: =Language!C545 -> Balanço do sistema e misc. | Q99: 1 | U99: 61700 | V99: Guiné | W99: GNF
C100: =Language!C546 -> Custos específicos do projeto | D100: Sistema de abastecimento de combustível | Q100: =IF(Q7=TRUE,1,0) -> 0 | U100: 61702 | V100: Guiné Equatorial | W100: XAF
...

Sheet Análise de Emissões
A1: =Language!C870&B188 -> Análise da Redução das Emissões RETScreen - Projeto produção de Eletricidade | N1: =IF(ISERROR(SUM(N2:N13, N40:N195)+GHG_Type),4,SUM(N2:N13, N40:N195)+GHG_Type) -> 3372.8104 | O1: 3372.8104 | P1: TRUE | Q1: GHG | R1: TRUE | S1: Simplified | AB1: 90000 | AC1: radiobuttons | AD1: row | AE1: col | AF1: lrow | AG1: lcol | AH1: value | AI1: group | AK1: checbox | AL1: row | AM1: columns | AN1: link row | AO1: link column | AP1: srow | AQ1: scolumn
P2: TRUE | Q2: CDM | R2: FALSE | S2: Standard | U2: 25 | V2: =Language!$C$587 -> tons CO2 = | W2: =Language!C588 -> 1 ton CH4 | AB2: 90000 | AD2: 5 | AE2: 1 | AF2: 1 | AG2: 18 | AH2: TRUE | AI2: GHG Analysis | AL2: 45 | AM2: 2 | AN2: 45 | AO2: 16 | AP2: 45 | AQ2: 5
C3: =Language!C24 -> Análise de Emissões | P3: FALSE | Q3: Baseline | R3: FALSE | S3: Custom | U3: 298 | V3: =Language!$C$587 -> tons CO2 = | W3: =Language!C589 -> 1 ton N2O | AB3: 91002 | AD3: 6 | AE3: 1 | AF3: 2 | AG3: 18 | AH3: TRUE | AI3: GHG Analysis
S4: EM off-grid | T4: =Iniciar!P3 -> 0 | V4: Project capacity | W4: =IF(OR(R5=2,R5=4,R5=5,R5=7),SUM('Modelo Energético'!H940:H946)-IF('Modelo Energético'!D946='Modelo Energético'!P1066,'Modelo Energético'!H946,0),0)/1000 -> 0.003795 | X4: MW | AB4: 91002 | AD4: 7 | AE4: 1 | AF4: 3 | AG4: 18 | AH4: TRUE | AI4: GHG Analysis
A5: ¤ | C5: =Language!C1811 -> Método 1 | H5: =Language!C585 -> Potencial de Aquecimento global dos GEE | N5: =IF(Link_GHG_Start=TRUE,100+GHG_Type*13,0)+IF(OR(R5=1,R5=3,R5=6),0,1)*IF(EM_gridtype=5,100,0) -> 139 | O5: =IF(Set_Level=1,3,IF(R2=TRUE,1,IF(R3=TRUE,2,3))) -> 3 | P5: =H6 -> 25 | Q5: GHG_POT_mem | R5: =HideCode_projectType -> 2 | S5: Project type | T5: =EM_gridtype -> 1 | U5: EM_gridtype | V5: Energy savings | W5: =(Q64-Q130)/3600 -> 0 | X5: GWh | AB5: 91002
A6: ¡ | C6: =Language!C1812 -> Método 2 | H6: 25 | I6: =IF(GHG_Type=1,Q7,Language!$C$587) -> tons CO2 = | J6: =Language!C588 -> 1 ton CH4 | K6: (IPCC 2007) | N6: =LangIndex -> 23 | P6: =H7 -> 298 | R6: ='Carga e Rede'!M377+'Modelo Energético'!G1179+Q63+IF(AND(R5=2,T5<>5),1,0) -> 20.405197 | S6: if greater than 0 electricity used | AB6: 91002
A7: ¡ | C7: =Language!C1813 -> Método 3 | H7: 298 | I7: =IF(GHG_Type=1,Q8,Language!$C$587) -> tons CO2 = | J7: =Language!C589 -> 1 ton N2O | K7: (IPCC 2007) | P7: 25 | Q7: =U2&" "&Language!$C$587 -> 25 tons CO2 = | R7: =IF(OR(R5=1,R5=3,R5=6),0,100)*0 -> 0 | AB7: 91002
P8: 298 | Q8: =U3&" "&Language!$C$587 -> 298 tons CO2 = | AB8: 91002
AB9: 90000
A10: =Language!C590 -> Sistema elétrico de referência ( Baseline) | N10: =IF(ISERROR(R6),100,IF(R6+R7>0,100,0)) -> 100 | AB10: 92000
AB11: 92000
D12: =Language!C412 -> Mix do combustível | E12: =Language!C591 -> Fator de emissão de CO2 | F12: =Language!C592 -> Fator de emissão de CH4 | G12: =Language!C593 -> Fator de emissão de N2O | H12: =Language!C594 -> Eficiência na geração de eletricidade | J12: =Language!C595 -> Perdas T&D | K12: =Language!C596 -> Fator de emissão de GEE | AB12: 92000
C13: =Language!C211 -> Tipo de Combustível | D13: =Language!C1306 -> % | E13: =Language!C1354 -> kg/GJ | F13: =$E$13 -> kg/GJ | G13: =$E$13 -> kg/GJ | H13: =D13 -> % | J13: =D13 -> % | K13: tCO2/MWh | AB13: 92000
C14: ='Carga e Rede'!P367 -> Gás Natural | D14: 1 | H14: =H26 -> 0 | K14: =IF(OR(HideCode_projectType=1,HideCode_projectType=3,HideCode_projectType=6,EM_gridtype<5),0,IF(D14=0,0,(E14+(F14*$P$5)+(G14*$P$6))*(1/H26)*(1/(1-J14))*3.6*(1/1000))) -> 0 | S14: =IF(OR(H14=0,H14=""),1,H14) -> 1 | T14: =IF(OR(J14=0,J14=""),0,J14) -> 0 | AB14: 92000
B15: Gás Natural | E15: 49.36 | F15: 0.0036253859 | G15: 0.00090634647 | H15: 0.40785591 | K15: =IF(OR(B15="",D15=0),0,(E15+(F15*$P$5)+(G15*$P$6))*(1/H15)*(1/(1-J15))*3.6*(1/1000)) -> 0 | N15: =SUM(N16:N36) -> 16 | O15: 16 | S15: =IF(OR(H15=0,H15=""),1,H15) -> 0.40785591 | T15: =IF(OR(J15=0,J15=""),0,J15) -> 0 | AB15: 92000
K16: =IF(OR(B16="",D16=0),0,(E16+(F16*$P$5)+(G16*$P$6))*(1/H16)*(1/(1-J16))*3.6*(1/1000)) -> 0 | N16: =IF(AND(B15="",B16="",D16=""),1,0) -> 0 | S16: =IF(OR(H16=0,H16=""),1,H16) -> 1 | T16: =IF(OR(J16=0,J16=""),0,J16) -> 0 | W16: GHG reductions | X16: =F189 -> 0 | Y16: tCO2 | AB16: 92000
K17: =IF(OR(B17="",D17=0),0,(E17+(F17*$P$5)+(G17*$P$6))*(1/H17)*(1/(1-J17))*3.6*(1/1000)) -> 0 | N17: =IF(AND(B16="",B17="",D17=""),1,0) -> 1 | S17: =IF(OR(H17=0,H17=""),1,H17) -> 1 | T17: =IF(OR(J17=0,J17=""),0,J17) -> 0 | W17: Simplified project if =2 | X17: =IF(OR(W4>15,W5>15,X16>15000),1,2) -> 2 | AB17: 92000
K18: =IF(OR(B18="",D18=0),0,(E18+(F18*$P$5)+(G18*$P$6))*(1/H18)*(1/(1-J18))*3.6*(1/1000)) -> 0 | N18: =IF(AND(B17="",B18="",D18=""),1,0) -> 1 | S18: =IF(OR(H18=0,H18=""),1,H18) -> 1 | T18: =IF(OR(J18=0,J18=""),0,J18) -> 0 | W18: CDM project Yes =1 | X18: =IF(P2=TRUE,1,0) -> 1 | AB18: 92000
K19: =IF(OR(B19="",D19=0),0,(E19+(F19*$P$5)+(G19*$P$6))*(1/H19)*(1/(1-J19))*3.6*(1/1000)) -> 0 | N19: =IF(AND(B18="",B19="",D19=""),1,0) -> 1 | S19: =IF(OR(H19=0,H19=""),1,H19) -> 1 | T19: =IF(OR(J19=0,J19=""),0,J19) -> 0 | AB19: 92000
K20: =IF(OR(B20="",D20=0),0,(E20+(F20*$P$5)+(G20*$P$6))*(1/H20)*(1/(1-J20))*3.6*(1/1000)) -> 0 | N20: =IF(AND(B19="",B20="",D20=""),1,0) -> 1 | S20: =IF(OR(H20=0,H20=""),1,H20) -> 1 | T20: =IF(OR(J20=0,J20=""),0,J20) -> 0 | AB20: 92000
K21: =IF(OR(B21="",D21=0),0,(E21+(F21*$P$5)+(G21*$P$6))*(1/H21)*(1/(1-J21))*3.6*(1/1000)) -> 0 | N21: =IF(AND(B20="",B21="",D21=""),1,0) -> 1 | S21: =IF(OR(H21=0,H21=""),1,H21) -> 1 | T21: =IF(OR(J21=0,J21=""),0,J21) -> 0 | AB21: 92000
K22: =IF(OR(B22="",D22=0),0,(E22+(F22*$P$5)+(G22*$P$6))*(1/H22)*(1/(1-J22))*3.6*(1/1000)) -> 0 | N22: =IF(AND(B21="",B22="",D22=""),1,0) -> 1 | S22: =IF(OR(H22=0,H22=""),1,H22) -> 1 | T22: =IF(OR(J22=0,J22=""),0,J22) -> 0 | AB22: 92000
K23: =IF(OR(B23="",D23=0),0,(E23+(F23*$P$5)+(G23*$P$6))*(1/H23)*(1/(1-J23))*3.6*(1/1000)) -> 0 | N23: =IF(AND(B22="",B23="",D23=""),1,0) -> 1 | S23: =IF(OR(H23=0,H23=""),1,H23) -> 1 | T23: =IF(OR(J23=0,J23=""),0,J23) -> 0 | AB23: 92000
K24: =IF(OR(B24="",D24=0),0,(E24+(F24*$P$5)+(G24*$P$6))*(1/H24)*(1/(1-J24))*3.6*(1/1000)) -> 0 | N24: =IF(AND(B23="",B24="",D24=""),1,0) -> 1 | S24: =IF(OR(H24=0,H24=""),1,H24) -> 1 | T24: =IF(OR(J24=0,J24=""),0,J24) -> 0 | V24: Unit switch | AB24: 92000
C25: =Language!C598 -> Mix de Eletricidade | D25: =IF(AND(EM_gridtype=5,GHG_EnergyModelUse=0),D14,SUM(D15:D24)) -> 0 | E25: =IF(AND(EM_gridtype=5,GHG_EnergyModelUse=0),$D$14*E14/$S$14/(1-$T$14),SUMPRODUCT($D$15:$D$24*E15:E24/$S$15:$S$24/(1-$T$15:$T$24))) -> 0 | F25: =IF(AND(EM_gridtype=5,GHG_EnergyModelUse=0),$D$14*F14/$S$14/(1-$T$14),SUMPRODUCT($D$15:$D$24*F15:F24/$S$15:$S$24/(1-$T$15:$T$24))) -> 0 | G25: =IF(AND(EM_gridtype=5,GHG_EnergyModelUse=0),$D$14*G14/$S$14/(1-$T$14),SUMPRODUCT($D$15:$D$24*G15:G24/$S$15:$S$24/(1-$T$15:$T$24))) -> 0 | J25: =IF(AND(EM_gridtype=5,GHG_EnergyModelUse=0),J14,SUMPRODUCT(D15:D24,J15:J24)) -> 0 | K25: =IF(AND(EM_gridtype=5,GHG_EnergyModelUse=0),K14,SUMPRODUCT(D15:D24,K15:K24)) -> 0 | S25: =IF(GHG_Type=2,E25,E37) -> 0 | T25: =IF(GHG_Type=2,F25,F37) -> 0 | U25: =IF(GHG_Type=2,G25,G37) -> 0 | AB25: 92000
C26: =C14 -> Gás Natural | D26: =D14 -> 1 | E26: =IF(C26="","",VLOOKUP($C26,$C$207:$F$221,2,FALSE)) -> 54.46 | F26: =IF($C26="","",VLOOKUP($C26,$C$207:$F$221,3,FALSE)) -> 0.004 | G26: =IF($C26="","",VLOOKUP($C26,$C$207:$F$221,4,FALSE)) -> 0.001 | H26: =IF('Carga e Rede'!W222=0,0,'Carga e Rede'!D246*3.6/'Carga e Rede'!W222) -> 0 | K26: =IF(OR(HideCode_projectType=1,HideCode_projectType=3,HideCode_projectType=6,EM_gridtype<5),0,IF(D26=0,0,(E26+(F26*U$2)+(G26*U$3))*(1/H26)*(1/(1-J26))*3.6*(1/1000))) -> 0 | P26: =IF(E26="",0,E26) -> 54.46 | Q26: =IF(F26="",0,F26) -> 0.004 | R26: =IF(G26="",0,G26) -> 0.001 | S26: =IF(OR(H26=0,H26=""),1,H26) -> 1 | T26: =IF(OR(J26=0,J26=""),0,J26) -> 0 | AB26: 92000
B27: Gás Natural | E27: =IF(B27="","",VLOOKUP($B27,$C$207:$F$221,2,FALSE)) -> 54.46 | F27: =IF($B27="","",VLOOKUP($B27,$C$207:$F$221,3,FALSE)) -> 0.004 | G27: =IF($B27="","",VLOOKUP($B27,$C$207:$F$221,4,FALSE)) -> 0.001 | H27: 0.40785591 | K27: =IF(OR(B27="",D27=0),0,(E27+(F27*U$2)+(G27*U$3))*(1/H27)*(1/(1-J27))*3.6*(1/1000)) -> 0 | P27: =IF(E27="",0,E27) -> 54.46 | Q27: =IF(F27="",0,F27) -> 0.004 | R27: =IF(G27="",0,G27) -> 0.001 | S27: =IF(OR(H27=0,H27=""),1,H27) -> 0.40785591 | T27: =IF(OR(J27=0,J27=""),0,J27) -> 0 | AB27: 92000
E28: =IF(B28="","",VLOOKUP($B28,$C$207:$F$221,2,FALSE)) | F28: =IF($B28="","",VLOOKUP($B28,$C$207:$F$221,3,FALSE)) | G28: =IF($B28="","",VLOOKUP($B28,$C$207:$F$221,4,FALSE)) | K28: =IF(OR(B28="",D28=0),0,(E28+(F28*U$2)+(G28*U$3))*(1/H28)*(1/(1-J28))*3.6*(1/1000)) -> 0 | N28: =IF(AND(B27="",B28="",D28=""),1,0) -> 0 | P28: =IF(E28="",0,E28) -> 0 | Q28: =IF(F28="",0,F28) -> 0 | R28: =IF(G28="",0,G28) -> 0 | S28: =IF(OR(H28=0,H28=""),1,H28) -> 1 | T28: =IF(OR(J28=0,J28=""),0,J28) -> 0 | AB28: 92000
E29: =IF(B29="","",VLOOKUP($B29,$C$207:$F$221,2,FALSE)) | F29: =IF($B29="","",VLOOKUP($B29,$C$207:$F$221,3,FALSE)) | G29: =IF($B29="","",VLOOKUP($B29,$C$207:$F$221,4,FALSE)) | K29: =IF(OR(B29="",D29=0),0,(E29+(F29*U$2)+(G29*U$3))*(1/H29)*(1/(1-J29))*3.6*(1/1000)) -> 0 | N29: =IF(AND(B28="",B29="",D29=""),1,0) -> 1 | P29: =IF(E29="",0,E29) -> 0 | Q29: =IF(F29="",0,F29) -> 0 | R29: =IF(G29="",0,G29) -> 0 | S29: =IF(OR(H29=0,H29=""),1,H29) -> 1 | T29: =IF(OR(J29=0,J29=""),0,J29) -> 0 | AB29: 92000
E30: =IF(B30="","",VLOOKUP($B30,$C$207:$F$221,2,FALSE)) | F30: =IF($B30="","",VLOOKUP($B30,$C$207:$F$221,3,FALSE)) | G30: =IF($B30="","",VLOOKUP($B30,$C$207:$F$221,4,FALSE)) | K30: =IF(OR(B30="",D30=0),0,(E30+(F30*U$2)+(G30*U$3))*(1/H30)*(1/(1-J30))*3.6*(1/1000)) -> 0 | N30: =IF(AND(B29="",B30="",D30=""),1,0) -> 1 | P30: =IF(E30="",0,E30) -> 0 | Q30: =IF(F30="",0,F30) -> 0 | R30: =IF(G30="",0,G30) -> 0 | S30: =IF(OR(H30=0,H30=""),1,H30) -> 1 | T30: =IF(OR(J30=0,J30=""),0,J30) -> 0 | AB30: 92000
E31: =IF(B31="","",VLOOKUP($B31,$C$207:$F$221,2,FALSE)) | F31: =IF($B31="","",VLOOKUP($B31,$C$207:$F$221,3,FALSE)) | G31: =IF($B31="","",VLOOKUP($B31,$C$207:$F$221,4,FALSE)) | K31: =IF(OR(B31="",D31=0),0,(E31+(F31*U$2)+(G31*U$3))*(1/H31)*(1/(1-J31))*3.6*(1/1000)) -> 0 | N31: =IF(AND(B30="",B31="",D31=""),1,0) -> 1 | P31: =IF(E31="",0,E31) -> 0 | Q31: =IF(F31="",0,F31) -> 0 | R31: =IF(G31="",0,G31) -> 0 | S31: =IF(OR(H31=0,H31=""),1,H31) -> 1 | T31: =IF(OR(J31=0,J31=""),0,J31) -> 0 | V31: GJ | AB31: 92000
E32: =IF(B32="","",VLOOKUP($B32,$C$207:$F$221,2,FALSE)) | F32: =IF($B32="","",VLOOKUP($B32,$C$207:$F$221,3,FALSE)) | G32: =IF($B32="","",VLOOKUP($B32,$C$207:$F$221,4,FALSE)) | K32: =IF(OR(B32="",D32=0),0,(E32+(F32*U$2)+(G32*U$3))*(1/H32)*(1/(1-J32))*3.6*(1/1000)) -> 0 | N32: =IF(AND(B31="",B32="",D32=""),1,0) -> 1 | P32: =IF(E32="",0,E32) -> 0 | Q32: =IF(F32="",0,F32) -> 0 | R32: =IF(G32="",0,G32) -> 0 | S32: =IF(OR(H32=0,H32=""),1,H32) -> 1 | T32: =IF(OR(J32=0,J32=""),0,J32) -> 0 | AB32: 92000
E33: =IF(B33="","",VLOOKUP($B33,$C$207:$F$221,2,FALSE)) | F33: =IF($B33="","",VLOOKUP($B33,$C$207:$F$221,3,FALSE)) | G33: =IF($B33="","",VLOOKUP($B33,$C$207:$F$221,4,FALSE)) | K33: =IF(OR(B33="",D33=0),0,(E33+(F33*U$2)+(G33*U$3))*(1/H33)*(1/(1-J33))*3.6*(1/1000)) -> 0 | N33: =IF(AND(B32="",B33="",D33=""),1,0) -> 1 | P33: =IF(E33="",0,E33) -> 0 | Q33: =IF(F33="",0,F33) -> 0 | R33: =IF(G33="",0,G33) -> 0 | S33: =IF(OR(H33=0,H33=""),1,H33) -> 1 | T33: =IF(OR(J33=0,J33=""),0,J33) -> 0 | AB33: 92000
E34: =IF(B34="","",VLOOKUP($B34,$C$207:$F$221,2,FALSE)) | F34: =IF($B34="","",VLOOKUP($B34,$C$207:$F$221,3,FALSE)) | G34: =IF($B34="","",VLOOKUP($B34,$C$207:$F$221,4,FALSE)) | K34: =IF(OR(B34="",D34=0),0,(E34+(F34*U$2)+(G34*U$3))*(1/H34)*(1/(1-J34))*3.6*(1/1000)) -> 0 | N34: =IF(AND(B33="",B34="",D34=""),1,0) -> 1 | P34: =IF(E34="",0,E34) -> 0 | Q34: =IF(F34="",0,F34) -> 0 | R34: =IF(G34="",0,G34) -> 0 | S34: =IF(OR(H34=0,H34=""),1,H34) -> 1 | T34: =IF(OR(J34=0,J34=""),0,J34) -> 0 | AB34: 92000
E35: =IF(B35="","",VLOOKUP($B35,$C$207:$F$221,2,FALSE)) | F35: =IF($B35="","",VLOOKUP($B35,$C$207:$F$221,3,FALSE)) | G35: =IF($B35="","",VLOOKUP($B35,$C$207:$F$221,4,FALSE)) | K35: =IF(OR(B35="",D35=0),0,(E35+(F35*U$2)+(G35*U$3))*(1/H35)*(1/(1-J35))*3.6*(1/1000)) -> 0 | N35: =IF(AND(B34="",B35="",D35=""),1,0) -> 1 | P35: =IF(E35="",0,E35) -> 0 | Q35: =IF(F35="",0,F35) -> 0 | R35: =IF(G35="",0,G35) -> 0 | S35: =IF(OR(H35=0,H35=""),1,H35) -> 1 | T35: =IF(OR(J35=0,J35=""),0,J35) -> 0 | AB35: 92000
E36: =IF(B36="","",VLOOKUP($B36,$C$207:$F$221,2,FALSE)) | F36: =IF($B36="","",VLOOKUP($B36,$C$207:$F$221,3,FALSE)) | G36: =IF($B36="","",VLOOKUP($B36,$C$207:$F$221,4,FALSE)) | K36: =IF(OR(B36="",D36=0),0,(E36+(F36*U$2)+(G36*U$3))*(1/H36)*(1/(1-J36))*3.6*(1/1000)) -> 0 | N36: =IF(AND(B35="",B36="",D36=""),1,0) -> 1 | P36: =IF(E36="",0,E36) -> 0 | Q36: =IF(F36="",0,F36) -> 0 | R36: =IF(G36="",0,G36) -> 0 | S36: =IF(OR(H36=0,H36=""),1,H36) -> 1 | T36: =IF(OR(J36=0,J36=""),0,J36) -> 0 | AB36: 92000
C37: =Language!C598 -> Mix de Eletricidade | D37: =IF(AND(EM_gridtype=5,GHG_EnergyModelUse=0),D26,SUMIF(B27:B36,"<>""",D27:D36)) -> 0 | E37: =IF(AND(EM_gridtype=5,GHG_EnergyModelUse=0),$D$26*P26/$S$26/(1-$T$26),SUMPRODUCT($D$27:$D$36*P27:P36/$S$27:$S$36/(1-$T$27:$T$36))) -> 0 | F37: =IF(AND(EM_gridtype=5,GHG_EnergyModelUse=0),$D$26*Q26/$S$26/(1-$T$26),SUMPRODUCT($D$27:$D$36*Q27:Q36/$S$27:$S$36/(1-$T$27:$T$36))) -> 0 | G37: =IF(AND(EM_gridtype=5,GHG_EnergyModelUse=0),$D$26*R26/$S$26/(1-$T$26),SUMPRODUCT($D$27:$D$36*R27:R36/$S$27:$S$36/(1-$T$27:$T$36))) -> 0 | J37: =IF(AND(EM_gridtype=5,GHG_EnergyModelUse=0),J26,SUMPRODUCT(D27:D36,J27:J36)) -> 0 | K37: =IF(AND(EM_gridtype=5,GHG_EnergyModelUse=0),K26,SUMPRODUCT(D27:D36,K27:K36)) -> 0 | AB37: 92000
AB38: 92000
AB39: 92000
B40: =IF(Q43=5,C13,Language!C631) -> País - região | E40: =C13 -> Tipo de Combustível | F40: =Language!C597 -> Fator de Emissão de GEE (excl. T&D) | G40: =J12 -> Perdas T&D | H40: =Language!C596 -> Fator de emissão de GEE | AB40: 92000
F41: tCO2/MWh | G41: =D13 -> % | H41: tCO2/MWh | AB41: 92000
C42: ='Carga e Rede'!P367 -> Gás Natural | H42: =F42*(1/(1-G42)) -> 0 | AB42: 92000
C43: Portugal | E43: Todos os tipos | F43: 0.4194 | G43: 0.07 | H43: =IF(Set_Level=2,F43*(1/(1-G43)),IF(AND(Set_Level=1,Iniciar!P4=0),'Modelo Energético'!F971,'Modelo Energético '!F958)) -> 0.45096774 | N43: =IF(E43="",1,MATCH(E43,N200:N204,0)) -> 1 | P43: =_xlnm.Criteria -> Portugal | Q43: =EM_gridtype -> 1 | AB43: 92000
AA44: 92000 | AB44: 92000
B45: ¨ | C45: =Language!C600 -> Mudanças na linha de base durante projeto | I45: =Language!C604 -> Troca no fator de emissão de GEE | J45: =Language!C1306 -> % | K45: -0.1 | N45: =IF(P45=TRUE,IF(HideCodeGHG_elect=0,111,0),111) -> 111 | P45: FALSE | AA45: 92030 | AB45: 92032
D46: =Language!C601 -> Ano da mudança | I46: =U204&E46&U205 -> Fator de emissão de GEE por ano e além | J46: tCO2/MWh | K46: =IF(GHG_Baseline=0,Q46*(1+K45),Q46) -> 0.45096774 | Q46: =IF(GHG_Type=1,K37,IF(GHG_Type=2,K25,IF(EM_gridtype=5,H42,H43))) -> 0.45096774 | AA46: 92034 | AB46: 92036
D47: =Language!C602 -> Motivo p/ mudança da referência | E47: =Language!C603 -> Nova planta hidroelétrica em construção | AB47: 92038
AB48: 92000
AB49: 90000
A50: =Language!C605 -> Sumário dos GEE do caso de referência (Baseline) | AB50: 93000
AB51: 93000
D52: =D12 -> Mix do combustível | E52: =Language!C591 -> Fator de emissão de CO2 | F52: =Language!C592 -> Fator de emissão de CH4 | G52: =Language!C593 -> Fator de emissão de N2O | I52: =Language!C606 -> Consumo de combustível | J52: =Language!C596 -> Fator de emissão de GEE | K52: =Language!C599 -> Emissão de GEE | AB52: 93000
C53: =C13 -> Tipo de Combustível | D53: =D13 -> % | E53: =$E$13 -> kg/GJ | F53: =$E$13 -> kg/GJ | G53: =$E$13 -> kg/GJ | I53: MWh | J53: tCO2/MWh | K53: =Language!C1409 -> tCO2 | Q53: GJ | S53: =D190 -> e além | AB53: 93000
C54: ='Carga e Rede'!L368 -> Biomassa | D54: =Q54/$Q$64 -> 0 | E54: =VLOOKUP($C54,$C$207:$F$222,2,FALSE) -> 0 | F54: =VLOOKUP($C54,$C$207:$F$222,3,FALSE) -> 0.032 | G54: =VLOOKUP($C54,$C$207:$F$222,4,FALSE) -> 0.004 | I54: =IF($I$53=$X$207,1,1/3.6)*Q54 -> 0 | J54: =IF(GHG_Type=1,IF(D54=0,0,(E54+(F54*U$2)+(G54*U$3))*3.6*(1/1000)),IF(D54=0,0,(E54+(F54*$P$5)+(G54*$P$6))*3.6*(1/1000))) -> 0 | K54: =J54*Q54/3.6 -> 0 | N54: =IF(ISERROR(Q54),10,IF(Q54=0,10,0)) -> 10 | Q54: ='Carga e Rede'!M368 -> 0 | R54: 0 | S54: =J54 -> 0 | AB54: 93000
C55: ='Carga e Rede'!L369 -> Carvão | D55: =Q55/$Q$64 -> 0 | E55: =VLOOKUP($C55,$C$207:$F$222,2,FALSE) -> 95.84 | F55: =VLOOKUP($C55,$C$207:$F$222,3,FALSE) -> 0.015 | G55: =VLOOKUP($C55,$C$207:$F$222,4,FALSE) -> 0.003 | I55: =IF($I$53=$X$207,1,1/3.6)*Q55 -> 0 | J55: =IF(GHG_Type=1,IF(D55=0,0,(E55+(F55*U$2)+(G55*U$3))*3.6*(1/1000)),IF(D55=0,0,(E55+(F55*$P$5)+(G55*$P$6))*3.6*(1/1000))) -> 0 | K55: =J55*Q55/3.6 -> 0 | N55: =IF(ISERROR(Q55),22,IF(Q55=0,22,0)) -> 22 | Q55: ='Carga e Rede'!M369 -> 0 | R55: 0 | S55: =J55 -> 0 | AB55: 93000
C56: ='Carga e Rede'!L370 -> Diesel (oleo#2) | D56: =Q56/$Q$64 -> 0 | E56: =VLOOKUP($C56,$C$207:$F$222,2,FALSE) -> 73.34 | F56: =VLOOKUP($C56,$C$207:$F$222,3,FALSE) -> 0.002 | G56: =VLOOKUP($C56,$C$207:$F$222,4,FALSE) -> 0.002 | I56: =IF($I$53=$X$207,1,1/3.6)*Q56 -> 0 | J56: =IF(GHG_Type=1,IF(D56=0,0,(E56+(F56*U$2)+(G56*U$3))*3.6*(1/1000)),IF(D56=0,0,(E56+(F56*$P$5)+(G56*$P$6))*3.6*(1/1000))) -> 0 | K56: =J56*Q56/3.6 -> 0 | N56: =IF(ISERROR(Q56),11,IF(Q56=0,11,0)) -> 11 | Q56: ='Carga e Rede'!M370 -> 0 | R56: 0 | S56: =J56 -> 0 | AB56: 93000
C57: ='Carga e Rede'!L371 -> Gasolina | D57: =Q57/$Q$64 -> 0 | E57: =VLOOKUP($C57,$C$207:$F$222,2,FALSE) -> 75.69 | F57: =VLOOKUP($C57,$C$207:$F$222,3,FALSE) -> 0.03 | G57: =VLOOKUP($C57,$C$207:$F$222,4,FALSE) -> 0.002 | I57: =IF($I$53=$X$207,1,1/3.6)*Q57 -> 0 | J57: =IF(GHG_Type=1,IF(D57=0,0,(E57+(F57*U$2)+(G57*U$3))*3.6*(1/1000)),IF(D57=0,0,(E57+(F57*$P$5)+(G57*$P$6))*3.6*(1/1000))) -> 0 | K57: =J57*Q57/3.6 -> 0 | N57: =IF(ISERROR(Q57),12,IF(Q57=0,12,0)) -> 12 | Q57: ='Carga e Rede'!M371 -> 0 | R57: 0 | S57: =J57 -> 0 | AB57: 93000
C58: ='Carga e Rede'!L372 -> Querosene | D58: =Q58/$Q$64 -> 0 | E58: =VLOOKUP($C58,$C$207:$F$222,2,FALSE) -> 73.85 | F58: =VLOOKUP($C58,$C$207:$F$222,3,FALSE) -> 0.007 | G58: =VLOOKUP($C58,$C$207:$F$222,4,FALSE) -> 0.002 | I58: =IF($I$53=$X$207,1,1/3.6)*Q58 -> 0 | J58: =IF(GHG_Type=1,IF(D58=0,0,(E58+(F58*U$2)+(G58*U$3))*3.6*(1/1000)),IF(D58=0,0,(E58+(F58*$P$5)+(G58*$P$6))*3.6*(1/1000))) -> 0 | K58: =J58*Q58/3.6 -> 0 | N58: =IF(ISERROR(Q58),13,IF(Q58=0,13,0)) -> 13 | Q58: ='Carga e Rede'!M372 -> 0 | R58: 0 | S58: =J58 -> 0 | AB58: 93000
C59: ='Carga e Rede'!L373 -> Gás Natural | D59: =Q59/$Q$64 -> 0 | E59: =VLOOKUP($C59,$C$207:$F$222,2,FALSE) -> 54.46 | F59: =VLOOKUP($C59,$C$207:$F$222,3,FALSE) -> 0.004 | G59: =VLOOKUP($C59,$C$207:$F$222,4,FALSE) -> 0.001 | I59: =IF($I$53=$X$207,1,1/3.6)*Q59 -> 0 | J59: =IF(GHG_Type=1,IF(D59=0,0,(E59+(F59*U$2)+(G59*U$3))*3.6*(1/1000)),IF(D59=0,0,(E59+(F59*$P$5)+(G59*$P$6))*3.6*(1/1000))) -> 0 | K59: =J59*Q59/3.6 -> 0 | N59: =IF(ISERROR(Q59),14,IF(Q59=0,14,0)) -> 14 | Q59: ='Carga e Rede'!M373 -> 0 | R59: 0 | S59: =J59 -> 0 | AB59: 93000
C60: ='Carga e Rede'!L374 -> Óleo (#6) | D60: =Q60/$Q$64 -> 0 | E60: =VLOOKUP($C60,$C$207:$F$222,2,FALSE) -> 77.83 | F60: =VLOOKUP($C60,$C$207:$F$222,3,FALSE) -> 0.003 | G60: =VLOOKUP($C60,$C$207:$F$222,4,FALSE) -> 0.002 | I60: =IF($I$53=$X$207,1,1/3.6)*Q60 -> 0 | J60: =IF(GHG_Type=1,IF(D60=0,0,(E60+(F60*U$2)+(G60*U$3))*3.6*(1/1000)),IF(D60=0,0,(E60+(F60*$P$5)+(G60*$P$6))*3.6*(1/1000))) -> 0 | K60: =J60*Q60/3.6 -> 0 | N60: =IF(ISERROR(Q60),111,IF(Q60=0,111,0)) -> 111 | Q60: ='Carga e Rede'!M374 -> 0 | R60: 0 | S60: =J60 -> 0 | AB60: 93000
C61: ='Carga e Rede'!L375 -> Propano | D61: =Q61/$Q$64 -> 0 | E61: =VLOOKUP($C61,$C$207:$F$222,2,FALSE) -> 67.92 | F61: =VLOOKUP($C61,$C$207:$F$222,3,FALSE) -> 0.001 | G61: =VLOOKUP($C61,$C$207:$F$222,4,FALSE) -> 0.001 | I61: =IF($I$53=$X$207,1,1/3.6)*Q61 -> 0 | J61: =IF(GHG_Type=1,IF(D61=0,0,(E61+(F61*U$2)+(G61*U$3))*3.6*(1/1000)),IF(D61=0,0,(E61+(F61*$P$5)+(G61*$P$6))*3.6*(1/1000))) -> 0 | K61: =J61*Q61/3.6 -> 0 | N61: =IF(ISERROR(Q61),15,IF(Q61=0,15,0)) -> 15 | Q61: ='Carga e Rede'!M375 -> 0 | R61: 0 | S61: =J61 -> 0 | AB61: 93000
C62: ='Carga e Rede'!L376 -> Combustível definido pelo usuário | D62: =Q62/$Q$64 -> 0 | E62: =VLOOKUP($C62,$C$207:$F$222,2,FALSE) -> 0 | F62: =VLOOKUP($C62,$C$207:$F$222,3,FALSE) -> 0 | G62: =VLOOKUP($C62,$C$207:$F$222,4,FALSE) -> 0 | I62: =IF($I$53=$X$207,1,1/3.6)*Q62 -> 0 | J62: =IF(GHG_Type=1,IF(D62=0,0,(E62+(F62*U$2)+(G62*U$3))*3.6*(1/1000)),IF(D62=0,0,(E62+(F62*$P$5)+(G62*$P$6))*3.6*(1/1000))) -> 0 | K62: =J62*Q62/3.6 -> 0 | N62: =IF(ISERROR(Q62),16,IF(Q62=0,16,0)) -> 16 | Q62: =IF(ISERROR('Carga e Rede'!M376),0,'Carga e Rede'!M376) -> 0 | R62: 0 | S62: =J62 -> 0 | AB62: 93000
C63: ='Carga e Rede'!L377 -> Eletricidade | D63: =Q63/$Q$64 -> 1 | E63: =VLOOKUP($C63,$C$207:$F$222,2,FALSE) -> 0 | F63: =VLOOKUP($C63,$C$207:$F$222,3,FALSE) -> 0 | G63: =VLOOKUP($C63,$C$207:$F$222,4,FALSE) -> 0 | I63: =IF($I$53=$X$207,1,1/3.6)*Q63 -> 5.3903326 | J63: =IF(GHG_Type=1,IF(D63=0,0,(E63+(F63*U$2)+(G63*U$3))*3.6*(1/1000)),IF(D63=0,0,(E63+(F63*$P$5)+(G63*$P$6))*3.6*(1/1000))) -> 0 | K63: =J63*Q63/3.6 -> 0 | N63: =IF(ISERROR(Q63),17,IF(Q63=0,17,0)) -> 0 | Q63: ='Carga e Rede'!M377+IF(OR(R5=9,R5=8,T5=5),0,1)*SUM('Modelo Energético'!J1107:J1108)*3.6 -> 19.405197 | R63: 19.405197 | S63: =K46 -> 0.45096774 | AB63: 93000
C64: =J169 -> Total | D64: =SUM(D54:D63) -> 1 | E64: =SUMPRODUCT($D$54:$D$63*E54:E63) -> 0 | F64: =SUMPRODUCT($D$54:$D$63*F54:F63) -> 0 | G64: =SUMPRODUCT($D$54:$D$63*G54:G63) -> 0 | I64: =IF($I$53=$X$207,1,1/3.6)*Q64 -> 5.3903326 | J64: =SUMPRODUCT($D$54:$D$63,J54:J63) -> 0 | K64: =J64*Q64/3.6 -> 0 | N64: =Q64 -> 19.405197 | Q64: =IF(SUM(Q54:Q63)=0,1,SUM(Q54:Q63)) -> 19.405197 | R64: 19.405197 | S64: =SUMPRODUCT($D$54:$D$63,S54:S63) -> 0.45096774 | AB64: 93000
C65: =C54 -> Biomassa | D65: =D54 -> 0 | I65: =IF($I$53=$X$207,1,1/3.6)*Q65 -> 0 | J65: =IF(GHG_Type=1,IF(D65=0,0,(E65+(F65*U$2)+(G65*U$3))*3.6*(1/1000)),IF(D65=0,0,(E65+(F65*$P$5)+(G65*$P$6))*3.6*(1/1000))) -> 0 | K65: =J65*Q65/3.6 -> 0 | Q65: =Q54 -> 0 | S65: =J65 -> 0 | AB65: 93000
C66: =C55 -> Carvão | D66: =D55 -> 0 | I66: =IF($I$53=$X$207,1,1/3.6)*Q66 -> 0 | J66: =IF(GHG_Type=1,IF(D66=0,0,(E66+(F66*U$2)+(G66*U$3))*3.6*(1/1000)),IF(D66=0,0,(E66+(F66*$P$5)+(G66*$P$6))*3.6*(1/1000))) -> 0 | K66: =J66*Q66/3.6 -> 0 | Q66: =Q55 -> 0 | S66: =J66 -> 0 | AB66: 93000
C67: =C56 -> Diesel (oleo#2) | D67: =D56 -> 0 | I67: =IF($I$53=$X$207,1,1/3.6)*Q67 -> 0 | J67: =IF(GHG_Type=1,IF(D67=0,0,(E67+(F67*U$2)+(G67*U$3))*3.6*(1/1000)),IF(D67=0,0,(E67+(F67*$P$5)+(G67*$P$6))*3.6*(1/1000))) -> 0 | K67: =J67*Q67/3.6 -> 0 | Q67: =Q56 -> 0 | S67: =J67 -> 0 | AB67: 93000
C68: =C57 -> Gasolina | D68: =D57 -> 0 | I68: =IF($I$53=$X$207,1,1/3.6)*Q68 -> 0 | J68: =IF(GHG_Type=1,IF(D68=0,0,(E68+(F68*U$2)+(G68*U$3))*3.6*(1/1000)),IF(D68=0,0,(E68+(F68*$P$5)+(G68*$P$6))*3.6*(1/1000))) -> 0 | K68: =J68*Q68/3.6 -> 0 | Q68: =Q57 -> 0 | S68: =J68 -> 0 | AB68: 93000
C69: =C58 -> Querosene | D69: =D58 -> 0 | I69: =IF($I$53=$X$207,1,1/3.6)*Q69 -> 0 | J69: =IF(GHG_Type=1,IF(D69=0,0,(E69+(F69*U$2)+(G69*U$3))*3.6*(1/1000)),IF(D69=0,0,(E69+(F69*$P$5)+(G69*$P$6))*3.6*(1/1000))) -> 0 | K69: =J69*Q69/3.6 -> 0 | Q69: =Q58 -> 0 | S69: =J69 -> 0 | AB69: 93000
C70: =C59 -> Gás Natural | D70: =D59 -> 0 | I70: =IF($I$53=$X$207,1,1/3.6)*Q70 -> 0 | J70: =IF(GHG_Type=1,IF(D70=0,0,(E70+(F70*U$2)+(G70*U$3))*3.6*(1/1000)),IF(D70=0,0,(E70+(F70*$P$5)+(G70*$P$6))*3.6*(1/1000))) -> 0 | K70: =J70*Q70/3.6 -> 0 | Q70: =Q59 -> 0 | S70: =J70 -> 0 | AB70: 93000
C71: =C60 -> Óleo (#6) | D71: =D60 -> 0 | I71: =IF($I$53=$X$207,1,1/3.6)*Q71 -> 0 | J71: =IF(GHG_Type=1,IF(D71=0,0,(E71+(F71*U$2)+(G71*U$3))*3.6*(1/1000)),IF(D71=0,0,(E71+(F71*$P$5)+(G71*$P$6))*3.6*(1/1000))) -> 0 | K71: =J71*Q71/3.6 -> 0 | Q71: =Q60 -> 0 | S71: =J71 -> 0 | AB71: 93000
C72: =C61 -> Propano | D72: =D61 -> 0 | I72: =IF($I$53=$X$207,1,1/3.6)*Q72 -> 0 | J72: =IF(GHG_Type=1,IF(D72=0,0,(E72+(F72*U$2)+(G72*U$3))*3.6*(1/1000)),IF(D72=0,0,(E72+(F72*$P$5)+(G72*$P$6))*3.6*(1/1000))) -> 0 | K72: =J72*Q72/3.6 -> 0 | Q72: =Q61 -> 0 | S72: =J72 -> 0 | AB72: 93000
C73: =C62 -> Combustível definido pelo usuário | D73: =D62 -> 0 | I73: =IF($I$53=$X$207,1,1/3.6)*Q73 -> 0 | J73: =IF(GHG_Type=1,IF(D73=0,0,(E73+(F73*U$2)+(G73*U$3))*3.6*(1/1000)),IF(D73=0,0,(E73+(F73*$P$5)+(G73*$P$6))*3.6*(1/1000))) -> 0 | K73: =J73*Q73/3.6 -> 0 | Q73: =Q62 -> 0 | S73: =J73 -> 0 | AB73: 93000
C74: =C63 -> Eletricidade | D74: =D63 -> 1 | E74: =E63 -> 0 | F74: =F63 -> 0 | G74: =G63 -> 0 | I74: =IF($I$53=$X$207,1,1/3.6)*Q74 -> 5.3903326 | J74: =IF(GHG_Type=1,IF(D74=0,0,(E74+(F74*U$2)+(G74*U$3))*3.6*(1/1000)),IF(D74=0,0,(E74+(F74*$P$5)+(G74*$P$6))*3.6*(1/1000))) -> 0 | K74: =J74*Q74/3.6 -> 0 | Q74: =Q63 -> 19.405197 | S74: =K46 -> 0.45096774 | AB74: 93000
C75: =J169 -> Total | D75: =SUM(D65:D74) -> 1 | E75: =SUMPRODUCT($D$54:$D$63*E65:E74) -> 0 | F75: =SUMPRODUCT($D$54:$D$63*F65:F74) -> 0 | G75: =SUMPRODUCT($D$54:$D$63*G65:G74) -> 0 | I75: =IF($I$53=$X$207,1,1/3.6)*Q75 -> 5.3903326 | J75: =SUMPRODUCT($D$65:$D$74,J65:J74) -> 0 | K75: =J75*Q75/3.6 -> 0 | Q75: =SUM(Q65:Q74) -> 19.405197 | S75: =SUMPRODUCT($D$65:$D$74,S65:S74) -> 0.45096774 | AB75: 93000
C76: =C54 -> Biomassa | D76: =D54 -> 0 | I76: =IF($I$53=$X$207,1,1/3.6)*Q76 -> 0 | J76: =IF(C76=$C$222,$H$43,J54) -> 0 | K76: =J76*Q76/3.6 -> 0 | Q76: =Q54 -> 0 | S76: =J76 -> 0 | AB76: 93000
C77: =C55 -> Carvão | D77: =D55 -> 0 | I77: =IF($I$53=$X$207,1,1/3.6)*Q77 -> 0 | J77: =IF(C77=$C$222,$H$43,J55) -> 0 | K77: =J77*Q77/3.6 -> 0 | Q77: =Q55 -> 0 | S77: =J77 -> 0 | AB77: 93000
C78: =C56 -> Diesel (oleo#2) | D78: =D56 -> 0 | I78: =IF($I$53=$X$207,1,1/3.6)*Q78 -> 0 | J78: =IF(C78=$C$222,$H$43,J56) -> 0 | K78: =J78*Q78/3.6 -> 0 | Q78: =Q56 -> 0 | S78: =J78 -> 0 | AB78: 93000
C79: =C57 -> Gasolina | D79: =D57 -> 0 | I79: =IF($I$53=$X$207,1,1/3.6)*Q79 -> 0 | J79: =IF(C79=$C$222,$H$43,J57) -> 0 | K79: =J79*Q79/3.6 -> 0 | Q79: =Q57 -> 0 | S79: =J79 -> 0 | AB79: 93000
C80: =C58 -> Querosene | D80: =D58 -> 0 | I80: =IF($I$53=$X$207,1,1/3.6)*Q80 -> 0 | J80: =IF(C80=$C$222,$H$43,J58) -> 0 | K80: =J80*Q80/3.6 -> 0 | Q80: =Q58 -> 0 | S80: =J80 -> 0 | AB80: 93000
C81: =C59 -> Gás Natural | D81: =D59 -> 0 | I81: =IF($I$53=$X$207,1,1/3.6)*Q81 -> 0 | J81: =IF(C81=$C$222,$H$43,J59) -> 0 | K81: =J81*Q81/3.6 -> 0 | Q81: =Q59 -> 0 | S81: =J81 -> 0 | AB81: 93000
C82: =C60 -> Óleo (#6) | D82: =D60 -> 0 | I82: =IF($I$53=$X$207,1,1/3.6)*Q82 -> 0 | J82: =IF(C82=$C$222,$H$43,J60) -> 0 | K82: =J82*Q82/3.6 -> 0 | Q82: =Q60 -> 0 | S82: =J82 -> 0 | AB82: 93000
C83: =C61 -> Propano | D83: =D61 -> 0 | I83: =IF($I$53=$X$207,1,1/3.6)*Q83 -> 0 | J83: =IF(C83=$C$222,$H$43,J61) -> 0 | K83: =J83*Q83/3.6 -> 0 | Q83: =Q61 -> 0 | S83: =J83 -> 0 | AB83: 93000
C84: =C62 -> Combustível definido pelo usuário | D84: =D62 -> 0 | I84: =IF($I$53=$X$207,1,1/3.6)*Q84 -> 0 | J84: =IF(C84=$C$222,$H$43,J62) -> 0 | K84: =J84*Q84/3.6 -> 0 | Q84: =Q62 -> 0 | S84: =J84 -> 0 | AB84: 93000
C85: =C63 -> Eletricidade | D85: =D63 -> 1 | I85: =IF($I$53=$X$207,1,1/3.6)*Q85 -> 5.3903326 | J85: =IF(C85=$C$222,IF(AND(EM_gridtype=5,GHG_EnergyModelUse=0),H42,$H$43),J63) -> 0.45096774 | K85: =J85*Q85/3.6 -> 2.4308661 | Q85: =Q63 -> 19.405197 | S85: =K46 -> 0.45096774 | AB85: 93000
C86: =J169 -> Total | D86: =SUM(D76:D85) -> 1 | I86: =IF($I$53=$X$207,1,1/3.6)*Q86 -> 5.3903326 | J86: =SUMPRODUCT($D$76:$D$85,J76:J85) -> 0.45096774 | K86: =J86*Q86/3.6 -> 2.4308661 | Q86: =SUM(Q76:Q85) -> 19.405197 | S86: =SUMPRODUCT($D$76:$D$85,S76:S85) -> 0.45096774 | AB86: 93000
AB87: 93000
E88: =Language!C591 -> Fator de emissão de CO2 | F88: =Language!C592 -> Fator de emissão de CH4 | G88: =Language!C593 -> Fator de emissão de N2O | I88: =Language!C607 -> Potencial de biogás | J88: =Language!C596 -> Fator de emissão de GEE | AB88: 93000
E89: =$E$13 -> kg/GJ | F89: =$E$13 -> kg/GJ | G89: =$E$13 -> kg/GJ | I89: GJ | J89: tCO2/MWh | Q89: GJ | AB89: 93000
C90: =Language!C608 -> Biogás queimado | E90: =D255 -> 0 | F90: =E255 -> 0 | G90: =F255 -> 0 | I90: =IF($I$89=$X$207,1,1/3.6)*Q90 -> 0 | J90: =IF(GHG_Type=1,(E90+(F90*U$2)+(G90*U$3))*3.6*(1/1000),(E90+(F90*$P$5)+(G90*$P$6))*3.6*(1/1000)) -> 0 | K90: =J90*Q90/3.6*O90 -> 0 | N90: =IF(ISERROR(GHG_LFG_F),0,IF(GHG_LFG_F>SMIN,193,0)) -> 0 | O90: =IF(ISERROR(VLOOKUP('Modelo Energético'!B1226,C117:C126,1,FALSE)),0,1) -> 0 | Q90: =IF(Ferramentas!D417=Ferramentas!B670,Ferramentas!N414*Ferramentas!D418,0)*O90 -> 0 | AB90: 93000
C91: =Language!C609 -> Emissões de biogás | E91: 0 | F91: =Ferramentas!D404 -> 17.988134 | G91: 0 | I91: =IF($I$89=$X$207,1,1/3.6)*Q91 -> 0 | J91: =IF(GHG_Type=1,(E91+(F91*U$2)+(G91*U$3))*3.6*(1/1000),(E91+(F91*$P$5)+(G91*$P$6))*3.6*(1/1000)) -> 1.618932 | K91: =J91*Q91/3.6*O90 -> 0 | Q91: =IF(ISERROR(Ferramentas!$N$414),0,(Ferramentas!$N$414-Q90)*O90) -> 0 | AB91: 93000
C92: =Language!C608 -> Biogás queimado | I92: =IF($I$89=$X$207,1,1/3.6)*Q92 -> 0 | J92: =IF(GHG_Type=1,(E92+(F92*U$2)+(G92*U$3))*3.6*(1/1000),(E92+(F92*$P$5)+(G92*$P$6))*3.6*(1/1000)) -> 0 | K92: =J92*Q92/3.6*O90 -> 0 | Q92: =Q90 -> 0 | AB92: 93000
C93: =Language!C609 -> Emissões de biogás | I93: =IF($I$89=$X$207,1,1/3.6)*Q93 -> 0 | J93: =IF(GHG_Type=1,(E93+(F93*U$2)+(G93*U$3))*3.6*(1/1000),(E93+(F93*$P$5)+(G93*$P$6))*3.6*(1/1000)) -> 0 | K93: =J93*Q93/3.6*O90 -> 0 | Q93: =Q91 -> 0 | AB93: 93000
C94: =Language!C608 -> Biogás queimado | I94: =IF($I$89=$X$207,1,1/3.6)*Q94 -> 0 | J94: =J90 -> 0 | K94: =J94*Q94/3.6*O90 -> 0 | Q94: =Q90 -> 0 | AB94: 93000
C95: =Language!C609 -> Emissões de biogás | I95: =IF($I$89=$X$207,1,1/3.6)*Q95 -> 0 | J95: =J91 -> 1.618932 | K95: =J95*Q95/3.6*O90 -> 0 | Q95: =Q91 -> 0 | AB95: 93000
J96: =J169 -> Total | K96: =IF(GHG_Type=1,K64+K90+K91,IF(GHG_Type=2,K75+K92+K93,K86+K94+K95)) -> 2.4308661 | AB96: 93000
N97: =IF(SUM($N$100:$N$109)=0,0,1) -> 0 | AB97: 93000
I98: =Language!C1477 -> Perda anual do refrigerante | J98: =Language!C1699 -> Potencial de aquecimento global | N98: =IF(SUM($N$100:$N$109)=0,0,1) -> 0 | AB98: 93000
H99: =Language!C1932 -> Refrigerante | I99: =Language!C1352 -> kg | J99: tCO2/t | N99: =IF(SUM($N$100:$N$109)=0,0,1) -> 0 | AB99: 93000
C100: =IF(EET!D22="","",EET!D22) | H100: =EET!AC22 -> 0 | I100: =EET!AF22*'Modelo Energético '!M47*IF('Modelo Energético '!Q47=TRUE,1,0)*IF($R$5=8,1,0) -> 0 | J100: =IF(H100=$N$453,EET!AI22,VLOOKUP(H100,$N$340:$O$452,2,FALSE)) -> #N/A | K100: =IF(ISERROR(I100*J100),0,I100*J100/1000)*IF(GHG_Type=2,0,1) -> 0 | N100: =IF(K100=0,0,1) -> 0 | AB100: 93000
...

Sheet Análise Financeira
A1: =Language!C2603&'Análise de Emissões'!B188 -> Análise Financeira RETScreen -Projeto produção de Eletricidade | T1: =HideCode_projectType -> 2 | U1: project type | V1: =IF(OR(Iniciar!O26=1,Iniciar!O26=3),1,2) -> 1 | W1: Grid type | AB1: 0 | AC1: -93.996927 | BG1: 70000 | BH1: 70000 | BI1: 70000 | BM1: Checbox | BN1: row | BO1: columns | BP1: link row | BQ1: link column | BR1: srow | BS1: scolumn
T2: =GHG -> 139 | U2: GHG use | BA2: ='Análise de Custos'!E254 -> 10 | BB2: ='Análise de Custos'!E255 -> 0 | BG2: 70000 | BH2: 70000 | BI2: 70000 | BN2: 20 | BO2: 4 | BP2: 81 | BQ2: 21 | BR2: 20 | BS2: 3
A3: =Language!C647 -> Parâmetros financeiros | F3: =Language!C682 -> Custo projeto e sumario econ./receita | M3: =Language!C642 -> Fluxo de caixa anual | T3: Cash Outflows | AA3: Cash Inflows | AH3: Net Cash Flows | AJ3: Tax Analysis | AR3: Taxes | AS3: Taxes | AU3: Taxes | AW3: Debt Service Coverage Analysis | BA3: Periodic Costs (Credits) | BG3: 72000 | BH3: 74000 | BI3: 76000 | BN3: 38 | BO3: 4 | BP3: 84 | BQ3: 21 | BR3: 38 | BS3: 3
A4: =Language!C657 -> Geral | F4: =Language!C683 -> Custos iniciais | M4: =Language!C643 -> Ano | N4: =Language!C644 -> Antes imposto | O4: =Language!C645 -> Após imposto | P4: =Language!C646 -> Cumulativo | T4: Init. cost | U4: O&M | V4: Fuel/el. | W4: Debt ser. | X4: Pre-tax | Y4: Taxes | Z4: After-tax | AA4: Energy Inc | AB4: Power sales | AC4: RE credit | AD4: Income | AE4: Incentive | AF4: Life end | AG4: Pre-tax | AH4: Pre-tax | AI4: After-tax | AJ4: Invest. | AK4: Principal | AL4: UCC | AM4: CCA $ | AN4: CCA $ | AO4: CAA $ | AP4: UCC | AQ4: Net Inc. | AR4: Flow-through | AS4: no carry | AT4: reserve | AU4: w/ carry | AV4: reserve | AW4: Opera. | AX4: Op. inc. | AY4: Service | AZ4: Coverage | BA4: Sch. 1 | BB4: Sch 2 | BC4: Sch. 1 | BD4: Sch 2 | BE4: Pre | BF4: After | BG4: 72100 | BH4: 74100 | BI4: 76000 | BN4: 48 | BO4: 4 | BP4: 82 | BQ4: 21 | BR4: 48 | BS4: 3
B5: =Language!C658 -> Reajuste do custo do combustível | C5: =C46 -> % | D5: 0.04 | G5: =Language!C508 -> Estudo de viabilidade | I5: =IF($K$14=0,"",K5/K$14) -> 0 | J5: =Currency -> € | K5: =IF(U58=2,IF(HideCodeCA_ProjectT=2,0,'Análise de Custos'!G35),0) -> 0 | M5: # | N5: =Currency -> € | O5: =Currency -> € | P5: =Currency -> € | S5: 0 | T5: ($) | U5: ($) | V5: ($) | W5: ($) | X5: total ($) | Y5: ($) | Z5: total ($) | AA5: ($) | AB5: ($) | AC5: ($) | AD5: GHG ($) | AE5: ($) | AF5: ($) | AG5: total ($) | AH5: ($) | AI5: total ($) | AJ5: ($) | AK5: ($) | AL5: beg ($) | AM5: None | AN5: DB | AO5: SL | AP5: end ($) | AQ5: ($) | AR5: ($) | AS5: ($) | AT5: beg ($) | AU5: ($) | AV5: end ($) | AW5: C/F($) | AX5: cum.($) | AY5: Debt ($) | AZ5: ($) | BA5: ($) | BB5: ($) | BC5: (yr) | BD5: (yr) | BE5: ROA | BF5: ROA | BG5: 72102 | BH5: 74102 | BI5: 76000 | BN5: 57 | BO5: 4 | BP5: 85 | BQ5: 21 | BR5: 57 | BS5: 3
B6: =Language!C659 -> Taxa de inflação | C6: =C46 -> % | D6: 0.03 | G6: =Language!C519 -> Desenvolvimento | I6: =IF($K$14=0,"",K6/K$14) -> 0.016441622 | J6: =Currency -> € | K6: =IF(U58=2,IF(HideCodeCA_ProjectT=2,0,'Análise de Custos'!G48),0) -> 100 | M6: 0 | N6: =AH6 -> -6082.125 | O6: =AI6 -> -6082.125 | P6: =O6 -> -6082.125 | S6: 100 | T6: =Equi_inv -> 6082.125 | U6: 0 | V6: 0 | W6: 0 | X6: =SUM(T6:W6)+SUM(BA6:BB6) -> 6082.125 | Y6: =IF(AND(W$63=1,M6<=D$29,M6>0),MIN(IF(W$62=1,AU6,IF(W$62=2,AS6,AR6)),0),IF(W$62=1,AU6,IF(W$62=2,AS6,AR6))) -> 0 | Z6: =X6+Y6 -> 6082.125 | AA6: 0 | AB6: 0 | AC6: 0 | AD6: 0 | AE6: =U65 -> 0 | AF6: =IF(M6=ProjLife,-K$27*#REF!,0) -> 0 | AG6: =SUM(AA6:AF6) -> 0 | AH6: =AG6-X6 -> -6082.125 | AI6: =-Z6+AG6 -> -6082.125 | AJ6: =T6 -> 6082.125 | AK6: 0 | AL6: =Init_costs -> 6082.125 | AM6: =IF(M6<U$64,0,-AL6) -> 0 | AN6: =-(1-D$25)*Init_costs -> -6082.125 | AO6: =-(1-D$25)*Init_costs -> -6082.125 | AP6: =AL6+IF(C$23=$X$81,AM6, IF(C$23=$X$82,AN6,AO6)) -> 0 | AQ6: =AH6+AJ6+AK6+IF(C$23=$X$81,AM6,IF(C$23=$X$82,AN6,AO6)) -> -6082.125 | AR6: =IF($W$61=1,D$21*AQ6,0) -> 0 | AS6: =IF(AR6<0,0,AR6) -> 0 | AT6: 0 | AU6: =MAX(AR6+AT6,0) -> 0 | AV6: =AT6+AR6-AU6 -> 0 | AW6: =AH6+W6 -> -6082.125 | AX6: =P6-O$6 -> 0 | AY6: =W6 -> 0 | AZ6: =IF(AY6<>0,(MAX(AW6,AX6)/AY6),"N/A") -> N/A | BA6: 0 | BB6: 0 | BC6: =IF(M6*$BA$2<=U$64,(IF(M6<=1,"",",")&TEXT(M6*$BA$2,"0"))," ") -> 0 | BD6: =IF(M6*$BB$2<=U$64,(IF(M6<=1,"",",")&TEXT(M6*$BB$2,"0"))," ") -> 0 | BE6: =-Init_costs+AG6 -> -6082.125 | BF6: =-Init_costs+AG6+Y6 -> -6082.125 | BG6: 72104 | BH6: 74104 | BI6: 76000 | BN6: 63 | BO6: 4 | BP6: 83 | BQ6: 21 | BR6: 63 | BS6: 3
B7: =Language!C660 -> Taxa de desconto | C7: =C46 -> % | D7: 0.025 | G7: =Language!C526 -> Engenharia | I7: =IF($K$14=0,"",K7/K$14) -> 0 | J7: =Currency -> € | K7: =IF(U58=2,IF(HideCodeCA_ProjectT=2,0,'Análise de Custos'!G59),0) -> 0 | M7: 1 | N7: =AH7 -> 812.18917 | O7: =AI7 -> 812.18917 | P7: =P6+O7 -> -5269.9358 | S7: 0 | U7: =IF(M7<=ProjLife,K$19*(1+$U$62)^M7,0) -> 309 | V7: =IF(M7<=ProjLife,K$20*(1+$U$61)^M7,0) -> 0 | W7: =IF(M7<=Debt_term,K$21,0) -> 0 | X7: =SUM(T7:W7)+SUM(BA7:BB7) -> 309 | Y7: =IF(AND(W$63=1,M7<=D$29,M7>0),MIN(IF(W$62=1,AU7,IF(W$62=2,AS7,AR7)),0),IF(W$62=1,AU7,IF(W$62=2,AS7,AR7))) -> 0 | Z7: =X7+Y7 -> 309 | AA7: =IF(M7<=ProjLife,(K$30+$K$33)*(1+$U$61)^M7,0) -> 0 | AB7: =IF(M7<=ProjLife,K$31*(1+$U$69)^M7,0) -> 1121.1892 | AC7: =IF(AND(M7<=D$67,M7<=U$64),K$35*(1+$D$68)^M7,0) -> 0 | AD7: =IF(AND(M7<=U$71,M7<=U$64,GHG>0),IF(AND(GHG_Baseline=0,M7<=$W$65),$D$39,$D$40),0)*$V$84*(1+$U$72)^M7*$U$59+$V$85*IF(M7<=$D$61,1,0)*(1+$D$62)^M7*$K$34*$U$59 -> 0 | AF7: =IF(M7=ProjLife,-K$27*(1+$U$62)^M7,0) -> 0 | AG7: =SUM(AA7:AF7) -> 1121.1892 | AH7: =AG7-X7 -> 812.18917 | AI7: =-Z7+AG7 -> 812.18917 | AK7: =IF(M7<=Debt_term,-PPMT(Debt_IR,M7,Debt_term,Debt_con),0) -> 0 | AL7: =AP6 -> 0 | AM7: =IF(M7<U$64,0,-AL7) -> 0 | AN7: =IF(M7<ProjLife,-D$26*AL7*IF(D24=lang_yes,0.5,1),-AL7) -> 0 | AO7: =IF(M7<ProjLife,IF(M7<=D$27,-D$25*Init_costs/D$27,0),-AL7) -> 0 | AP7: =AL7+IF(C$23=$X$81,AM7, IF(C$23=$X$82,AN7,AO7)) -> 0 | AQ7: =AH7+AJ7+AK7+IF(C$23=$X$81,AM7,IF(C$23=$X$82,AN7,AO7)) -> 812.18917 | AR7: =IF($W$61=1,D$21*AQ7,0) -> 0 | AS7: =IF(AR7<0,0,AR7) -> 0 | AT7: =AV6 -> 0 | AU7: =MAX(AR7+AT7,0) -> 0 | AV7: =AT7+AR7-AU7 -> 0 | AW7: =AH7+W7 -> 812.18917 | AX7: =P7-O$6 -> 812.18917 | AY7: =W7 -> 0 | AZ7: =IF(AY7<>0,(MAX(AW7,AX7)/AY7),"N/A") -> N/A | BA7: =IF($BA$2=0,0,IF(AND(M7<=ProjLife,MOD(M7,$BA$2)=0),K$25*(1+$U$62)^M7,0)) -> 0 | BB7: =IF($BB$2=0,0,IF(AND(M7<=ProjLife,MOD(M7,$BB$2)=0),K$26*(1+$U$62)^M7,0)) -> 0 | BC7: =IF(M7*$BA$2<=U$64,(IF(M7<=1,"",",")&TEXT(M7*$BA$2,"0"))," ") -> 10 | BD7: =IF(M7*$BB$2<=U$64,(IF(M7<=1,"",",")&TEXT(M7*$BB$2,"0"))," ") -> 0 | BE7: =AH7 -> 812.18917 | BF7: =AI7 -> 812.18917 | BG7: 72106 | BH7: 74106 | BI7: 76000
B8: =Language!C661 -> Vida do projeto | C8: =C67 -> ano | D8: 25 | G8: =Language!C1284 -> Sistema de produção de eletricidade | I8: =IF($K$14=0,"",K8/K$14) -> 0.93593933 | J8: =Currency -> € | K8: =IF(U58=2,IF(HideCodeCA_ProjectT=2,'Análise de Custos'!G11,'Análise de Custos'!G71),IF(V58=0,'Modelo Energético'!D1000,'Modelo Energético '!D987)) -> 5692.5 | M8: 2 | N8: =AH8 -> 847.76674 | O8: =AI8 -> 847.76674 | P8: =P7+O8 -> -4422.1691 | S8: 5692.5 | U8: =IF(M8<=ProjLife,K$19*(1+$U$62)^M8,0) -> 318.27 | V8: =IF(M8<=ProjLife,K$20*(1+$U$61)^M8,0) -> 0 | W8: =IF(M8<=Debt_term,K$21,0) -> 0 | X8: =SUM(T8:W8)+SUM(BA8:BB8) -> 318.27 | Y8: =IF(AND(W$63=1,M8<=D$29,M8>0),MIN(IF(W$62=1,AU8,IF(W$62=2,AS8,AR8)),0),IF(W$62=1,AU8,IF(W$62=2,AS8,AR8))) -> 0 | Z8: =X8+Y8 -> 318.27 | AA8: =IF(M8<=ProjLife,(K$30+$K$33)*(1+$U$61)^M8,0) -> 0 | AB8: =IF(M8<=ProjLife,K$31*(1+$U$69)^M8,0) -> 1166.0367 | AC8: =IF(AND(M8<=D$67,M8<=U$64),K$35*(1+$D$68)^M8,0) -> 0 | AD8: =IF(AND(M8<=U$71,M8<=U$64,GHG>0),IF(AND(GHG_Baseline=0,M8<=$W$65),$D$39,$D$40),0)*$V$84*(1+$U$72)^M8*$U$59+$V$85*IF(M8<=$D$61,1,0)*(1+$D$62)^M8*$K$34*$U$59 -> 0 | AF8: =IF(M8=ProjLife,-K$27*(1+$U$62)^M8,0) -> 0 | AG8: =SUM(AA8:AF8) -> 1166.0367 | AH8: =AG8-X8 -> 847.76674 | AI8: =-Z8+AG8 -> 847.76674 | AK8: =IF(M8<=Debt_term,-PPMT(Debt_IR,M8,Debt_term,Debt_con),0) -> 0 | AL8: =AP7 -> 0 | AM8: =IF(M8<U$64,0,-AL8) -> 0 | AN8: =IF(M8<ProjLife,-D$26*AL8,-AL8) -> 0 | AO8: =IF(M8<ProjLife,IF(M8<=D$27,-D$25*Init_costs/D$27,0),-AL8) -> 0 | AP8: =AL8+IF(C$23=$X$81,AM8, IF(C$23=$X$82,AN8,AO8)) -> 0 | AQ8: =AH8+AJ8+AK8+IF(C$23=$X$81,AM8,IF(C$23=$X$82,AN8,AO8)) -> 847.76674 | AR8: =IF($W$61=1,D$21*AQ8,0) -> 0 | AS8: =IF(AR8<0,0,AR8) -> 0 | AT8: =AV7 -> 0 | AU8: =MAX(AR8+AT8,0) -> 0 | AV8: =AT8+AR8-AU8 -> 0 | AW8: =AH8+W8 -> 847.76674 | AX8: =P8-O$6 -> 1659.9559 | AY8: =W8 -> 0 | AZ8: =IF(AY8<>0,(MAX(AW8,AX8)/AY8),"N/A") -> N/A | BA8: =IF($BA$2=0,0,IF(AND(M8<=ProjLife,MOD(M8,$BA$2)=0),K$25*(1+$U$62)^M8,0)) -> 0 | BB8: =IF($BB$2=0,0,IF(AND(M8<=ProjLife,MOD(M8,$BB$2)=0),K$26*(1+$U$62)^M8,0)) -> 0 | BC8: =IF(M8*$BA$2<=U$64,(IF(M8<=1,"",",")&TEXT(M8*$BA$2,"0"))," ") -> ,20 | BD8: =IF(M8*$BB$2<=U$64,(IF(M8<=1,"",",")&TEXT(M8*$BB$2,"0"))," ") -> ,0 | BE8: =AH8 -> 847.76674 | BF8: =AI8 -> 847.76674 | BG8: 72108 | BH8: 74108 | BI8: 76000
G9: =Language!C1283 -> Sistema de Aquecimento | I9: =IF($K$14=0,"",K9/K$14) -> 0 | J9: =Currency -> € | K9: =IF(U58=2,IF(HideCodeCA_ProjectT=2,IF(OR(Set_H=7,Set_H=8),'Análise de Custos'!G13,'Análise de Custos'!G12),'Análise de Custos'!G85),IF(V58=0,'Modelo Energético'!D1001,'Modelo Energético '!D988)) -> 0 | M9: 3 | N9: =AH9 -> 884.86011 | O9: =AI9 -> 884.86011 | P9: =P8+O9 -> -3537.309 | S9: 0 | U9: =IF(M9<=ProjLife,K$19*(1+$U$62)^M9,0) -> 327.8181 | V9: =IF(M9<=ProjLife,K$20*(1+$U$61)^M9,0) -> 0 | W9: =IF(M9<=Debt_term,K$21,0) -> 0 | X9: =SUM(T9:W9)+SUM(BA9:BB9) -> 327.8181 | Y9: =IF(AND(W$63=1,M9<=D$29,M9>0),MIN(IF(W$62=1,AU9,IF(W$62=2,AS9,AR9)),0),IF(W$62=1,AU9,IF(W$62=2,AS9,AR9))) -> 0 | Z9: =X9+Y9 -> 327.8181 | AA9: =IF(M9<=ProjLife,(K$30+$K$33)*(1+$U$61)^M9,0) -> 0 | AB9: =IF(M9<=ProjLife,K$31*(1+$U$69)^M9,0) -> 1212.6782 | AC9: =IF(AND(M9<=D$67,M9<=U$64),K$35*(1+$D$68)^M9,0) -> 0 | AD9: =IF(AND(M9<=U$71,M9<=U$64,GHG>0),IF(AND(GHG_Baseline=0,M9<=$W$65),$D$39,$D$40),0)*$V$84*(1+$U$72)^M9*$U$59+$V$85*IF(M9<=$D$61,1,0)*(1+$D$62)^M9*$K$34*$U$59 -> 0 | AF9: =IF(M9=ProjLife,-K$27*(1+$U$62)^M9,0) -> 0 | AG9: =SUM(AA9:AF9) -> 1212.6782 | AH9: =AG9-X9 -> 884.86011 | AI9: =-Z9+AG9 -> 884.86011 | AK9: =IF(M9<=Debt_term,-PPMT(Debt_IR,M9,Debt_term,Debt_con),0) -> 0 | AL9: =AP8 -> 0 | AM9: =IF(M9<U$64,0,-AL9) -> 0 | AN9: =IF(M9<ProjLife,-D$26*AL9,-AL9) -> 0 | AO9: =IF(M9<ProjLife,IF(M9<=D$27,-D$25*Init_costs/D$27,0),-AL9) -> 0 | AP9: =AL9+IF(C$23=$X$81,AM9, IF(C$23=$X$82,AN9,AO9)) -> 0 | AQ9: =AH9+AJ9+AK9+IF(C$23=$X$81,AM9,IF(C$23=$X$82,AN9,AO9)) -> 884.86011 | AR9: =IF($W$61=1,D$21*AQ9,0) -> 0 | AS9: =IF(AR9<0,0,AR9) -> 0 | AT9: =AV8 -> 0 | AU9: =MAX(AR9+AT9,0) -> 0 | AV9: =AT9+AR9-AU9 -> 0 | AW9: =AH9+W9 -> 884.86011 | AX9: =P9-O$6 -> 2544.816 | AY9: =W9 -> 0 | AZ9: =IF(AY9<>0,(MAX(AW9,AX9)/AY9),"N/A") -> N/A | BA9: =IF($BA$2=0,0,IF(AND(M9<=ProjLife,MOD(M9,$BA$2)=0),K$25*(1+$U$62)^M9,0)) -> 0 | BB9: =IF($BB$2=0,0,IF(AND(M9<=ProjLife,MOD(M9,$BB$2)=0),K$26*(1+$U$62)^M9,0)) -> 0 | BC9: =IF(M9*$BA$2<=U$64,(IF(M9<=1,"",",")&TEXT(M9*$BA$2,"0"))," ") | BD9: =IF(M9*$BB$2<=U$64,(IF(M9<=1,"",",")&TEXT(M9*$BB$2,"0"))," ") -> ,0 | BE9: =AH9 -> 884.86011 | BF9: =AI9 -> 884.86011 | BG9: 72100 | BH9: 74110 | BI9: 76000
